Workbook

Sheet Claim Sheet
A1: Task ID | B1: Force Claim Link | C1: Claimed By | D1: What Was Fixed | E1: AHT (mins) | F1: Claude Score | G1: Claude Feedback | H1: Claude Feedback | I1: Eval Tool | J1: Eval Score | K1: Date fixed | L1: Too Simple | M1: Task Completed | N1: Sent Back for Fixes
A2: 7a807980-2578-4689-9a0a-784ea3d33e86 | B2: =concat("https://www.tsip.ai/force/",A2) -> https://www.tsip.ai/force/7a807980-2578-4689-9a0a-784ea3d33e86 | C2: John W | D2: vlookup returning wrong value for JG europe, fixed | updated prompt | fixed output/input | E2: 70 | F2: generate in-task | G2: generate in-task | H2: generate in-task | I2: generate in-task | J2: generate in-task | K2: 46160 | L2: FALSE | M2: TRUE
A3: 44ac67cb-1bb6-4667-8756-b22d439ca759 | B3: =concat("https://www.tsip.ai/force/",A3) -> https://www.tsip.ai/force/44ac67cb-1bb6-4667-8756-b22d439ca759 | C3: Nadine M | D3: redid prompt, fixed formatting and hardcoding issues in workbook. refined rubric (no stacking) and now aligns with prompt and workbook. | E3: 50 | F3: generate in-task | G3: generate in-task | H3: generate in-task | I3: generate in-task | J3: generate in-task | K3: 46161 | L3: FALSE | M3: TRUE
A4: 65be1d3a-83f6-4e28-9f85-b3a419a84fd6 | B4: =concat("https://www.tsip.ai/force/",A4) -> https://www.tsip.ai/force/65be1d3a-83f6-4e28-9f85-b3a419a84fd6 | C4: Ariya S | D4: workbook fixes based on claude feedback; rubric: added model integration and minor fixes across other sections | E4: 35 | F4: generate in-task | G4: generate in-task | H4: generate in-task | I4: generate in-task | J4: generate in-task | K4: 46160 | M4: TRUE
A5: 2f1fdba6-a805-483f-810e-035773eb691d | B5: =concat("https://www.tsip.ai/force/",A5) -> https://www.tsip.ai/force/2f1fdba6-a805-483f-810e-035773eb691d | C5: Elliot S | D5: redid prompt, fixed claude issues, and rubric | E5: 65 | F5: generate in-task | G5: generate in-task | H5: generate in-task | I5: generate in-task | J5: generate in-task | K5: 46160 | L5: FALSE | M5: TRUE
A6: 295e3612-cb62-4eaf-b87a-96708f62d7c2 | B6: =concat("https://www.tsip.ai/force/",A6) -> https://www.tsip.ai/force/295e3612-cb62-4eaf-b87a-96708f62d7c2 | C6: John W | D6: workbook fixes, prompt edit, created model integration + output validation | E6: 70 | F6: generate in-task | G6: generate in-task | H6: generate in-task | I6: generate in-task | J6: generate in-task | K6: 46160 | L6: FALSE | M6: TRUE
A7: 16e3ef61-3f9c-4ac7-b32f-4823bbc356f7 | B7: =concat("https://www.tsip.ai/force/",A7) -> https://www.tsip.ai/force/16e3ef61-3f9c-4ac7-b32f-4823bbc356f7 | C7: Ariya S | D7: workbook, prompt, and rubric small fixes from claude feedback | E7: 50 | F7: generate in-task | G7: generate in-task | H7: generate in-task | I7: generate in-task | J7: generate in-task | K7: 46160 | L7: FALSE | M7: TRUE
A8: aad52b58-4443-48b3-918d-98c1742f1df1 | B8: =concat("https://www.tsip.ai/force/",A8) -> https://www.tsip.ai/force/aad52b58-4443-48b3-918d-98c1742f1df1 | C8: Ariya S | D8: fixes to workbook based on claude feedback, rubric fixes resulting from that | E8: 70 | F8: generate in-task | G8: generate in-task | H8: generate in-task | I8: generate in-task | J8: generate in-task | K8: 46160 | L8: FALSE | M8: TRUE
A9: 8a831111-f767-4ed0-95e2-7f69615d0959 | B9: =concat("https://www.tsip.ai/force/",A9) -> https://www.tsip.ai/force/8a831111-f767-4ed0-95e2-7f69615d0959 | C9: Diogo P | D9: Major changes to input and output workbook. Both had linked cells to blank cells. Part of prompt didn't correspond to what was happening in the model. | E9: 100 | F9: generate in-task | G9: generate in-task | H9: generate in-task | I9: generate in-task | J9: generate in-task | K9: 46162 | L9: FALSE | M9: TRUE
A10: bc059c29-6c77-45f1-8172-fdbe6d1c4d42 | B10: =concat("https://www.tsip.ai/force/",A10) -> https://www.tsip.ai/force/bc059c29-6c77-45f1-8172-fdbe6d1c4d42 | C10: Antonio V | D10: Required significant work throughout | E10: 240 | F10: generate in-task | G10: generate in-task | H10: generate in-task | I10: generate in-task | J10: generate in-task | K10: 46160 | L10: FALSE | M10: TRUE
A11: f5f33709-656b-4730-bf27-54d886510a8a | B11: =concat("https://www.tsip.ai/force/",A11) -> https://www.tsip.ai/force/f5f33709-656b-4730-bf27-54d886510a8a | C11: Francisco C | D11: Output: Typo on FCF calculation with change in invested capital as a positive. This was corrected but there was no impact on valuation | Input: Removed unatural progression - Summary valuation already had the output from the task | Prompt: Minor changes | Rubric: Corrected output and perturbation sections; Removed duplicated and out of scope | E11: 70 | F11: generate in-task | G11: generate in-task | H11: generate in-task | I11: generate in-task | J11: generate in-task | K11: 46160 | L11: FALSE | M11: TRUE
A12: bf86fd2e-3e2d-4d0f-a173-db297660e072 | B12: =concat("https://www.tsip.ai/force/",A12) -> https://www.tsip.ai/force/bf86fd2e-3e2d-4d0f-a173-db297660e072 | C12: Francisco C | D12: Input: Removed hardcoded inputs on BS that were not natural progression | Output: Simplified assumption on goodwill amortization (was already calculated in the model); Few minor edits | Prompt: Removed incorrect hardcode for goodwill amortization; Simplified grammar | Rubric: Corrected wrong output validation criterion; Removed out of scope | E12: 55 | F12: generate in-task | G12: generate in-task | H12: generate in-task | I12: generate in-task | J12: generate in-task | K12: 46160 | L12: FALSE | M12: TRUE
A13: 5452a654-d533-46eb-b47f-1357a47eeca6 | B13: =concat("https://www.tsip.ai/force/",A13) -> https://www.tsip.ai/force/5452a654-d533-46eb-b47f-1357a47eeca6 | C13: Elliot S | D13: fixed rubric + logical progression of input to output by removing dependencies | E13: 60 | F13: generate in-task | G13: generate in-task | H13: generate in-task | I13: generate in-task | J13: generate in-task | K13: 46161 | L13: FALSE | M13: TRUE
A14: 91f0eaf1-2d4b-41ab-a262-8453686cea5a | B14: =concat("https://www.tsip.ai/force/",A14) -> https://www.tsip.ai/force/91f0eaf1-2d4b-41ab-a262-8453686cea5a | C14: Pragyat A | D14: Minor changes in prompt, model and rubrics | E14: 65 | F14: generate in-task | G14: generate in-task | H14: generate in-task | I14: generate in-task | J14: generate in-task | K14: 46163 | L14: FALSE | M14: TRUE
A15: cf573523-a0a1-40fb-ad40-b6b41b27ae3d | B15: =concat("https://www.tsip.ai/force/",A15) -> https://www.tsip.ai/force/cf573523-a0a1-40fb-ad40-b6b41b27ae3d | C15: Pragyat A | D15: Prompt, Rubric and output file. But their is issue in Input file too. regarding true values in check. | E15: 63 | F15: generate in-task | G15: generate in-task | H15: generate in-task | I15: generate in-task | J15: generate in-task | K15: 46163 | L15: FALSE | M15: TRUE
A16: e66fa748-66f4-4f25-b521-834f0ba81ff4 | B16: =concat("https://www.tsip.ai/force/",A16) -> https://www.tsip.ai/force/e66fa748-66f4-4f25-b521-834f0ba81ff4 | C16: Ariya S | D16: workbook fixes based on claude feedback;several prompt rewrites/reorganization; many rubric changes | E16: 70 | F16: generate in-task | G16: generate in-task | H16: generate in-task | I16: generate in-task | J16: generate in-task | K16: 46160 | L16: FALSE | M16: TRUE
... A18: 90bbed8a-b185-4f3d-96d0-b1527582ae9b | B18: =concat("https://www.tsip.ai/force/",A18) -> https://www.tsip.ai/force/90bbed8a-b185-4f3d-96d0-b1527582ae9b | C18: Ariya S | D18: workbook, prompt, and rubric fixes based on claude | E18: 50 | F18: generate in-task | G18: generate in-task | H18: generate in-task | I18: generate in-task | J18: generate in-task | K18: 46160 | L18: FALSE | M18: TRUE
A19: 0d9d675e-f3aa-4291-9183-9828fc1cca68 | B19: =concat("https://www.tsip.ai/force/",A19) -> https://www.tsip.ai/force/0d9d675e-f3aa-4291-9183-9828fc1cca68 | C19: Ariya S | D19: rubric to be regen (old format) | F19: generate in-task | G19: generate in-task | H19: generate in-task | I19: generate in-task | J19: generate in-task | L19: FALSE | M19: FALSE
A20: 74071b8e-e1a7-4815-9604-056c66f53fcd | B20: =concat("https://www.tsip.ai/force/",A20) -> https://www.tsip.ai/force/74071b8e-e1a7-4815-9604-056c66f53fcd | C20: Ariya S | D20: rubric fixes | E20: 45 | F20: generate in-task | G20: generate in-task | H20: generate in-task | I20: generate in-task | J20: generate in-task | K20: 46160 | L20: FALSE | M20: TRUE
A21: 5329fcc2-0bb8-4eaf-b563-54b64adf97da | B21: 2d607b4b-a8a1-41eb-a290-966ef66a1a8e | C21: Ava Z | D21: Workbook: fixed incorrectly locked cells, | F21: generate in-task | G21: generate in-task | H21: generate in-task | I21: generate in-task | J21: generate in-task | L21: FALSE | M21: FALSE
A22: 7e959336-04ed-49e4-bfef-665c0782448c | B22: =concat("https://www.tsip.ai/force/",A22) -> https://www.tsip.ai/force/7e959336-04ed-49e4-bfef-665c0782448c | C22: Ariya S | D22: fixes to workbook and rubric based on claude feedback | E22: 60 | F22: generate in-task | G22: generate in-task | H22: generate in-task | I22: generate in-task | J22: generate in-task | K22: 46160 | L22: FALSE | M22: TRUE
A23: a2cea33d-12d0-44ca-a889-a81ace87c570 | B23: =concat("https://www.tsip.ai/force/",A23) -> https://www.tsip.ai/force/a2cea33d-12d0-44ca-a889-a81ace87c570 | C23: Pragyat A | D23: Changes in Prompt, Rubric and Output file. | E23: 53 | F23: generate in-task | G23: generate in-task | H23: generate in-task | I23: generate in-task | J23: generate in-task | K23: 46163 | L23: FALSE | M23: TRUE
A24: e12b11cd-c4b1-416a-89cc-76419d8c598a | B24: =concat("https://www.tsip.ai/force/",A24) -> https://www.tsip.ai/force/e12b11cd-c4b1-416a-89cc-76419d8c598a | C24: Jalaj G | D24: prompt - minor changes workbook output - changed a few labels - added historical missing calcs rubric - unstacked fc criteria - removed out of scope criteria - added presentation criteria | E24: 60 | F24: generate in-task | G24: generate in-task | H24: generate in-task | I24: generate in-task | J24: generate in-task | K24: 46162 | L24: FALSE | M24: TRUE
A25: 62e771dc-72a6-41f0-9a53-41f396bef554 | B25: =concat("https://www.tsip.ai/force/",A25) -> https://www.tsip.ai/force/62e771dc-72a6-41f0-9a53-41f396bef554 | C25: Jalaj G | D25: prompt - added missing data - added missing calculation methodology - improved language throughout workbook output - several changes in labels and formulae - standardised formatting rubric - unstacked many criteria - added mi criteria - updated values of some ov and pt criteria - added presentation criteria | E25: 55 | F25: generate in-task | G25: generate in-task | H25: generate in-task | I25: generate in-task | J25: generate in-task | K25: 46161 | L25: FALSE | M25: TRUE
A26: 76d1c9fa-dcc0-4ae6-8d8a-54b7a3af800a | B26: =concat("https://www.tsip.ai/force/",A26) -> https://www.tsip.ai/force/76d1c9fa-dcc0-4ae6-8d8a-54b7a3af800a | C26: Jalaj G | D26: prompt - aligned analysis with actual workbook - entered missing hardcoded data - improved language throughout workbook output - applied consistent formatting rubric - unstacked many criteria - removed out of scope and superfluous criteria - added presentation criteria | E26: 65 | F26: generate in-task | G26: generate in-task | H26: generate in-task | I26: generate in-task | J26: generate in-task | K26: 46161 | L26: FALSE | M26: TRUE
A27: de0b9b68-3655-4ad8-b299-716ccea058fa | B27: =concat("https://www.tsip.ai/force/",A27) -> https://www.tsip.ai/force/de0b9b68-3655-4ad8-b299-716ccea058fa | C27: Jalaj G | D27: prompt - minor changes workbook output - updated formatting rubric - unstacked fc criteria - added mi criteria - removed out of scope criteria - added presentation criteria | E27: 55 | F27: generate in-task | G27: generate in-task | H27: generate in-task | I27: generate in-task | J27: generate in-task | K27: 46162 | L27: FALSE | M27: TRUE
A28: 9b77ed14-955e-476d-b455-9b9b4d7e0441 | B28: =concat("https://www.tsip.ai/force/",A28) -> https://www.tsip.ai/force/9b77ed14-955e-476d-b455-9b9b4d7e0441 | C28: Jalaj G | D28: prompt - rewrote completely - added missing inputs - added missing direction to delete tab workbook output - updated formatting - removed some hardcodes rubric - unstacked fc criteria - added mi criteria - corrected values of some ov and pt criteria - removed out of scope criteria - added presentation criteria | E28: 50 | F28: generate in-task | G28: generate in-task | H28: generate in-task | I28: generate in-task | J28: generate in-task | K28: 46162 | L28: FALSE | M28: TRUE
A29: 98424092-bac5-4483-9f0f-dcfa1df92519 | B29: =concat("https://www.tsip.ai/force/",A29) -> https://www.tsip.ai/force/98424092-bac5-4483-9f0f-dcfa1df92519 | C29: Jalaj G | D29: prompt - added missing calculation methodology - minor changes workbook output - changed formula in row 105 rubric - unstacked fc criteria - added mi criteria - added pt criteria - removed out of scope criteria - added presentation criteria | E29: 90 | F29: generate in-task | G29: generate in-task | H29: generate in-task | I29: generate in-task | J29: generate in-task | K29: 46161 | L29: FALSE | M29: TRUE
A30: 36e31d9a-2788-4c0b-816a-22f66623d6fd | B30: =concat("https://www.tsip.ai/force/",A30) -> https://www.tsip.ai/force/36e31d9a-2788-4c0b-816a-22f66623d6fd | C30: Jalaj G | D30: prompt - minor changes workbook output - changed formatting at a few places - corrected wrong linkages and formulae rubric - unstacked fc criteria - added mi criteria - corrected values of some ov and pt criteria - removed out of scope criteria - added presentation criteria | E30: 50 | F30: generate in-task | G30: generate in-task | H30: generate in-task | I30: generate in-task | J30: generate in-task | K30: 46162 | L30: FALSE | M30: TRUE
A31: 0a88b778-e4f3-418f-a39c-31aa94b7afa0 | B31: =concat("https://www.tsip.ai/force/",A31) -> https://www.tsip.ai/force/0a88b778-e4f3-418f-a39c-31aa94b7afa0 | C31: Jeff Z | D31: Model: Included SAP in all comps outputs (previously incorrect), renamed tab correctly Prompt: Tweaked prompt wording Rubric: Unstacked Pitfalls section, unstacked Presentation section, updated Perturbation to exact values, corrected rubric items for Output Validation section (for updated output workbook), standardized rubric for Model Integration section, updated scoring and labeling for the Formula Correctness section | E31: 45 | F31: 3 | G31: Run tsip-claude-feedback-ed0c7447-3724-4cda-9c27-4e1d044607af Completed May 18, 10:02 PM Major Takeaways The output workbook successfully builds the Comparable Company Analysis (CCA) tab from scratch and populates the Formatted Charts tab with correct cross-tab links. All six companies are present with correct company information, all financial metrics link dynamically to the respective Formatted tabs, EV/Revenue and EV/ARR formulas are correct (EV÷Revenue, EV÷ARR), the Implied Valuation section correctly multiplies CCA statistics by Snowflake's revenue/ARR, number formatting is professional (accounting format with $, 0.0"x" for multiples, bold blue section headers), and no error values exist in either key tab. However, there is a meaningful implementation error: the CCA summary statistics (C15:D19) use the range L6:L9/M6:M9 covering only four companies—Oracle, MongoDB, Atlassian, Autodesk—silently excluding SAP SE (row 10) from the peer set. The prompt explicitly says to exclude only Snowflake. The Formatted Charts median correctly uses MEDIAN(C5:C9), which includes all five peers (SAP SE included), creating an internal inconsistency within the output workbook itself. The task-specific rubric is internally inconsistent as a consequence: its formula correctness criteria state "computed from the peer set, excluding Snowflake" (implying all five peers), but its output validation expected values were derived from the four-company erroneous calculation, so a model producing the truly correct output would fail output validation. Major Errors CCA summary statistics use wrong peer set (L6:L9 instead of L6:L10): SAP SE (row 10) is excluded from MAX, PERCENTILE, MEDIAN, and MIN formulas in cells C15:D19. This contradicts the prompt instruction to use "only the peer set (Snowflake should be excluded)." The prompt lists six companies, five of which should form the peer set; only Snowflake should be excluded from the statistics. Internal inconsistency between CCA and Formatted Charts: The Formatted Charts median (C11/D11) correctly uses =MEDIAN(C5:C9) covering all five peers including SAP SE (producing EV/Revenue median of 8.46x and EV/ARR median of 10.02x), while the CCA stats use only four peers (EV/Revenue median 9.28x). The median values in these two sections do not agree for EV/Revenue. Rubric internal inconsistency: The formula correctness criteria (e.g., criteria IDs edadd311, 17d30dc2, 832aa785, 3029eaa6, 4a81e33f, 01712254) assert "computed exclusively from the peer set, excluding Snowflake," but the rubric's output validation expected values (9.28x median EV/Revenue; 19171.86 implied median EV/Revenue) are derived from the four-company set that excludes SAP SE. A model that correctly includes SAP SE in the CCA peer set would pass formula correctness but fail output validation; a model that replicates the error would fail formula correctness but pass output validation. Critical Errors SAP SE excluded from CCA summary statistics: The formulas =MAX(L6:L9), =PERCENTILE(L6:L9, 0.75), =MEDIAN(L6:L9), etc., should extend to L6:L10 to include SAP SE. This causes all five CCA summary statistics and all ten implied valuation values to be computed from the wrong peer set. The same four-range error is in the corresponding M6:M9 formulas for EV/ARR. This is the single change that moves the output from a "4" to a "3"—the analysis logic is structurally sound but quantitatively wrong relative to the prompt specification. Rubric output validation values calibrated to the erroneous output: Because the rubric's expected values (56484.83 max implied EV/ARR; 19171.86 median implied EV/Revenue; 9.28x CCA median EV/Revenue; 22065.76 75th-pct implied EV/Revenue; 17.87x 75th-pct EV/ARR) all match the four-peer calculation, a corrected output with SAP SE included would show different values (e.g., CCA median EV/Revenue ≈ 8.46x, implied median EV/Revenue ≈ 17,476) and fail output validation. This degraded rubric reliability prevents clean training signal. | H31: generate in-task | I31: generate in-task | J31: generate in-task | K31: 46163 | L31: FALSE | M31: TRUE
A32: d83d3eb8-99ca-4de7-9f98-991a81ce1147 | B32: =concat("https://www.tsip.ai/force/",A32) -> https://www.tsip.ai/force/d83d3eb8-99ca-4de7-9f98-991a81ce1147 | C32: Jalaj G | D32: feedback done, to complete on 5/21 | F32: generate in-task | G32: generate in-task | H32: generate in-task | I32: generate in-task | J32: generate in-task | L32: FALSE | M32: FALSE
A33: 2d607b4b-a8a1-41eb-a290-966ef66a1a8e | B33: =concat("https://www.tsip.ai/force/",A33) -> https://www.tsip.ai/force/2d607b4b-a8a1-41eb-a290-966ef66a1a8e | C33: Francisco C | D33: Output: Typo on one of the hardcodes for covid downside; removed the covenant and summary section to make the task more natural | Prompt: Minor adjustments | Rubric: Corrected most of validation and perturbation; Removed out of scope | E33: 65 | F33: generate in-task | G33: generate in-task | H33: generate in-task | I33: generate in-task | J33: generate in-task | K33: 46161 | L33: FALSE | M33: TRUE
A34: 45417e1e-19aa-4c6b-83e6-cd694026420d | B34: =concat("https://www.tsip.ai/force/",A34) -> https://www.tsip.ai/force/45417e1e-19aa-4c6b-83e6-cd694026420d | C34: Megan S | D34: Rubric did not match scope of output workbook, prompt rewritten + input workbook had to be recontextualized since it had hardcodes from the output workbook in it | E34: 90 | F34: generate in-task | G34: generate in-task | H34: generate in-task | I34: generate in-task | J34: generate in-task | K34: 46162 | L34: FALSE | M34: TRUE
A35: 108dc013-5e4c-4773-8379-c873684fe7ca | B35: =concat("https://www.tsip.ai/force/",A35) -> https://www.tsip.ai/force/108dc013-5e4c-4773-8379-c873684fe7ca | C35: Ava Z | D35: output workbook: fixed inconsistent decimals, corrected Other Rec calculation; fine turned prompt; rubric: revised formula checks | E35: 90 | F35: generate in-task | G35: generate in-task | H35: generate in-task | I35: generate in-task | J35: generate in-task | K35: 46161 | L35: FALSE | M35: TRUE
A36: bb995691-d4c3-4929-82e0-514c944b369a | B36: =concat("https://www.tsip.ai/force/",A36) -> https://www.tsip.ai/force/bb995691-d4c3-4929-82e0-514c944b369a | C36: Pragyat A | D36: Input, Prompt and rubric change | E36: 50 | F36: generate in-task | G36: generate in-task | H36: generate in-task | I36: generate in-task | J36: generate in-task | K36: 46163 | L36: FALSE | M36: TRUE
A37: ea0c47ab-e763-421c-b9cd-9d61c1e1c880 | B37: =concat("https://www.tsip.ai/force/",A37) -> https://www.tsip.ai/force/ea0c47ab-e763-421c-b9cd-9d61c1e1c880 | C37: Francisco C | D37: Input: Input was missing historical financials as mentioned by prompt; Corrected for natural progression (TV section had the outputs already pasted) | Output: Several typos across formulas, discounted cashflows missed the initial year, terminal value across the 2 methodologies was not discounted; Minor formatting typos | Prompt: Correction for alignment with new output | Rubric: Missing perturbation section, output section was mostly wrong; Other minor adjustements | E37: 90 | F37: generate in-task | G37: generate in-task | H37: generate in-task | I37: generate in-task | J37: generate in-task | K37: 46161 | L37: FALSE | M37: TRUE
A38: c3e5538c-d952-4ac9-9a99-7069e6438856 | B38: =concat("https://www.tsip.ai/force/",A38) -> https://www.tsip.ai/force/c3e5538c-d952-4ac9-9a99-7069e6438856 | C38: Jalaj G | D38: prompt - aligned all model values with prompt - added missing calculation methodology - improved language throughout workbook output - increased column widths - standardised formatting rubric - unstacked many criteria - added mi criteria - added pt criteria - added presentation criteria | E38: 80 | F38: generate in-task | G38: generate in-task | H38: generate in-task | I38: generate in-task | J38: generate in-task | K38: 46161 | L38: FALSE | M38: TRUE
A39: b66e0bf3-d738-4297-83dc-c19c545cf74c | B39: =concat("https://www.tsip.ai/force/",A39) -> https://www.tsip.ai/force/b66e0bf3-d738-4297-83dc-c19c545cf74c | C39: Jalaj G | D39: prompt - aligned all model values with prompt - removed unnecessary clutter - improved language throughout workbook output - aligned all model values with prompt - completed missing formulae - corrected wrong formulae - removed unnecessary clutter - simplified formatting a bit - standardised formatting rubric - unstacked many criteria - added mi criteria - corrected values of some ov and pt criteria - added presentation criteria | E39: 90 | F39: generate in-task | G39: generate in-task | H39: generate in-task | I39: generate in-task | J39: generate in-task | K39: 46161 | L39: FALSE | M39: TRUE
A40: 058b4565-71f7-4ebc-a015-b8c266077015 | B40: =concat("https://www.tsip.ai/force/",A40) -> https://www.tsip.ai/force/058b4565-71f7-4ebc-a015-b8c266077015 | C40: Spencer H | D40: workbook: addressed claude feedback prompt: had many repetitive hardcodes that were redundant; rewriting the logic for most lines since it is not explaining things correctly; didnt say any margin hardcodes rubric: fixed formula stacking; fixed perturbation issues | E40: 60 | F40: generate in-task | G40: generate in-task | H40: generate in-task | I40: generate in-task | J40: generate in-task | K40: 46161 | L40: FALSE | M40: TRUE
A41: 041e6f7f-5946-4fbd-8fb3-44b05aa05bfc | B41: =concat("https://www.tsip.ai/force/",A41) -> https://www.tsip.ai/force/041e6f7f-5946-4fbd-8fb3-44b05aa05bfc | C41: Antonio V | D41: Had to rebuild the whole exercise | E41: 120 | F41: generate in-task | G41: generate in-task | H41: generate in-task | I41: generate in-task | J41: generate in-task | K41: 46161 | L41: FALSE | M41: TRUE
A42: f30e6ae0-df43-4046-bcf8-a3f33b59aeb9 | B42: =concat("https://www.tsip.ai/force/",A42) -> https://www.tsip.ai/force/f30e6ae0-df43-4046-bcf8-a3f33b59aeb9 | C42: Antonio V | D42: Significant work required to get the task in shape | E42: 120 | F42: generate in-task | G42: generate in-task | H42: generate in-task | I42: generate in-task | J42: generate in-task | K42: 46161 | L42: FALSE | M42: TRUE
A43: be626304-e5bb-4b2f-9ce0-8b4cd83bfbf3 | B43: =concat("https://www.tsip.ai/force/",A43) -> https://www.tsip.ai/force/be626304-e5bb-4b2f-9ce0-8b4cd83bfbf3 | C43: Elliot S | D43: rewrote the prompt and fixed claude errors, also fixed criteria across rubric | E43: 75 | F43: generate in-task | G43: generate in-task | H43: generate in-task | I43: generate in-task | J43: generate in-task | K43: 46160 | L43: FALSE | M43: TRUE
A44: bf4c8c03-081b-4fc0-898a-fe986f5af59f | B44: =concat("https://www.tsip.ai/force/",A44) -> https://www.tsip.ai/force/bf4c8c03-081b-4fc0-898a-fe986f5af59f | C44: Spencer H | D44: fixed the prompt structure which was adding some things to incorrect sections; rewriting; fixed incorrect hardcodes; rewriting this prompt; fixed claude's comments on prompt/workbook discrepencies; removed formula testing outputs; perturbation items were slightly off | E44: 50 | F44: generate in-task | G44: generate in-task | H44: generate in-task | I44: generate in-task | J44: generate in-task | K44: 46163 | L44: FALSE | M44: TRUE
... A50: 23a19259-e3c4-4823-bb05-ed7821221264 | B50: =concat("https://www.tsip.ai/force/",A50) -> https://www.tsip.ai/force/23a19259-e3c4-4823-bb05-ed7821221264 | C50: Diogo P | D50: Workbook had significant issues. Input workbook had already the output of the output workbook hardcoded. | E50: 100 | F50: generate in-task | G50: generate in-task | H50: generate in-task | I50: generate in-task | J50: generate in-task | K50: 46161 | L50: FALSE | M50: TRUE
A51: d295bf7f-ae0d-4757-af49-90df5a265211 | B51: =concat("https://www.tsip.ai/force/",A51) -> https://www.tsip.ai/force/d295bf7f-ae0d-4757-af49-90df5a265211 | C51: Caitlin R | D51: Minor feedback on the rubric. no changes to prompt | E51: 23 | F51: generate in-task | G51: generate in-task | H51: generate in-task | I51: generate in-task | J51: generate in-task | L51: FALSE | M51: FALSE
A52: a6dbab57-b9a1-4329-8bed-969535af74bd | B52: =concat("https://www.tsip.ai/force/",A52) -> https://www.tsip.ai/force/a6dbab57-b9a1-4329-8bed-969535af74bd | C52: Elliot S | D52: rewrote prompt and fixed claude issues | E52: 60 | F52: generate in-task | G52: generate in-task | H52: generate in-task | I52: generate in-task | J52: generate in-task | K52: 46161 | L52: FALSE | M52: TRUE
A53: 3784aa9e-504c-4e54-b985-7a5cb8d1933a | B53: =concat("https://www.tsip.ai/force/",A53) -> https://www.tsip.ai/force/3784aa9e-504c-4e54-b985-7a5cb8d1933a | C53: Elliot S | D53: old rubric + way to simple regardless just pulling numbers and simple P&L line item calcs woukd take 10 min for analyst | E53: 10 | F53: generate in-task | G53: generate in-task | H53: generate in-task | I53: generate in-task | J53: generate in-task | K53: 46161 | L53: TRUE | M53: TRUE
A54: 8d6779ec-df84-4fcb-8d42-17100bec979c | B54: =concat("https://www.tsip.ai/force/",A54) -> https://www.tsip.ai/force/8d6779ec-df84-4fcb-8d42-17100bec979c | C54: Elliot S | D54: fixed prompt/workbook, rubric | E54: 85 | F54: generate in-task | G54: generate in-task | H54: generate in-task | I54: generate in-task | J54: generate in-task | K54: 46163 | L54: FALSE | M54: TRUE
A55: d5f5c3cc-bec3-457a-8f25-39e33cce876f | B55: =concat("https://www.tsip.ai/force/",A55) -> https://www.tsip.ai/force/d5f5c3cc-bec3-457a-8f25-39e33cce876f | C55: Nadine M | D55: Rewrote prompt and fixed Claude issues. Also worked on rubric to get rid of stacking | E55: 35 | F55: generate in-task | G55: generate in-task | H55: generate in-task | I55: generate in-task | J55: generate in-task | K55: 46162 | L55: FALSE | M55: TRUE
A56: b63e33e0-f4e9-4802-9908-2ce8ca7c074e | B56: =concat("https://www.tsip.ai/force/",A56) -> https://www.tsip.ai/force/b63e33e0-f4e9-4802-9908-2ce8ca7c074e | C56: Nimisha M | F56: generate in-task | G56: generate in-task | H56: generate in-task | I56: generate in-task | J56: generate in-task | L56: FALSE | M56: FALSE
A57: 6be2cad2-d839-433a-837f-ead416902d88 | B57: =concat("https://www.tsip.ai/force/",A57) -> https://www.tsip.ai/force/6be2cad2-d839-433a-837f-ead416902d88 | C57: Nadine M | D57: Rewrote prompt with more details and logical flow. Fixed formatting and formulas in Workbook. Rubric: got rid of stacking, fixed output validation figures. | E57: 40 | F57: generate in-task | G57: generate in-task | H57: generate in-task | I57: generate in-task | J57: generate in-task | K57: 46163 | L57: FALSE | M57: TRUE
A58: 4b3370f6-b062-4b42-a9c0-70edb4a9f649 | B58: =concat("https://www.tsip.ai/force/",A58) -> https://www.tsip.ai/force/4b3370f6-b062-4b42-a9c0-70edb4a9f649 | D58: old rubric | F58: generate in-task | G58: generate in-task | H58: generate in-task | I58: generate in-task | J58: generate in-task | L58: FALSE | M58: FALSE
A59: 8506d678-28b4-4dc3-8d48-e847e8bb11f0 | B59: =concat("https://www.tsip.ai/force/",A59) -> https://www.tsip.ai/force/8506d678-28b4-4dc3-8d48-e847e8bb11f0 | C59: Spencer H | D59: addressed claude's comments; added formatting in the prompt and made a few other small tweaks; fixed perturbation errors; removed formula items out of scope; updated workbook format inconsistencies | E59: 40 | F59: generate in-task | G59: generate in-task | H59: generate in-task | I59: generate in-task | J59: generate in-task | K59: 46161 | L59: FALSE | M59: TRUE
A60: b6c24819-eb15-41e3-9e85-e1ec3944a1f3 | B60: =concat("https://www.tsip.ai/force/",A60) -> https://www.tsip.ai/force/b6c24819-eb15-41e3-9e85-e1ec3944a1f3 | C60: Spencer H | D60: making slight tweaks to the prompt since it is in decent shape - missing a few hardcodes and things not stated in other parts of the model that it assumed was being pulled in; had to rewrite parts of this; formula section was testing hardcodes; removed formula stacking; all oututs out of scope | E60: 45 | F60: generate in-task | G60: generate in-task | H60: generate in-task | I60: generate in-task | J60: generate in-task | K60: 46163 | L60: FALSE | M60: TRUE
A61: 3068d001-beac-4e53-ba25-1029c5b31b0a | B61: =concat("https://www.tsip.ai/force/",A61) -> https://www.tsip.ai/force/3068d001-beac-4e53-ba25-1029c5b31b0a | C61: Francisco C | D61: General: Critical mistake on NOPAT calculation. NOPAT should consider taxes on EBIT, not on EBT. | Output: Corrected NOPAT taxes calculation. Adjusted free cash flows to Unlevered free cashflows | Prompt: Rewording, changed nomenclature for Unlevered free cash flow so that NOPAT is the basis for firm valuation | Rubric: Corrected validation and perturbation to accomodate the corrections made | E61: 60 | F61: generate in-task | G61: generate in-task | H61: generate in-task | I61: generate in-task | J61: generate in-task | K61: 46160 | L61: FALSE | M61: TRUE
A62: 4afa716c-2632-44e3-a046-1d3cafde99ad | B62: =concat("https://www.tsip.ai/force/",A62) -> https://www.tsip.ai/force/4afa716c-2632-44e3-a046-1d3cafde99ad | C62: Jared M | D62: illogical build - adding in a CF into an already fully built out model with valuations... will revisit to build a different task | F62: generate in-task | G62: generate in-task | H62: generate in-task | I62: generate in-task | J62: generate in-task | L62: FALSE | M62: FALSE
A63: 9ac50b6a-b3cc-4e39-80db-26efc527a7df | B63: =concat("https://www.tsip.ai/force/",A63) -> https://www.tsip.ai/force/9ac50b6a-b3cc-4e39-80db-26efc527a7df | C63: Jared M | D63: simple task but illogical input state with the Int Expense figures hardcoded when this schedule drives the calculations; rework on the prompt and rubric | E63: 70 | F63: generate in-task | G63: generate in-task | H63: generate in-task | I63: generate in-task | J63: generate in-task | K63: 46161 | L63: FALSE | M63: TRUE
A64: dd5dd87a-520c-4890-ae75-645ec85a25b0 | B64: =concat("https://www.tsip.ai/force/",A64) -> https://www.tsip.ai/force/dd5dd87a-520c-4890-ae75-645ec85a25b0 | C64: Diogo P | D64: Had to rework all the rubric as it had missing sections. Also changes to prompt and minor to model. | E64: 80 | F64: generate in-task | G64: generate in-task | H64: generate in-task | I64: generate in-task | J64: generate in-task | K64: 46161 | L64: FALSE | M64: TRUE
A65: 9050883a-2ded-43ff-bdef-b111598bfe77 | B65: =concat("https://www.tsip.ai/force/",A65) -> https://www.tsip.ai/force/9050883a-2ded-43ff-bdef-b111598bfe77 | F65: generate in-task | G65: generate in-task | H65: generate in-task | I65: generate in-task | J65: generate in-task | L65: FALSE | M65: FALSE
A66: 95e47754-95d9-43e7-b7ac-b7182ed26a1f | B66: =concat("https://www.tsip.ai/force/",A66) -> https://www.tsip.ai/force/95e47754-95d9-43e7-b7ac-b7182ed26a1f | C66: Spencer H | D66: redoing the prompt, it is too ambiguous; removed formula stacking and out of scope rubric items | E66: 50 | F66: generate in-task | G66: generate in-task | H66: generate in-task | I66: generate in-task | J66: generate in-task | K66: 46162 | L66: FALSE | M66: TRUE
A67: 2a848255-51e8-41af-8bf6-33720f84f8f3 | B67: =concat("https://www.tsip.ai/force/",A67) -> https://www.tsip.ai/force/2a848255-51e8-41af-8bf6-33720f84f8f3 | C67: Diego P | D67: migrated from 5/17 sheet | E67: 65 | F67: generate in-task | G67: generate in-task | H67: generate in-task | I67: generate in-task | J67: generate in-task | K67: 46160 | L67: FALSE | M67: TRUE
A68: 1c826292-7474-41b0-b55c-c5c3026881e9 | B68: =concat("https://www.tsip.ai/force/",A68) -> https://www.tsip.ai/force/1c826292-7474-41b0-b55c-c5c3026881e9 | C68: Diogo P | D68: Changes to prompt and rubric. Wrong output workbook submitted and that's why it had errors. Issue has been solved | E68: 60 | F68: generate in-task | G68: generate in-task | H68: generate in-task | I68: generate in-task | J68: generate in-task | K68: 46160 | L68: FALSE | M68: TRUE
A69: 654770a8-7e2c-447f-a770-57a6b05f1683 | B69: =concat("https://www.tsip.ai/force/",A69) -> https://www.tsip.ai/force/654770a8-7e2c-447f-a770-57a6b05f1683 | C69: Ariya S | D69: migrated from 5/17 sheet | F69: generate in-task | G69: generate in-task | H69: generate in-task | I69: generate in-task | J69: generate in-task | L69: FALSE | M69: TRUE
A70: 25c6fc3e-a489-4b5c-a24f-6ac3bf5f7cf2 | B70: =concat("https://www.tsip.ai/force/",A70) -> https://www.tsip.ai/force/25c6fc3e-a489-4b5c-a24f-6ac3bf5f7cf2 | C70: Spencer H | D70: fixed claude's comments which were some presentation issues and one perturbation; had already done this before and it said it was 2 rubric items away from a 5 | E70: 45 | F70: generate in-task | G70: generate in-task | H70: generate in-task | I70: generate in-task | J70: generate in-task | K70: 46161 | L70: FALSE | M70: TRUE
A71: 3426a792-0dce-4172-99f3-ad16f69e29e3 | B71: =concat("https://www.tsip.ai/force/",A71) -> https://www.tsip.ai/force/3426a792-0dce-4172-99f3-ad16f69e29e3 | C71: Spencer H | D71: workbook needed signifcant edits to fix claude errors; the prompt was in pretty good shape so just making slight edits; many formula items were stacked; model integration had to be more specific; all the perturbations just said something like "computed with the correct value" without actually stating a value | E71: 45 | F71: generate in-task | G71: generate in-task | H71: generate in-task | I71: generate in-task | J71: generate in-task | K71: 46162 | L71: FALSE | M71: TRUE
A72: f355ac29-6025-4a13-a04b-b1e0b9cf0b67 | B72: =concat("https://www.tsip.ai/force/",A72) -> https://www.tsip.ai/force/f355ac29-6025-4a13-a04b-b1e0b9cf0b67 | C72: Pragyat A | E72: 62 | F72: generate in-task | G72: generate in-task | H72: generate in-task | I72: generate in-task | J72: generate in-task | K72: 46159 | L72: FALSE | M72: TRUE
A73: 68f08b51-5cf5-446d-ac68-50ed30841bdc | B73: =concat("https://www.tsip.ai/force/",A73) -> https://www.tsip.ai/force/68f08b51-5cf5-446d-ac68-50ed30841bdc | C73: Pragyat A | E73: 77 | F73: generate in-task | G73: generate in-task | H73: generate in-task | I73: generate in-task | J73: generate in-task | K73: 46159 | L73: FALSE | M73: TRUE
A74: a8590094-240a-4bd5-9fc9-1957975c02cd | B74: =concat("https://www.tsip.ai/force/",A74) -> https://www.tsip.ai/force/a8590094-240a-4bd5-9fc9-1957975c02cd | C74: Diogo P | D74: migrated from 5/17 sheet | E74: 70 | F74: generate in-task | G74: generate in-task | H74: generate in-task | I74: generate in-task | J74: generate in-task | K74: 46159 | L74: FALSE | M74: TRUE
A75: 3166a5a4-9fa1-4cb6-9cb7-69efb4129132 | B75: =concat("https://www.tsip.ai/force/",A75) -> https://www.tsip.ai/force/3166a5a4-9fa1-4cb6-9cb7-69efb4129132 | C75: Elliot S | D75: too simple - just building a few sensitivity tables | E75: 10 | F75: generate in-task | G75: generate in-task | H75: generate in-task | I75: generate in-task | J75: generate in-task | K75: 46161 | L75: TRUE | M75: TRUE
A76: f37029d6-f2f6-458e-803a-32d664f3e0ca | B76: =concat("https://www.tsip.ai/force/",A76) -> https://www.tsip.ai/force/f37029d6-f2f6-458e-803a-32d664f3e0ca | C76: Diogo P | D76: Rubric had comlpetely wrong sections (numer 1 and 4) | E76: 70 | F76: generate in-task | G76: generate in-task | H76: generate in-task | I76: generate in-task | J76: generate in-task | K76: 46162 | L76: TRUE | M76: TRUE
A77: d44d1f90-a527-4f89-b6b8-7b0182b31ac6 | B77: =concat("https://www.tsip.ai/force/",A77) -> https://www.tsip.ai/force/d44d1f90-a527-4f89-b6b8-7b0182b31ac6 | C77: Diogo P | D77: Minor changes to model, rubric and prompt. | E77: 50 | F77: generate in-task | G77: generate in-task | H77: generate in-task | I77: generate in-task | J77: generate in-task | K77: 46163 | L77: TRUE | M77: TRUE
A78: 274a5df8-9de4-47da-a688-f7c2c545426a | B78: =concat("https://www.tsip.ai/force/",A78) -> https://www.tsip.ai/force/274a5df8-9de4-47da-a688-f7c2c545426a | C78: Elliot S | D78: migrated from 5/17 sheet | E78: 60 | F78: generate in-task | G78: generate in-task | H78: generate in-task | I78: generate in-task | J78: generate in-task | K78: 46160 | L78: FALSE | M78: TRUE
A79: 735a68dd-f94a-4837-aa1a-4e4db7330811 | B79: =concat("https://www.tsip.ai/force/",A79) -> https://www.tsip.ai/force/735a68dd-f94a-4837-aa1a-4e4db7330811 | C79: Spencer H | D79: rewriting this; fixed claude's workbook comments; removed formula stacking in rubric; model integration was not specific enough; perturbation items were slightly off; fixed presentation | E79: 60 | F79: generate in-task | G79: generate in-task | H79: generate in-task | I79: generate in-task | J79: generate in-task | K79: 46162 | L79: FALSE | M79: TRUE
A80: fe06a32d-2474-4338-8d11-e6391b0e0002 | B80: =concat("https://www.tsip.ai/force/",A80) -> https://www.tsip.ai/force/fe06a32d-2474-4338-8d11-e6391b0e0002 | C80: Antonio V | D80: migrated from 5/17 sheet | E80: 120 | F80: generate in-task | G80: generate in-task | H80: generate in-task | I80: generate in-task | J80: generate in-task | K80: 46160 | L80: FALSE | M80: TRUE
A81: c603f188-012e-432c-987a-bab69d68e967 | B81: =concat("https://www.tsip.ai/force/",A81) -> https://www.tsip.ai/force/c603f188-012e-432c-987a-bab69d68e967 | C81: Nadine M | D81: Had to redo prompt to align with workbook. Fixed formatting in sheet (color coding, decimals, consistency). fixed workbook formulas. Rubric: got rid of stacking and redid output validation and perturbation given my changes. | E81: 100 | F81: generate in-task | G81: generate in-task | H81: generate in-task | I81: generate in-task | J81: generate in-task | K81: 46162 | L81: FALSE | M81: TRUE
A82: 4d4aebcd-b8ad-4ced-bf88-65f873ada047 | B82: =concat("https://www.tsip.ai/force/",A82) -> https://www.tsip.ai/force/4d4aebcd-b8ad-4ced-bf88-65f873ada047 | C82: Antonio V | D82: migrated from 5/17 sheet | E82: 300 | F82: generate in-task | G82: generate in-task | H82: generate in-task | I82: generate in-task | J82: generate in-task | K82: 46160 | L82: FALSE | M82: TRUE
A83: f294960f-a3ca-40cf-acca-b9590c052592 | B83: =concat("https://www.tsip.ai/force/",A83) -> https://www.tsip.ai/force/f294960f-a3ca-40cf-acca-b9590c052592 | C83: Megan S | D83: migrated from 5/17 sheet | E83: 200 | F83: generate in-task | G83: generate in-task | H83: generate in-task | I83: generate in-task | J83: generate in-task | K83: 46160 | L83: FALSE | M83: TRUE
A84: 837b4154-66d4-4608-ae5e-c276a5353e0a | B84: =concat("https://www.tsip.ai/force/",A84) -> https://www.tsip.ai/force/837b4154-66d4-4608-ae5e-c276a5353e0a | C84: Jalaj G | D84: migrated from 5/17 sheet | E84: 48 | F84: generate in-task | G84: generate in-task | H84: generate in-task | I84: generate in-task | J84: generate in-task | K84: 46160 | M84: TRUE
A85: 1edd989b-7321-4735-a6f3-3ee860e97797 | B85: =concat("https://www.tsip.ai/force/",A85) -> https://www.tsip.ai/force/1edd989b-7321-4735-a6f3-3ee860e97797 | C85: Jalaj G | D85: migrated from 5/17 sheet | E85: 67 | F85: generate in-task | G85: generate in-task | H85: generate in-task | I85: generate in-task | J85: generate in-task | K85: 46160 | M85: TRUE
A86: 8acc4474-5e33-4ec3-a13b-91af7d059e53 | B86: =concat("https://www.tsip.ai/force/",A86) -> https://www.tsip.ai/force/8acc4474-5e33-4ec3-a13b-91af7d059e53 | C86: Jalaj G | D86: migrated from 5/17 sheet | E86: 60 | F86: generate in-task | G86: generate in-task | H86: generate in-task | I86: generate in-task | J86: generate in-task | K86: 46160 | M86: TRUE
A87: a9ecec1f-7c00-483e-a8a2-ca5e37bb67d7 | B87: =concat("https://www.tsip.ai/force/",A87) -> https://www.tsip.ai/force/a9ecec1f-7c00-483e-a8a2-ca5e37bb67d7 | C87: Jalaj G | D87: migrated from 5/17 sheet | E87: 80 | F87: generate in-task | G87: generate in-task | H87: generate in-task | I87: generate in-task | J87: generate in-task | K87: 46160 | M87: TRUE
A88: 91773d4f-fedd-4d3c-869c-677ea3db26c5 | B88: =concat("https://www.tsip.ai/force/",A88) -> https://www.tsip.ai/force/91773d4f-fedd-4d3c-869c-677ea3db26c5 | C88: Jared M | D88: just a simple CF build with a revolver schedule that is pretty meaningless as its never drawn; the prompt has no details on any mechanics for the revolver; there's a good DCF build in the seed WB that I'll use as a task | E88: 75 | F88: generate in-task | G88: generate in-task | H88: generate in-task | I88: generate in-task | J88: generate in-task | K88: 46161 | L88: FALSE | M88: TRUE
A89: 67f9d9b6-ddab-458f-825e-472de522a481 | B89: =concat("https://www.tsip.ai/force/",A89) -> https://www.tsip.ai/force/67f9d9b6-ddab-458f-825e-472de522a481 | C89: Jalaj G | D89: prompt - improved language throughout workbook output - changed formula in c214 - deleted hardcodes from d248:l248 - standardised formatting rubric - unstacked many criteria - added some mi criteria - updated values of some ov and pt criteria - added presentation criteria | E89: 60 | F89: generate in-task | G89: generate in-task | H89: generate in-task | I89: generate in-task | J89: generate in-task | K89: 46161 | L89: FALSE | M89: TRUE
A90: fedb1a49-141f-4903-bb1d-af4e416f99e9 | B90: =concat("https://www.tsip.ai/force/",A90) -> https://www.tsip.ai/force/fedb1a49-141f-4903-bb1d-af4e416f99e9 | D90: the wrong output workbook submitted | E90: 5 | F90: generate in-task | G90: generate in-task | H90: generate in-task | I90: generate in-task | J90: generate in-task | K90: 46161 | L90: FALSE | M90: FALSE
A91: 88bf1a51-3a20-4248-aa51-d6f16244776d | B91: =concat("https://www.tsip.ai/force/",A91) -> https://www.tsip.ai/force/88bf1a51-3a20-4248-aa51-d6f16244776d | C91: Megan S | D91: old rubric | F91: generate in-task | G91: generate in-task | H91: generate in-task | I91: generate in-task | J91: generate in-task | L91: FALSE | M91: FALSE
A92: ed6c77a7-69a7-4c66-9b3b-277ccab17b9d | B92: =concat("https://www.tsip.ai/force/",A92) -> https://www.tsip.ai/force/ed6c77a7-69a7-4c66-9b3b-277ccab17b9d | C92: Diego P | D92: migrated from 5/17 sheet | E92: 60 | F92: generate in-task | G92: generate in-task | H92: generate in-task | I92: generate in-task | J92: generate in-task | K92: 46159 | L92: FALSE | M92: TRUE
A93: 7e1002d3-e929-49ff-b66f-0c8639cd3d49 | B93: =concat("https://www.tsip.ai/force/",A93) -> https://www.tsip.ai/force/7e1002d3-e929-49ff-b66f-0c8639cd3d49 | C93: Francisco C | D93: Implemented minor Claude feedback | E93: 25 | F93: generate in-task | G93: generate in-task | H93: generate in-task | I93: generate in-task | J93: generate in-task | K93: 46162 | L93: FALSE | M93: TRUE
A94: f54cc8f4-531c-43ad-8271-0731f6a5fc1f | B94: =concat("https://www.tsip.ai/force/",A94) -> https://www.tsip.ai/force/f54cc8f4-531c-43ad-8271-0731f6a5fc1f | C94: John W | D94: migrated from 5/17 sheet | E94: 60 | F94: generate in-task | G94: generate in-task | H94: generate in-task | I94: generate in-task | J94: generate in-task | K94: 46160 | M94: TRUE
A95: bcdd0085-aeb2-483b-937b-3eca8c90a71a | B95: =concat("https://www.tsip.ai/force/",A95) -> https://www.tsip.ai/force/bcdd0085-aeb2-483b-937b-3eca8c90a71a | C95: Jalaj G | D95: prompt - added 3 more checks to make the task chunkier - re-wrote entire prompt workbook input - aligned summary tab with output file - changed column widths workbook output - added 3 more checks to make the task chunkier - added some functionality - aligned summary tab with input file - changed column widths rubric - re-wrote the entire rubric - added mi criteria - added ov criteria - added pt criteria - removed out of scope criteria - added presentation criteria | E95: 95 | F95: generate in-task | G95: generate in-task | H95: generate in-task | I95: generate in-task | J95: generate in-task | K95: 46161 | L95: FALSE | M95: TRUE
A96: ecea9d6b-d4fa-4ceb-9612-428e69c57930 | B96: =concat("https://www.tsip.ai/force/",A96) -> https://www.tsip.ai/force/ecea9d6b-d4fa-4ceb-9612-428e69c57930 | C96: Francisco C | D96: migrated from 5/17 sheet | E96: 50 | F96: generate in-task | G96: generate in-task | H96: generate in-task | I96: generate in-task | J96: generate in-task | K96: 46159 | M96: TRUE
A97: cf2067a1-99b4-4c0d-817b-01e60ba24c80 | B97: =concat("https://www.tsip.ai/force/",A97) -> https://www.tsip.ai/force/cf2067a1-99b4-4c0d-817b-01e60ba24c80 | C97: Diogo P | D97: Financial model and minor changes to rubric and prompt | E97: 50 | F97: generate in-task | G97: generate in-task | H97: generate in-task | I97: generate in-task | J97: generate in-task | K97: 46160 | M97: TRUE
A98: 455a84b6-0dec-4e36-9f0c-a49a25261eda | B98: =concat("https://www.tsip.ai/force/",A98) -> https://www.tsip.ai/force/455a84b6-0dec-4e36-9f0c-a49a25261eda | C98: Spencer H | D98: this is extremely underspecified and i am rewriting the whole thing - it only says the section headers of the whole LBO tab without going into any more detail; fixed claude's comments on the workbook; some formula correctness was testing hardcoded input values; some formulas had output items in them; one perturbation item was incorrect | E98: 70 | F98: generate in-task | G98: generate in-task | H98: generate in-task | I98: generate in-task | J98: generate in-task | K98: 46161 | L98: FALSE | M98: TRUE
A99: e3c878e1-31cc-44a5-9d12-3045a0475fdd | B99: =concat("https://www.tsip.ai/force/",A99) -> https://www.tsip.ai/force/e3c878e1-31cc-44a5-9d12-3045a0475fdd | C99: Caitlin R | D99: Fixed rubric and prompt | E99: 44 | F99: generate in-task | G99: generate in-task | H99: generate in-task | I99: generate in-task | J99: generate in-task | K99: 46161 | L99: FALSE | M99: TRUE
A100: 36ab5d58-e3a7-40e2-9388-e1d156a775f7 | B100: =concat("https://www.tsip.ai/force/",A100) -> https://www.tsip.ai/force/36ab5d58-e3a7-40e2-9388-e1d156a775f7 | C100: Ariya S | D100: workbook fixes based on claude feedback; additions to prompt; rubric fixes | E100: 55 | F100: generate in-task | G100: generate in-task | H100: generate in-task | I100: generate in-task | J100: generate in-task | K100: 46161 | L100: FALSE | M100: TRUE
A101: 1ef74bd2-64b2-448e-a858-57a93046a5fd | B101: =concat("https://www.tsip.ai/force/",A101) -> https://www.tsip.ai/force/1ef74bd2-64b2-448e-a858-57a93046a5fd | C101: Nadine M | D101: Rubric: fixed stacking and out of scope. Redid Model Integration section. Workbook and prompt: fixed and aligned formatting. | E101: 40 | F101: generate in-task | G101: generate in-task | H101: generate in-task | I101: generate in-task | J101: generate in-task | K101: 46162 | L101: not eligible for too simple - please complete the task regardless | M101: TRUE
A102: 3f333b76-25bc-4c8a-80b4-c06e7d095f32 | B102: =concat("https://www.tsip.ai/force/",A102) -> https://www.tsip.ai/force/3f333b76-25bc-4c8a-80b4-c06e7d095f32 | C102: Francisco C | D102: Output: Corrected debt value calculation; Adjusted WACC components | Prompt: Full re write to include necessary data and make it more clear | Rubric: Removed out of scope, corrected output validation and perturbation sections based on the new output base case correction | E102: 70 | F102: generate in-task | G102: generate in-task | H102: generate in-task | I102: generate in-task | J102: generate in-task | K102: 46162 | L102: not eligible for too simple - please complete the task regardless | M102: TRUE
A103: 67c66149-8cf4-4a0c-9bd0-959882d572f1 | B103: =concat("https://www.tsip.ai/force/",A103) -> https://www.tsip.ai/force/67c66149-8cf4-4a0c-9bd0-959882d572f1 | C103: Diego P | D103: Fixed formatting erros and rubric pitfall error. Noting interest expense is hardcoded. Mino rubric adjustments. | E103: 46 | F103: generate in-task | G103: generate in-task | H103: generate in-task | I103: generate in-task | J103: generate in-task | K103: 46161 | L103: not eligible for too simple - please complete the task regardless | M103: TRUE
A104: 733e1ae8-7516-4dcf-8dd9-3a9b082c2153 | B104: =concat("https://www.tsip.ai/force/",A104) -> https://www.tsip.ai/force/733e1ae8-7516-4dcf-8dd9-3a9b082c2153 | C104: Diego P | D104: Fixed both the input/output workbooks for erros and blank referencing. Then had to completely rewrite index formulas because the numbers were being calculated incorrectly in the model tab. After that I had to redo the whole rubric to match. | E104: 150 | F104: generate in-task | G104: generate in-task | H104: generate in-task | I104: generate in-task | J104: generate in-task | K104: 46163 | L104: not eligible for too simple - please complete the task regardless | M104: FALSE
A105: 7b100f04-743a-441e-9b0c-6bebe95cbee0 | B105: =concat("https://www.tsip.ai/force/",A105) -> https://www.tsip.ai/force/7b100f04-743a-441e-9b0c-6bebe95cbee0 | C105: Diego P | D105: Fixed formatting in output workbook, as well as clarified that WACC is not an input, but rather a calculation | E105: 38 | F105: 4 | G105: Run tsip-claude-feedback-085207da-cfd8-4b2b-8845-d656227d5319 Completed 19 may, 19:10 Major Takeaways This is a high-quality patch-based task. The prompt is well-scoped, provides all hardcoded input values, describes the three-section structure clearly (Discount Rate Inputs with three subsections, WACC, Valuation Calculation), and is written in natural human language. The input workbook is a professionally constructed SaaS financial model with an o_Fin Stats tab containing cash flows, EBITDA, balance sheet data, and a consistent structural convention. The output workbook adds an o_DCF tab that is correctly integrated: the 60-month timeline header rows link to o_Fin Stats, operating and investing cash flows pull from rows 185 and 190 of o_Fin Stats respectively with an IF-actual/forecast conditional, the Valuation Date links to i_Setup!U26, and the P/Current EBITDA ratio links to o_Fin Stats!M104. All nine output validation checks pass exactly (WACC = 6.72%, TV = 2,111,109.40, sum DCF = 2,153,930.79, EV = 2,089,312.87, Equity Value = 2,228,528.32, P/Current EBITDA = 20.01x, P/Forward EBITDA = 10.46x, CoE = 7.40%, DLOM = −64,617.92). All six perturbation checks were verified algebraically and match the rubric expectations (e.g., TV growth 1.5% → 2.5% yields equity value ≈ 2,586,754). No error values exist in any tab. The o_DCF tab is correctly inserted between o_Fin Stats and o_Dashboard, and the sysCheck tab lists o_DCF as a monitored sheet. Major Errors K42 and K43 number format: The Cost of Equity (K42) and Cost of Debt after tax (K43) output cells in the WACC section use the simplified 0.00% format rather than the workbook-standard 0.00%_);[Red]\-0.00%_);0.00%_);[Red]"Err-"@ format used throughout the input assumption cells. This creates a minor visual inconsistency in the WACC section. WACC row missing top border: Cell H44 ("WACC") in the WACC section does not have a thin top border, unlike other total/subtotal rows (rows 53, 56, 62, 65, 70) which all have thin top borders correctly applied. BW53 not populated: There is no column-BW summary formula for "Cash Flow before Terminal Value" (row 53), though BW56 (Cash Flow before Discounting) correctly sums across the entire row including terminal value. This is a minor presentational gap that has no impact on calculations. Critical Errors None. All formula logic is correct, all model integrations are live and linked, all output values match expected ranges exactly, all perturbation sensitivities are dynamic and correct, and no error values or broken references exist in any tab. Rubric Rationale Meridian Rubric (Patch-Based): Prompt–Workbook Coherence: 5/5 — All referenced artifacts exist; no mismatches. The o_Fin Stats cash flow rows, EBITDA line, balance sheet items, and i_Setup valuation date are all present and properly linkable. Task Feasibility: 4/5 — Fully executable with at most one or two minor domain-standard interpretations (monthly discounting convention, terminal year as average of last 12 months). All task-specific assumptions (WACC inputs, growth rate, DLOM) are explicitly stated. Input Workbook Starting State: 5/5 — Realistic, professional SaaS operating model; ideal preceding state for a DCF extension. Output Workbook – Data Integrity: 5/5 — Zero error values across all nine tabs; all formulas resolve correctly. Output Workbook – Formula Quality: 5/5 — Fully dynamic; all calculation cells reference labeled assumption cells; no hardcoded values in formulas. Output Workbook – Formatting & Presentation: 4/5 — Arial font throughout, correct number formats on valuation cells (#,##0;[Red]\(#,##0\);"-"_)), bold labels on total rows, thin top borders on key totals. Minor inconsistency: K42/K43 use simplified 0.00% format and H44 is missing a top border. Input-to-Output Progression: 5/5 — Classic analyst workflow; operating model → DCF valuation tab is the definitive patch task archetype. Task-Specific Rubric Formula Correctness (25 pts possible): All 15 criteria pass — Debt Share, CAPM CoE, CoD after tax, WACC, CF before TV, Terminal Value, CF before discounting, discounting factor, discounted CF, DLOM, enterprise value, equity value bridge, debt sign convention, P/Current EBITDA, P/Forward EBITDA are all correctly implemented. Model Integration (16 pts possible): All 4 criteria pass — timeline linked to o_Fin Stats, CF from operating linked with actual/forecast conditional, Valuation Date linked to i_Setup, P/Current EBITDA linked to o_Fin Stats!M104. Output Validation (40 pts possible): All 9 criteria pass with sub-0.1% deviation from expected values. Perturbation (30 pts possible): All 6 sensitivities verified algebraically to match expected outputs within tolerance. Presentation (6 pts possible): ~5-6/6 — correct number formats, bold totals, thin borders (with the WACC row border gap noted), Arial font consistent. Pitfalls (0 penalty): No error values, no truncation observed. Overall, the task meets the standard for a 4 (Good) under the Meridian framework. All components score 3 or higher and most score 4 or 5. The output workbook is an excellent, fully-integrated DCF implementation with correct formulas and exact output values. The minor deductions are limited to cosmetic formatting inconsistencies (K42/K43 number format, one missing border) that do not affect correctness, integration, or usability as training data. | H105: generate in-task | I105: generate in-task | J105: generate in-task | K105: 46161 | L105: not eligible for too simple - please complete the task regardless | M105: TRUE
A106: 7b5945dd-98a8-43ef-b9d2-2c94c05bf17a | B106: =concat("https://www.tsip.ai/force/",A106) -> https://www.tsip.ai/force/7b5945dd-98a8-43ef-b9d2-2c94c05bf17a | C106: Diego P | D106: Fixed formatting in output workbook, as well as slightly rewrote prompt. | E106: 74 | F106: 4 | G106: Run tsip-claude-feedback-eb87dd6b-9096-470d-9b71-5f191507d969 Completed 19 may, 20:18 Major Takeaways The output workbook adds a new "Entry-Exit Analysis" tab that is near-perfectly constructed. All ten output-validation targets match their expected values exactly: IRR = 55.21% (target 55.2%), CoC = 5.810x (target 5.81x), Exit EV = INR 12,021.15 mn, Exit Equity Value = INR 12,133.29 mn, JM Investment exit amount = INR 1,597.75 mn, net debt at exit = –INR 112.14 mn, pre-money equity value = INR 1,745.60 mn, post-money EV/EBITDA = 16.41x, IRR sensitivity (700 mn / 13×) = 44.89%, and CoC sensitivity (600 mn / 12×) = 3.50×. All five perturbation scenarios also compute correctly due to fully dynamic formulas: the pre-money EV is driven by MAX(MIN(G16×G6, G18), G17), XIRR uses dated cash flows, and all cross-tab links are live (Revenue from Financial Statements!CA14/10^6, Total Investment from Balance Sheet Assumptions!Q6/10^6, JM stake from Emiza - Cap Table!R17). The prompt is well-scoped, internally consistent, and references tabs and line items that exist in the input workbook. No #REF!, #DIV/0!, or other error values are present. Major Errors G13 (Total Investment Amount) is formatted as a hardcoded input: Cell G13 holds the formula ='Balance Sheet Assumptions'!Q6/10^6 (a live cross-tab link) but carries blue font (FF0000FF) and yellow fill (FFFFFFCC), the convention reserved for hardcoded assumptions. Formula-driven cells should be black on white. Sensitivity table section headers are not bold: O13 ("Exit EV / EBITDA (FY26)"), M15/M24 ("FY26 EBITDA (INR mn)"), and O22 ("Exit EV / EBITDA (FY26)") all carry the dark navy fill (FF002060) and theme-white font, satisfying the fill requirement, but font.bold = False on all four—contrary to the rubric's "dark navy fill and white bold font" specification. By contrast, the main financial-summary header row (C3:K3) is correctly bold. Potential text truncation in M15 and M24: Column M is 8.55 units wide; the label "FY26 EBITDA (INR mn)" (20 characters) overflows into N15 and N24 which are occupied (values 500 and 500), causing visual truncation of the row-variable header in both sensitivity tables. This triggers the −3 pitfall deduction. Critical Errors None. There are no critical errors: all formulas are correct, all expected numeric outputs fall within tolerance, all cross-tab integrations are properly live-linked, and all five perturbation tests produce correct downstream updates. Rubric Rationale Task-Specific Rubric (additive point scoring) Section Available Earned Notes Formula Correctness (15 criteria) 23 23 All formulas verified correct — pre-money EV floor/cap, net debt (both dates), equity values, XIRR IRR, CoC, all implied multiples, both data-table sensitivities Model Integration (3 criteria) 8 8 Revenue → FS tab ÷10⁶ ✓; Total Investment → BSA tab ÷10⁶ ✓; JM stake → Cap Table ✓ Output Validation (10 criteria) 44 44 All 10 point-in-time values within tolerance Perturbation (5 criteria) 25 25 All five dynamic updates verified arithmetically Presentation (3 criteria) 7 5 −1 G13 formatted as hardcoded input; −1 sensitivity headers not bold (partial credit on criterion 3) Pitfalls −8 max −3 No error values (0); text truncation in M15/M24 (−3) Total 107 102 95.3% Meridian Rubric (holistic 1–5): Prompt–Workbook Coherence: 5 — all referenced tabs (Financial Statements, Balance Sheet Assumptions, Emiza Cap Table) exist with correct data; entry date March 31 2022 maps correctly to FY22 EBITDA and Balance Sheet column AC/CB; no mismatches. Task Feasibility: 5 — all assumptions provided in the prompt; the one non-obvious design choice (using Dec 2021 balance sheet for pre-money net debt, before the Series B cash injection, labeled "Net Debt (Dec'21)") is internally consistent and produces the correct expected output. Input Workbook Starting State: 5 — realistic multi-tab financial model with clean data and no pre-existing errors. Output Workbook – Data Integrity: 5 — zero formula errors, all computations resolve. Output Workbook – Formula Quality: 4 — fully dynamic; only blemish is G13 cosmetically misclassified as hardcoded input. Output Workbook – Formatting: 4 — professional structure, correct number formats throughout, blue+yellow inputs, dark-navy headers; sensitivity sub-headers lack bold and M column is too narrow. The task-specific rubric score of ~95% and strong performance across all Meridian dimensions yields a holistic 4 (Good). The deduction from a perfect 5 is driven exclusively by the three minor presentation issues: G13 misformatted, sensitivity headers not bold, and column-M label truncation. No calculation, formula logic, or model integration issue prevents a full score on every substantive criterion. | H106: generate in-task | I106: generate in-task | J106: generate in-task | K106: 46161 | L106: not eligible for too simple - please complete the task regardless | M106: TRUE
...

Sheet Tasks to Send Back
A1: Task ID | B1: Claude Score | C1: Claude Feedback | D1: Rubric Tool | E1: Rubric Feedback
A2: Outcome | B2: Claude Score | C2: Claude Feedback | D2: Rubric Score | E2: Failed Criteria
A3: Send back to CB - Claude | B3: 3 | C3: # 1a694939-ce51-42dd-9273-d4121f1ffab0 **Score: 3 / 5** --- ## Major Takeaways The output workbook correctly builds the full Silver, Gold, and Platinum SAC breakdown by subscription type (rows 402–480), including all commission value formulas, Other SAC per-sub inputs, growth-rate projections, Total Other SAC capitalized lines, and the three amortization waterfalls with correct useful-life half-year conventions. All 11 output-validation benchmarks fall within the specified 2% tolerance, and all 7 perturbation tests pass at the tier level (Silver rows 428/430, Gold row 455, Platinum rows 478/480). No error values exist anywhere in the sheet. Formatting is largely correct—hardcoded inputs are blue, formula cells carry dark theme color (interpreted as black), dollar values show 2 decimal places with parentheses, and percentages use 0.0%. The critical defect is the projection-period aggregate section (rows 387–400): `Commission Value and Other SAC Value` (G391–K391), `Amortized Commissions and Other SAC` (G393–K393), `Other S&M` (G396–K396), and `Total S&M` (G400–K400) are all **hardcoded floats** rather than formula-linked sums. These cells feed the income statement (row 21, via row 400) and the non-GAAP and cash-flow sections (rows 51, 61, 68), so no upstream assumption change will flow into those sections. The hardcoded aggregate values also lack the blue font that should be applied to hardcoded inputs. --- ## Major Errors 1. **Hardcoded aggregate rows in the S&M rollup section (rows 391, 393, 396, 400, projection years G–K):** `G391:K391` (Commission Value & Other SAC aggregate), `G393:K393` (Amortized Commissions & Other SAC aggregate), `G396:K396` (Other S&M, which should equal Total Revenue × 4%), and `G400:K400` (Total S&M) are plain float values rather than formulas. Changing any upstream assumption (e.g., commission rate, inflation, subscriber counts) updates the tier-level SAC rows but leaves the income statement, non-GAAP metrics, and cash-flow statement unresponsive. 2. **Missing blue-font convention on projection-period hardcoded aggregate values:** The hardcoded cells in G391–K391, G393–K393, G396–K396, and G400–K400 carry the default theme color (interpreted as black/auto) rather than blue `#0000FF`. Hardcoded inputs in the existing workbook, and all other hardcoded inputs in the new section, correctly use blue; these aggregate rows are inconsistent. 3. **Minor number-format inconsistency:** Several intermediate rows (e.g., `Other SAC New Subs` row 414, `Other SAC Retention/Downgrade` row 416, amortization waterfall rows 422–426) use `#,##0.00_);(#,##0.00)` (no dollar-sign prefix) while the summary rows and adjacent dollar lines use `"$"#,##0.00_);("$"#,##0.00)`. Both formats meet the two-decimal, comma-separator, parentheses-for-negatives requirements, so this is cosmetic. --- ## Critical Errors - **Aggregate consolidation rows (391, 393, 396, 400) hardcoded in projection period:** This is the single most impactful defect. It fails three Formula Correctness rubric criteria (−4 pts) and the most heavily weighted Model Integration criterion (−4 pts). It also means the income statement, non-GAAP metrics, and cash-flow statement are silently disconnected from the new SAC schedule for all five forecast years. In a real analyst workflow this would be caught immediately and treated as a structural rebuild error. --- ## Rubric Rationale **Task-Specific Rubric (scored item by item):** | Section | Points Available | Points Earned | Notes | |---|---|---|---| | Formula Correctness | 26 | 22 | Fails items for aggregate Commission Value (1), aggregate Amortized SAC (1), and Total S&M formula (2); all tier-level formulas pass | | Model Integration | 32 | 28 | Fails the 4-pt criterion for aggregate rows not linked to Silver/Gold/Platinum; all tier-level linkages verified correct | | Output Validation | 44 | 44 | All 11 benchmarks verified within ±2%: Silver Total Cap SAC 2027P = −46.34 ✓, Silver Amortized SAC 2027P = −45.61 ✓, Gold Total Cap SAC 2027P = −19.92 ✓, Platinum Total Cap SAC 2027P = −22.11 ✓, etc. | | Perturbation | 35 | 35 | All 7 tests confirmed at tier-level rows: e.g., Silver cap rate 18%→22% gives G430 = −50.79 ✓; Plat commission rate 10%→15% gives K480 = −31.27 ✓ | | Presentation | 6 | 5 | Missing blue on hardcoded aggregate projection values (−1); dollar format, pct format, black-formula font all pass | | Pitfalls | 0 possible penalty | 0 | No #REF!, #DIV/0!, or other error values found; no truncation issues observed | | **Total** | **143** | **134 (93.7%)** | | **Meridian Rubric Assessment:** | Dimension | Rating | Reasoning | |---|---|---| | Prompt–Workbook Coherence | 5 | Prompt maps cleanly to existing sections; all referenced sales values, subscriber counts, ASPs, and inflation rate link correctly | | Task Feasibility | 5 | Fully executable from the prompt and input workbook | | Input Workbook Starting State | 5 | Professional, complete model with no pre-existing errors | | Output Data Integrity | 5 | No error values; all formulas resolve; no broken references | | Output Formula Quality | 3 | Tier sections are fully dynamic; however 4 consolidation rows covering 5 forecast years are hardcoded rather than formula-driven—this is more than "one or two minor hardcoded values" | | Output Formatting | 4 | Minor inconsistency (missing blue on aggregate hardcoded values; two number-format variants for dollar rows) | | Input-to-Output Progression | 5 | Logical and substantive extension of an operating model | Overall Meridian score: **3 (Acceptable)**. The core deliverable—three complete, formula-driven, correctly structured SAC waterfall sections—is accurately built and fully validated. However, the systematic hardcoding of the projection-period aggregate rows (391, 393, 396, 400) creates a meaningful model-integration gap that prevents downstream financials from updating when assumptions change. This falls short of the "minor weakness" threshold for a 4 but does not trigger an audit-failure condition, placing the task squarely at Acceptable. | D3: 97 | E3: Formula Correctness — Is the aggregate Commission Value and Other SAC Value line computed as the sum of Silver Total Capitalized SAC, Gold Total Capitalized SAC, and Platinum Total Capitalized SAC? Formula Correctness — Is the aggregate Amortized Commissions and Other SAC line computed as the sum of Silver Amortized SAC, Gold Amortized SAC, and Platinum Amortized SAC? Formula Correctness — Is Total Sales and Marketing Costs computed as the sum of Amortized Commissions and Other SAC plus Other S&M? Model Integration — Are Silver, Gold, and Platinum amortization waterfalls linked to each tier’s Total Capitalized SAC row? Model Integration — Are aggregate Commission Value and Other SAC Value and aggregate Amortized Commissions and Other SAC linked to the Silver, Gold, and Platinum sections? Perturbation — If the Platinum Commission Rate for Upgrade/Retention/Downgrade on the Operating Model tab is changed from 10.0% to 15.0% for 2027P, does Platinum Total Capitalized SAC for 2027P in the Sales and Marketing Breakdown by Subscription Type section update to within +/- 2% of -31.27? Perturbation — If the Platinum Other SAC Per Retention/Upgrade on the Operating Model tab is changed from $49.25 to $55.00 for 2022E, does Platinum Total Capitalized SAC for 2023P in the Sales and Marketing Breakdown by Subscription Type section update to within +/- 2% of -2.15? Presentation — Are all dollar-denominated values in the Sales & Marketing Breakdown sections on the Operating Model tab formatted with parentheses for negatives? Pitfalls — Are there any error values in the Operating Model tab (#REF!, #DIV/0!, #VALUE!, #NAME?, #N/A, #NUM!)? Pitfalls — Is any data or label text truncated or hidden due to insufficient column widths or row heights in the Operating Model tab? Formula Correctness — Is the Platinum amortization waterfall spreading each year's capitalized costs over a 3-year useful life with half-year amounts in the first and last periods and full-year amounts in the two middle periods? Formula Correctness — Is Silver Other SAC Per New Sub projected by growing the prior year value at the model’s assumed inflation rate? Presentation — Are formula-driven values displayed in black font (#000000) across the Sales and Marketing Breakdown by Subscription Type section on the Operating Model tab?
A4: Send back to CB - Claude | B4: 3 | C4: # f84b70a6-25e7-4a65-a48f-e49f3d11ee68 **Overall Meridian Score: 3 / 5** **Task-Specific Rubric Score: 87 / 87 (100%)** --- ## Major Takeaways The output workbook adds a new `Valuation` tab to an existing ENTG financial model (Assumptions, Model, Comps). The core structure is present and well-constructed: Trading Liquidity, Public Market Overview, Analyst Ratings, a timetable (2020–2040, annual), P/E Multiple (2025E–2030E, cols O–T), DCF (2025E–2040E, cols O–AD), and a WACC Build section. All key formulas are correct—CoE, weighted average CoD, after-tax CoD, WACC, Gordon Growth Model terminal value, discount factor, and sum-of-cash-flow aggregation. All eight output validation targets and all five perturbation targets in the task-specific rubric are met, and no error values exist anywhere. Arial font and correct number formats are used throughout. However, the output contains three substantive structural failures versus the prompt that the task-specific rubric does not detect: (1) the DCF output rows (Terminal Value → IRR, rows 71–81) are populated only for 2025E (col O) and 2030E–2040E (cols T–AD), leaving four full years (2026E–2029E, cols P–S) completely blank; (2) UFCF YoY growth is hardcoded to 8% for 2031E–2036E but declines to 7%, 6%, 5.5%, and 5% for 2037E–2040E, directly violating the prompt's instruction of 8% for all of 2031E–2040E; and (3) Position Size is hardcoded to 50 while the prompt says 20—however, the rubric perturbation test was calibrated to 50, exposing a prompt factual error. Additionally, an editorial annotation ("<<< 25.0x is significantly lower than sellside…") was left in cell U49. --- ## Major Errors - **Missing DCF output section for 2026E–2029E (cols P, Q, R, S):** Rows 71–81 (Terminal Value, Sum of Cash Flows, PV of Terminal Value, Enterprise Value, Net Debt, Equity Value, FDSO, Implied DCF Price Target, % Upside, IRR) are entirely absent for years 2026E through 2029E. Only col O (2025E) and cols T–AD (2030E–2040E) have these rows populated. The DCF upper rows (Revenue, UFCF, Discount Factor, PV of UFCF, rows 58–66) are correctly populated across all columns. - **UFCF YoY growth not uniformly 8% for 2031E–2040E:** Cells U63–Z63 (2031–2036) are correctly hardcoded at 0.08, but AA63 (2037) = 0.07, AB63 (2038) = 0.06, AC63 (2039) = 0.055, AD63 (2040) = 0.05. The prompt explicitly says to hardcode 8.0% for the entire 2031E–2040E range. Despite the wrong rates, the 2040E DCF outputs land near the rubric-expected values (the expected values appear to have been computed using these declining rates, not uniform 8%). - **Position Size hardcoded at 50 instead of 20:** E11 = 50; the prompt explicitly states "Position Size (hardcode to 20)." This is a prompt factual error—the perturbation test (ADV% 20%→10% yielding days ≈ 2.021) is designed around a position size of 50. A model that correctly followed the prompt and entered 20 would fail that perturbation test (~0.81 days, ~60% off target). - **Extraneous editorial annotation:** U49 contains an inline comment about the exit multiple being below sell-side consensus, which should not appear in a production output workbook. --- ## Critical Errors - **Structural incompleteness of DCF output block (2026E–2029E):** The prompt asks for the "Implied DCF Price Target, % Upside and IRR" (and all prerequisite rows) across the full 2025E–2040E range. Four consecutive years are silently absent. This means the output workbook does not faithfully implement the full DCF-per-year table the prompt describes. - **UFCF growth instruction violated for 2037E–2040E:** Four explicit hardcoded cells deviate from the instruction (8% for all of 2031–2040). The rubric's UFCF-growth formula criterion passes because it only checks the formula structure for 2031E (U61), not the numerical values in 2037–2040. These incorrect rates would cause the 2040E DCF outputs to be wrong if the rubric expected values were actually based on uniform 8% (they are not, but an LLM trained on this task would learn the wrong growth profile). --- ## Rubric Rationale **Task-Specific Rubric (87/87 possible):** | Section | Earned | Available | Notes | |---|---|---|---| | Formula Correctness | 20 | 20 | All 12 formula checks pass: CoE (I94=I91*I92+I93), balance-weighted CoD SUMPRODUCT, AT CoD (H105=H104*(1–25%)), WACC (I107=I86*I94+I87*H105), EV = SUM(E18:E20), Weighted Avg Score SUMPRODUCT, Gordon Growth TV, DCF EV = SUM(O73:O74), Implied PT = Equity/FDSO, Total VPS = SUM(O50:O51), Discount Factor = 1/(1+WACC)^hold, UFCF formula structure | | Model Integration | 4 | 4 | E19 links to Model!BW186+BW187+BW188; those rows are in the Leverage section (starts at row 185) | | Output Validation | 35 | 35 | WACC 8.74% ✓; DCF PT 2040 $176.25 ✓; DCF IRR 2040 4.63% ✓; Total VPS 2030 $218.65 ✓; EV $17,406.60 ✓; Weighted Avg Score 2.571 ✓; PV TV 2040 $18,940 ✓; UFCF 2025 $557.6 ✓ | | Perturbation | 25 | 25 | Beta 1.50→new WACC 9.16%, formulas live; ERP 5% updates CoE dynamically; UFCF 2031 10% ratio = 1.10/1.08 → ~$179.51 within 2%; TGR links via Assumptions!E45→G45; ADV% 10% with PS=50 gives exactly 2.021 days | | Presentation | 3 | 3 | IRR format `#,##0.0%`, per-share `#,##0.00`, Arial confirmed on all sampled cells | | Pitfalls | 0 | (max –8) | No error values in Valuation or Assumptions tabs; U49 annotation not treated as required-data truncation | **Meridian Rubric Assessment:** - **Prompt quality:** ~3 — well-structured and mostly complete, but contains a clear factual error (position size 20 stated vs. 50 in golden output), and the UFCF "hardcode to 8% for 2031–2040" instruction contradicts the declining rates in the output. - **Input Workbook:** 4–5 — clean professional ENTG model with no errors, appropriate starting state. - **Output Workbook:** 3 — no errors, professional formatting, correct formulas, but structurally incomplete (4 DCF years missing) and violates two explicit prompt instructions (UFCF growth uniformity, position size). - **Rubric:** 3 — internally self-consistent against the actual output; factually correct for the output values tested; however, it does not test UFCF growth uniformity (2037–2040), does not flag the missing DCF columns, and contains the same position-size inconsistency as the prompt. **Overall: 3 — Acceptable.** The task passes audit (no error values, core structural sections present, rubric criteria internally consistent), but it has noticeable structural gaps and prompt factual errors that prevent a score of 4. | D4: 100

Sheet Model Decomp
A1: Task ID | B1: Seed ID | C1: Claimed By | D1: Force Claim Link | E1: Prompt Done? | F1: Checked FC / MI | G1: Date Completed | H1: AHT (mins) | I1: Rubric to Paste and Edit | J1: Rubric Reviewer | K1: OV/PT/Pres/Pitfalls Checked? | L1: Date Completed | M1: AHT (mins) - Post Prompt | N1: Admin Link Helper | O1: Checked? | P1: Notes | Q1: SOTA (Est.) | R1: Notes | T1: 46160 | U1: =countifs(E:E,true,G:G,$T1) -> 2 | V1: =countifs(K:K,true,L:L,$T1) -> 2
A2: 89eae8f1-dc6f-4145-a072-f056af902c05 | B2: 85d3d5d5-f85d-4799-8504-b807ad61ed36 | C2: Jalaj G | D2: =concat("https://www.tsip.ai/force/",A2) -> https://www.tsip.ai/force/89eae8f1-dc6f-4145-a072-f056af902c05 | E2: TRUE | F2: FALSE | G2: 46161 | H2: 50 | I2: =iferror(VLOOKUP(A2,'Decomp Rubrics'!A:B,2,false),"generating") -> generating | K2: FALSE | N2: ="https://admin.tsip.ai/tasks/"&A2 -> https://admin.tsip.ai/tasks/89eae8f1-dc6f-4145-a072-f056af902c05 | O2: FALSE | T2: 46161 | U2: =countifs(E:E,true,G:G,$T2) -> 7 | V2: =countifs(K:K,true,L:L,$T2) -> 0
A3: 2130b610-dc4c-4605-9163-a8b2224abd06 | B3: 09e67384-2f7f-4070-abcb-4ed9a2f4545e | C3: Jalaj G | D3: =concat("https://www.tsip.ai/force/",A3) -> https://www.tsip.ai/force/2130b610-dc4c-4605-9163-a8b2224abd06 | E3: TRUE | F3: TRUE | G3: 46162 | H3: 55 | I3: =iferror(VLOOKUP(A3,'Decomp Rubrics'!A:B,2,false),"generating") -> Section 1: Formula Correctness 1.1. Is Total Cost in the main project table on the Gross Margin tab calculated as the sum of Project-Level Cost and Client-Level Cost Allocation for each project? [+2] 1.2. Is Gross Profit in the main project table on the Gross Margin tab calculated as Project Value minus Total Cost for each project? [+2] 1.3. Is Gross Margin in the main project table on the Gross Margin tab calculated as Gross Profit divided by Project Value for each project? [+1] 1.4. Is the Total row Gross Margin on the Gross Margin tab calculated as total Gross Profit divided by total Project Value, rather than as an average of individual project margins? [+2] 1.5. Is the Average row Gross Margin on the Gross Margin tab calculated as average Gross Profit divided by average Project Value, not as the average of individual margins? [+2] 1.6. Does the Total row on the Gross Margin tab sum all 20 projects for Project Value, Hours at Project Level, Project-Level Cost, Client-Level Cost Allocation, Total Cost, and Gross Profit? [+2] 1.7. Does the Average row on the Gross Margin tab compute the arithmetic mean across all 20 projects for each numeric column (value, hours, costs, gross profit)? [+1] 1.8. Is the percentage-of-total column in each client allocation subtable on the Gross Margin tab calculated as that project's Project-Level Cost divided by the client's total Project-Level Cost? [+2] 1.9. Is the Client Level Cost Allocation per project in each client subtable on the Gross Margin tab calculated as the project's percentage of total cost multiplied by the client's total non-project-level cost? [+2] 1.10. Does the total row within each client allocation subtable on the Gross Margin tab sum Hours and Project-Level Cost across all projects listed in that client block? [+1] 1.11. Are Hours in the non-project-level time section on the Gross Margin tab aggregated from Harvest Data by matching both client name and the exact label 'Time not at Project Level' in Project Phase? [+2] 1.12. Is Client-Level Cost in the non-project-level time section on the Gross Margin tab aggregated from Harvest Data's Grossed Extended Cost column using the same dual-filter on client name and Project Phase? [+2] 1.13. Is the Client-Level Cost Allocation in the main table hardcoded to zero for projects belonging to clients with no non-project-level overhead (H&M, Panda Express, Red Sky, Vision Food Group)? [+2] 1.14. Is the Client-Level Cost Allocation for School of Rock's single project in the main table a direct reference to that client's total non-project-level cost rather than a subtable lookup? [+1] Section 2: Model Integration 2.1. Is the Hours at Project Level on the Gross Margin - Completed Projec tab linked to the Grossed Up Hours on the Harvest Data tab? [+5] 2.2. Is the Project Start Date on the Gross Margin - Completed Projec tab linked to the Actual start date (Permit Ops) on the Projects tab? [+3] Section 3: Output Validation 3.1. Is the Total Gross Profit on the Gross Margin - Completed Projec tab (Total row, column L) within +/- 2% of 898393.31? [+5] 3.2. Is the Total Gross Margin on the Gross Margin - Completed Projec tab (Total row, column M) within +/- 0.5 pp of 64.8%? [+5] 3.3. Is the Average Gross Profit on the Gross Margin - Completed Projec tab (Average row, column L) within +/- 2% of 44919.67? [+5] 3.4. Is the Total Project-Level Cost on the Gross Margin - Completed Projec tab (Total row, column I) within +/- 2% of 449498.69? [+4] 3.5. Is the Total Client-Level Cost Allocation on the Gross Margin - Completed Projec tab (Total row, column J) within +/- 2% of 39000? [+5] 3.6. Is the Total Hours at Project Level on the Gross Margin - Completed Projec tab (Total row, column H) within +/- 2% of 7858.18? [+3] 3.7. Is the Total Total Cost on the Gross Margin - Completed Projec tab (Total row, column K) within +/- 2% of 488498.69? [+5] 3.8. Is the Total Project Value on the Gross Margin - Completed Projec tab (Total row, column G) within +/- 2% of 1386892? [+3] 3.9. Is the Average Gross Margin on the Gross Margin - Completed Projec tab (Average row, column M) within +/- 0.5 pp of 64.7%? [+5] Section 4: Perturbation 4.1. If the Grossed Extended Cost value for the first data row in the Harvest Data tab (the row with task ID 15485439, Grossed Extended Cost of approximately 1034.81) is changed from 1034.8128 to 2069.6256 (doubled), does the Total Project-Level Cost on the Gross Margin - Completed Projec tab (Total row) update to reflect the increase, within +/- 2% of the correctly computed value? [+5] 4.2. If the Grossed Up Hours value for the first data row in the Harvest Data tab (the row with Grossed Up Hours of 8) is changed from 8 to 24 (tripled), does the Total Hours at Project Level on the Gross Margin - Completed Projec tab (Total row) update to reflect the increase, within +/- 2% of the correctly computed value? [+5] 4.3. If the Grossed Extended Cost value on the Harvest Data tab in the second data row (approximately 381.19) is changed from 381.1872 to 762.3744 (doubled), does the Total Gross Profit on the Gross Margin - Completed Projec tab (Total row) update to reflect the increased cost reducing profit, within +/- 2% of the correctly computed value? [+5] 4.4. If the Grossed Extended Cost value on the Harvest Data tab in the third data row (approximately 735.19) is changed from 735.1872 to 1470.3744 (doubled), does the Total row Gross Margin percentage on the Gross Margin - Completed Projec tab update to reflect the reduced margin, within +/- 0.5 percentage points of the correctly computed value? [+5] 4.5. If the Grossed Up Hours value on the Harvest Data tab in the second data row (value of 8) is changed from 8 to 40 (5x), does the Average Hours at Project Level on the Gross Margin - Completed Projec tab (Average row) update to reflect the increase, within +/- 2% of the correctly computed value? [+5] 4.6. If the Grossed Extended Cost for the fourth data row on the Harvest Data tab (approximately 129.35, column AM row index corresponding to the fourth upstream constant at AB3's paired cost) is changed from 1034.8128 to 0 (zeroed out), does the Total Cost on the Gross Margin - Completed Projec tab (Total row) update to reflect the decrease, within +/- 2% of the correctly computed value? [+5] 4.7. If the Grossed Extended Cost on the Harvest Data tab in the third data row (approximately 735.19) is changed from 735.1872 to 0 (zeroed out), does the Average Gross Profit on the Gross Margin - Completed Projec tab (Average row) update to reflect the improved profitability, within +/- 2% of the correctly computed value? [+5] Section 5: Presentation 5.1. Are all dollar-denominated values on the Gross Margin - Completed Projec tab formatted with a dollar sign prefix, comma separators, and no decimal places? [+2] 5.2. Do hardcoded values on the Gross Margin - Completed Projec tab appear in blue font, formula-driven values in black font, and cross-sheet references in green font? [+2] 5.3. Are the Total and Average rows and client-subtable total rows on the Gross Margin - Completed Projec tab visually distinguished with bold text? [+2] Section 6: Pitfalls 6.1. Are there any error values in the Internal Metrics tab and the Gross Margin - Completed Projec tab (#REF!, #DIV/0!, #VALUE!, #NAME?, #N/A, #NUM!)? [-5] 6.2. Is any data or label text truncated due to insufficient column widths or row heights in the Internal Metrics tab and the Gross Margin - Completed Projec tab? [-3] | K3: TRUE | L3: 46162 | M3: 65 | N3: ="https://admin.tsip.ai/tasks/"&A3 -> https://admin.tsip.ai/tasks/2130b610-dc4c-4605-9163-a8b2224abd06 | O3: FALSE | T3: 46162 | U3: =countifs(E:E,true,G:G,$T3) -> 20 | V3: =countifs(K:K,true,L:L,$T3) -> 12
A4: 6520d1cb-ef7f-4e18-8e27-901c61b13a4b | B4: 8bcd0914-32d4-4fc9-b97e-3c0c61e9c9ae | C4: Jalaj G | D4: =concat("https://www.tsip.ai/force/",A4) -> https://www.tsip.ai/force/6520d1cb-ef7f-4e18-8e27-901c61b13a4b | E4: TRUE | F4: FALSE | G4: 46161 | H4: 65 | I4: =iferror(VLOOKUP(A4,'Decomp Rubrics'!A:B,2,false),"generating") -> generating | K4: FALSE | N4: ="https://admin.tsip.ai/tasks/"&A4 -> https://admin.tsip.ai/tasks/6520d1cb-ef7f-4e18-8e27-901c61b13a4b | O4: FALSE | T4: 46163 | U4: =countifs(E:E,true,G:G,$T4) -> 8 | V4: =countifs(K:K,true,L:L,$T4) -> 6
A5: f0ec3331-b842-4f0f-bc7a-b3aa14727aa1 | B5: 8bcd0914-32d4-4fc9-b97e-3c0c61e9c9ae | C5: Jalaj G | D5: =concat("https://www.tsip.ai/force/",A5) -> https://www.tsip.ai/force/f0ec3331-b842-4f0f-bc7a-b3aa14727aa1 | E5: TRUE | F5: FALSE | G5: 46161 | H5: 65 | I5: =iferror(VLOOKUP(A5,'Decomp Rubrics'!A:B,2,false),"generating") -> generating | K5: FALSE | N5: ="https://admin.tsip.ai/tasks/"&A5 -> https://admin.tsip.ai/tasks/f0ec3331-b842-4f0f-bc7a-b3aa14727aa1 | O5: FALSE | T5: 46164 | U5: =countifs(E:E,true,G:G,$T5) -> 0 | V5: =countifs(K:K,true,L:L,$T5) -> 0
A6: cb5b1a21-8bce-42c1-807f-d08dcf9df983 | B6: 848b60ba-8233-45dd-a962-e6ba852d7b60 | C6: Jalaj G | D6: =concat("https://www.tsip.ai/force/",A6) -> https://www.tsip.ai/force/cb5b1a21-8bce-42c1-807f-d08dcf9df983 | E6: TRUE | F6: FALSE | G6: 46161 | H6: 55 | I6: =iferror(VLOOKUP(A6,'Decomp Rubrics'!A:B,2,false),"generating") -> generating | K6: FALSE | N6: ="https://admin.tsip.ai/tasks/"&A6 -> https://admin.tsip.ai/tasks/cb5b1a21-8bce-42c1-807f-d08dcf9df983 | O6: FALSE
A7: 4ebd8dfe-d037-41fa-914c-0a150d04cb87 | B7: 848b60ba-8233-45dd-a962-e6ba852d7b60 | C7: Jalaj G | D7: =concat("https://www.tsip.ai/force/",A7) -> https://www.tsip.ai/force/4ebd8dfe-d037-41fa-914c-0a150d04cb87 | E7: TRUE | F7: FALSE | G7: 46161 | H7: 65 | I7: =iferror(VLOOKUP(A7,'Decomp Rubrics'!A:B,2,false),"generating") -> generating | K7: FALSE | N7: ="https://admin.tsip.ai/tasks/"&A7 -> https://admin.tsip.ai/tasks/4ebd8dfe-d037-41fa-914c-0a150d04cb87 | O7: FALSE
A8: 212df67f-c687-4e67-afe9-50edeaab2592 | B8: 874f82c0-6de1-4a82-8270-2c8d51e3dddc | C8: Jared M | D8: =concat("https://www.tsip.ai/force/",A8) -> https://www.tsip.ai/force/212df67f-c687-4e67-afe9-50edeaab2592 | E8: TRUE | F8: TRUE | G8: 46161 | H8: 90 | I8: =iferror(VLOOKUP(A8,'Decomp Rubrics'!A:B,2,false),"generating") -> generating | K8: TRUE | L8: 46162 | M8: 60 | N8: ="https://admin.tsip.ai/tasks/"&A8 -> https://admin.tsip.ai/tasks/212df67f-c687-4e67-afe9-50edeaab2592 | O8: FALSE
A9: 53f5ed76-f45f-4c3d-986c-2aa0015a4bc0 | B9: 874f82c0-6de1-4a82-8270-2c8d51e3dddc | C9: Ava Z | D9: =concat("https://www.tsip.ai/force/",A9) -> https://www.tsip.ai/force/53f5ed76-f45f-4c3d-986c-2aa0015a4bc0 | E9: TRUE | F9: TRUE | G9: 46161 | H9: 150 | I9: Section 1: Formula Correctness 1.1. Is Total New Subscribers in the Core Metrics section on the Revenue Detail tab calculated as the sum of New Annual Subscribers, New Monthly Subscribers, and New Advisor Subscribers? [+2] 1.2. Is Total Subscribers in the Core Metrics section on the Revenue Detail tab calculated as the sum of Annual Subscribers, Monthly Subscribers, and Advisor Subscribers? [+2] 1.3. Is Total ARR in the ARR Summary section on the Revenue Detail tab calculated as the sum of Annual ARR, Monthly ARR, Advisors ARR, and Other ARR? [+2] 1.4. Is Total Revenue in the grand total section on the Revenue Detail tab calculated as the sum of Total Annual+Monthly Revenue, Advisor Revenue, Net Refunds, and Other Revenue? [+2] 1.5. Is Total Revenue in the Annual+Monthly section on the Revenue Detail tab calculated as the sum of Annual Subscription Revenue and Monthly Subscription Revenue? [+1] 1.6. Is Total Billings in the Annual+Monthly section on the Revenue Detail tab calculated as the sum of Annual Billings and Monthly Billings? [+1] 1.7. Is Expansion Billings Only in the Annual+Monthly section on the Revenue Detail tab calculated as the sum of Annual Upgrade Billings and Monthly Upgrade Billings? [+1] 1.8. Is Billings - Monthly on the Revenue Detail tab derived as the simple average of the current period's and next period's Monthly Subscription Revenue rather than a direct sum of billing components? [+2] 1.9. Is the Monthly Conversion to Tier A rate on the Revenue Detail tab capped at 40% using conditional logic that increments by 1 percentage point per period after the initial zero-rate periods? [+3] 1.10. Is Monthly Renewed Subscriber Billings on the Revenue Detail tab derived as total monthly billings minus new subscriber billings (a back-into calculation) rather than a build-up? [+2] 1.11. Is the Monthly ending subscriber rollforward on the Revenue Detail tab computed as beginning subscribers plus new subscribers plus renewals minus churned subscribers? [+2] 1.12. Is Average Revenue per Sub per Month in Core Metrics on the Revenue Detail tab calculated as Total Revenue minus Other Revenue minus Net Refunds minus Advisor Revenue, divided by the sum of ending Annual and Monthly subscribers? [+2] 1.13. Is Total Deferred Revenue in the Deferred Revenue section on the Revenue Detail tab calculated as the sum of Total Annual+Monthly Deferred Revenue, Advisor Deferred Revenue, and Lifetime Deferred Revenue? [+2] 1.14. Is Total Refund % of 12 Mo Billings in the Disputes and Refunds section on the Revenue Detail tab calculated as Total Refunds Pool divided by a trailing 12-month rolling sum of annual billings? [+3] 1.15. Is ARR Growth % in the KPI header area on the Revenue Detail tab calculated as the period-over-period percentage change in the Total ARR line? [+1] Section 2: Model Integration 2.1. Is the Average Billing Rate in the Monthly Subscribers section on the Revenue Detail tab linked to the Monthly Billing Rate on the Omni tab? [+3] 2.2. Is the Subscription Revenue in the Monthly Subscribers section on the Revenue Detail tab linked to the Total Monthly Subscriptions on the Actuals P&L tab? [+3] 2.3. Is the Renewed Subscriber Billings in the Monthly Subscribers section on the Revenue Detail tab linked to the Total Monthly Billings on the Omni tab? [+3] 2.4. Is the Total Deferred Revenue in the Annual plus Monthly section on the Revenue Detail tab linked to the platform deferred revenue lines on the Actuals BS tab? [+3] 2.5. Is the Net Refunds on the Revenue Detail tab linked to the refund and dispute lines on the Actuals P&L tab? [+3] 2.6. Is the Lifetime Deferred Revenue on the Revenue Detail tab linked to the Lifetime membership deferred revenue on the Actuals BS tab? [+2] Section 3: Output Validation 3.1. Is Total ARR on the Revenue Detail tab in the final forecast period (column BP) within +/- 2% of 8,964,888? [+5] 3.2. Is Total Subscribers on the Revenue Detail tab in the final forecast period (column BP) within +/- 2% of 36,498? [+5] 3.3. Is Annualized Billings on the Revenue Detail tab in the final forecast period (column BP) within +/- 2% of 9,082,860? [+5] 3.4. Is Total New Subscribers on the Revenue Detail tab in the last actuals period (column BJ) within +/- 2% of 951? [+5] 3.5. Is Total Deferred Revenue on the Revenue Detail tab in the last actuals period (column BJ) within +/- 2% of 353,498.07? [+5] 3.6. Is Expansion Billings Only on the Revenue Detail tab in the last actuals period (column BJ) within +/- 2% of 20,044.09? [+4] 3.7. Is Total Revenue on the Revenue Detail tab in period 35 within +/- 2% of 432,093.08? [+4] 3.8. Is ARR Growth % on the Revenue Detail tab in the last actuals period within +/- 0.5 pp of 2.7%? [+3] 3.9. Is Total ARR on the Revenue Detail tab in period 25 (column AA) within +/- 2% of 3,389,400? [+3] Section 4: Perturbation 4.1. If the Annual Subscription starting subscribers value on the Revenue Detail tab (period 1, currently 8251) is changed to 16502, does Total Subscribers on the Revenue Detail tab in the Core Metrics section for the same period update to within +/- 2% of the expected value reflecting the doubled annual subscriber count? [+5] 4.2. If the Upgrade Price of Tier A for Monthly Subscribers on the Revenue Detail tab is changed from 19.99 to 39.98 (doubled), does Expansion Billings Only in the Total - Annual + Monthly section update to within +/- 2% of the expected value reflecting doubled monthly upgrade pricing for the final projected period? [+5] 4.3. If the Conversion to Tier A rate for Monthly Subscribers on the Revenue Detail tab is changed from 0% to 20% in the first ramp period (column AC), does Monthly Upgrade Billings for that same period update to within +/- 2% of the expected value reflecting the 20% conversion rate? [+5] 4.4. If the Apple Deferred Revenue balance on the Actuals BS tab for the latest actuals period (column AA) is changed from its current value of 0 to 500000, does Total Deferred Revenue in the Deferred Revenue summary section on the Revenue Detail tab for the corresponding period update to within +/- 2% of the expected value reflecting the 500000 addition? [+5] 4.5. If the ending monthly subscriber count hardcoded on the Revenue Detail tab for period L (currently 894) is changed to 1788 (doubled), does Total Subscribers Excluding Advisory in the Core Metrics section for the same period update to within +/- 2% of the expected value reflecting the doubled monthly subscriber base? [+5] 4.6. If the Sponsor subscriber conversion rate (Converts in Same Month fraction) on the Revenue Detail tab is changed from 0.71 to 0.35 (halved) in column AB, does Total New Subscribers in the Core Metrics section for that period update to within +/- 2% of the expected value reflecting the reduced conversion fraction? [+5] 4.7. If the Annual ending subscriber count hardcoded on the Revenue Detail tab for period Y (currently 7426) is changed to 3713 (halved), does the Average Revenue per Sub per Month in the Revenue per Sub (Excl Advisors) Core Metrics section for that period update to within +/- 2% of the expected value reflecting the halved annual subscriber denominator? [+5] Section 5: Presentation 5.1. Are hardcoded values on the Revenue Detail tab displayed in blue font, formula-driven values in black font, and cross-sheet references in green font? [+2] 5.2. Are dollar-denominated values in the new sections on the Revenue Detail tab formatted with a dollar sign prefix and comma separators with no decimal places, consistent with the existing Annual Subscribers section? [+2] 5.3. Are percentage rows in the new sections on the Revenue Detail tab formatted as percentages with one decimal place, consistent with the existing growth rate and mix rows? [+2] Section 6: Pitfalls 6.1. Are there any error values in the Revenue Detail tab (#REF!, #DIV/0!, #VALUE!, #NAME?, #N/A, #NUM!)? [-5] 6.2. Is any data or label text truncated due to insufficient column widths or row heights in the Revenue Detail tab? [-3] | K9: TRUE | L9: 46162 | M9: 90 | N9: ="https://admin.tsip.ai/tasks/"&A9 -> https://admin.tsip.ai/tasks/53f5ed76-f45f-4c3d-986c-2aa0015a4bc0 | O9: FALSE
A10: 0cf86c7d-efd2-449c-ba36-fd3f8ef9d235 | B10: 874f82c0-6de1-4a82-8270-2c8d51e3dddc | C10: Jared M | D10: =concat("https://www.tsip.ai/force/",A10) -> https://www.tsip.ai/force/0cf86c7d-efd2-449c-ba36-fd3f8ef9d235 | E10: TRUE | F10: TRUE | G10: 46162 | H10: 15 | K10: TRUE | L10: 46162 | M10: 45 | N10: ="https://admin.tsip.ai/tasks/"&A10 -> https://admin.tsip.ai/tasks/0cf86c7d-efd2-449c-ba36-fd3f8ef9d235 | O10: FALSE
A11: 9e7084f5-eb7b-4985-8ff5-e110682dca32 | B11: 874f82c0-6de1-4a82-8270-2c8d51e3dddc | C11: Jared M | D11: =concat("https://www.tsip.ai/force/",A11) -> https://www.tsip.ai/force/9e7084f5-eb7b-4985-8ff5-e110682dca32 | E11: TRUE | F11: TRUE | G11: 46162 | H11: 25 | K11: TRUE | L11: 46162 | M11: 45 | N11: ="https://admin.tsip.ai/tasks/"&A11 -> https://admin.tsip.ai/tasks/9e7084f5-eb7b-4985-8ff5-e110682dca32 | O11: FALSE
A12: 5772657d-c020-44b6-94e5-9d663dce40a6 | B12: 874f82c0-6de1-4a82-8270-2c8d51e3dddc | C12: Jared M | D12: =concat("https://www.tsip.ai/force/",A12) -> https://www.tsip.ai/force/5772657d-c020-44b6-94e5-9d663dce40a6 | E12: FALSE | F12: FALSE | K12: FALSE | N12: ="https://admin.tsip.ai/tasks/"&A12 -> https://admin.tsip.ai/tasks/5772657d-c020-44b6-94e5-9d663dce40a6 | O12: FALSE
A13: ba300a65-ea63-4c81-b690-60c9a9a42c30 | B13: 874f82c0-6de1-4a82-8270-2c8d51e3dddc | C13: Jared M | D13: =concat("https://www.tsip.ai/force/",A13) -> https://www.tsip.ai/force/ba300a65-ea63-4c81-b690-60c9a9a42c30 | E13: FALSE | F13: FALSE | K13: FALSE | N13: ="https://admin.tsip.ai/tasks/"&A13 -> https://admin.tsip.ai/tasks/ba300a65-ea63-4c81-b690-60c9a9a42c30 | O13: FALSE
A14: ee4eea58-d556-41cf-beea-19d9036fb126 | B14: 874f82c0-6de1-4a82-8270-2c8d51e3dddc | C14: Jared M | D14: =concat("https://www.tsip.ai/force/",A14) -> https://www.tsip.ai/force/ee4eea58-d556-41cf-beea-19d9036fb126 | E14: TRUE | F14: TRUE | G14: 46162 | H14: 25 | K14: TRUE | L14: 46163 | M14: 45 | N14: ="https://admin.tsip.ai/tasks/"&A14 -> https://admin.tsip.ai/tasks/ee4eea58-d556-41cf-beea-19d9036fb126 | O14: FALSE
A15: 4cd85cb8-ca9a-42b6-a531-2a9066090578 | B15: 0cddf145-b561-4b9e-81fd-d4dfa1dd1eae | C15: Jalaj G | D15: =concat("https://www.tsip.ai/force/",A15) -> https://www.tsip.ai/force/4cd85cb8-ca9a-42b6-a531-2a9066090578 | E15: FALSE | F15: FALSE | I15: =iferror(VLOOKUP(A15,'Decomp Rubrics'!A:B,2,false),"generating") -> Section 1: Formula Correctness 1.1. Is cumulative units on the Unit Assumptions tab calculated as a running sum of all prior and current year new units sold, using a rolling accumulation pattern? [+2] 1.2. Is cumulative market share on the Unit Assumptions tab derived as cumulative units divided by total addressable market size for the corresponding year? [+1] 1.3. Is the total addressable market size for 2025P through 2029P on the Unit Assumptions tab grown from the prior year using the specified annual growth rates of 1.0%, 0.8%, 0.5%, 0.4%, and 0.4%? [+2] 1.4. Is units with pets on the Unit Assumptions tab calculated as 60% of total market size, and units with non-AA pets as 92% of units with pets? [+1] 1.5. Is YoY units sold growth on the Unit Assumptions tab derived as the current year new units sold divided by the prior year new units sold, minus one? [+1] 1.6. Is Data users as a percent of cumulative Profile units on the Unit Assumptions tab derived as total Data users divided by cumulative Profile units for each year? [+1] 1.7. Is the Growth row on the Revenue Assumptions tab calculated as each vintage year's cost divided by the prior vintage year's cost, minus one? [+1] 1.8. Is the per-unit recognition amount for projected cohort vintages on the Revenue Assumptions tab derived as the 2023 cohort's same-lifecycle-year amount multiplied by the ratio of the projected calendar year cost to 25? [+3] 1.9. Are the 2023 cohort's Year 8 through Year 12 base amounts on the Revenue Assumptions tab grown from the Year 7 base at 5% per lifecycle year before applying the cost ratio scaling? [+2] 1.10. Is cohort revenue on the Revenue Build tab for each projected year calculated as the cohort's unit count multiplied by the applicable per-unit recognition amount for that cohort vintage and lifecycle year? [+2] 1.11. Is Total Profile Revenue on the Revenue Build tab calculated as the sum of all cohort vintage revenue rows plus the Unaffiliated line for each year? [+2] 1.12. Is Data revenue on the Revenue Detail tab for projected years calculated as total Data users from the Unit Assumptions tab multiplied by the revenue per user assumption from Revenue Assumptions? [+2] 1.13. Is Total Revenue on the Revenue Detail tab calculated as the sum of Profile, Data, Atlas Platform, and Other revenue lines for each year? [+2] 1.14. Are the CAGR calculations on the Revenue Detail tab for the 2021-to-2024 and 2023-to-2029 periods derived using the standard compound annual growth rate formula based on end and start values and the number of years? [+2] 1.15. Is the Amt Recognized in Year 8+ per Unit for 2017 row on the Revenue Assumptions tab carried forward from the 2017 cohort's Year 7 actual amount, scaled each projected year by the applicable cost growth rate? [+2] Section 2: Model Integration 2.1. Is the cohort revenue on the Revenue Build tab linked to the per-unit recognition amount on the Revenue Assumptions tab? [+5] 2.2. Is the Profile revenue on the Revenue Detail tab linked to the Total Profile Revenue on the Revenue Build tab? [+4] 2.3. Is the Data revenue on the Revenue Detail tab linked to the Total Users on the Unit Assumptions tab? [+4] 2.4. Is the Data revenue on the Revenue Detail tab linked to the RPU on the Revenue Assumptions tab? [+4] 2.5. Is the cohort unit count on the Revenue Build tab linked to the New Units Sold on the Unit Assumptions tab? [+4] 2.6. Is the New Units Sold on the Unit Assumptions tab linked to the historical cohort units on the Revenue Build tab? [+3] 2.7. Is the Cumulative Units on the Unit Assumptions tab linked to the cohort vintage units on the Revenue Build tab? [+3] 2.8. Is the Total Addressable Market on the Unit Assumptions tab linked to the year labels on the Detailed P&L tab? [+2] Section 3: Output Validation 3.1. Is Total Profile Revenue for 2029P on the Revenue Build tab within +/- 2% of 294,888,940? [+5] 3.2. Is Total Revenue for 2029P on the Revenue Detail tab within +/- 2% of 353,104,940? [+5] 3.3. Is Total Profile Revenue for 2024F on the Revenue Build tab within +/- 2% of 39,543,648? [+5] 3.4. Is cumulative units for 2029P on the Unit Assumptions tab within +/- 2% of 18,374,000? [+3] 3.5. Is Data revenue for 2025P on the Revenue Detail tab within +/- 2% of 8,490,000? [+4] 3.6. Is Total Profile Revenue for 2027P on the Revenue Build tab within +/- 2% of 138,927,480? [+5] 3.7. Is the cumulative market share for 2029P on the Unit Assumptions tab within +/- 0.5 pp of 39.2%? [+4] 3.8. Is Total Revenue for 2024F on the Revenue Detail tab within +/- 2% of 53,770,648? [+5] 3.9. Is the Total Profile Revenue YoY growth rate for 2025P on the Revenue Build tab within +/- 0.5 pp of 62.0%? [+4] Section 4: Perturbation 4.1. If the new units sold (Multi-Family / Single-Family) for 2024F on the Unit Assumptions tab is changed from 1,500,000 to 3,000,000, does Total Profile Revenue for 2024F on the Revenue Build tab update to within +/- 2% of the correctly computed value reflecting doubled 2024 cohort units? [+5] 4.2. If the Share Growth assumption for 2025P on the Unit Assumptions tab is changed from 25% to 50%, does Total Profile Revenue for 2025P on the Revenue Detail tab update to within +/- 2% of the correctly computed value reflecting the higher share growth feeding through units sold to revenue? [+5] 4.3. If the market YoY growth rate for 2025P on the Unit Assumptions tab is changed from 1.0% to 5.0%, does the cumulative units figure for 2025P on the Unit Assumptions tab update to within +/- 2% of the correctly computed value reflecting the larger addressable market? [+5] 4.4. If the Units with Pets percentage on the Unit Assumptions tab is changed from 60% to 30%, does Total Profile Revenue for 2026P on the Revenue Detail tab update to within +/- 2% of the correctly computed value reflecting halved pet-owning unit assumptions flowing through units sold to revenue? [+5] 4.5. If the pets per household (non-AA) multiplier on the Unit Assumptions tab is changed from 1.59 to 3.18, does Total Profile Revenue for 2027P on the Revenue Detail tab update to within +/- 2% of the correctly computed value reflecting doubled pet density assumptions? [+5] 4.6. If the units with non-AA pets percentage on the Unit Assumptions tab is changed from 92% to 46%, does Total Revenue for 2028P on the Revenue Detail tab update to within +/- 2% of the correctly computed value reflecting halved non-AA pet ownership flowing through Profile units sold and Data users to total revenue? [+5] 4.7. If the Share Growth assumption for 2026P on the Unit Assumptions tab is changed from 25% to 50%, does Total Profile Revenue for 2029P on the Revenue Build tab update to within +/- 2% of the correctly computed value reflecting the compounded effect of higher share growth on all subsequent cohort vintages? [+5] Section 5: Presentation 5.1. Are hardcoded assumption values displayed in blue font while formula-driven values use black font and cross-sheet references use green font across the Unit Assumptions and Revenue Build tabs? [+2] 5.2. Are section header rows on the Unit Assumptions tab (Profile, Data) formatted with a yellow-gold fill and bold text's header styling? [+2] 5.3. Are total and subtotal rows on the Revenue Build and Unit Assumptions tabs visually distinguished with bold text? [+2] Section 6: Pitfalls 6.1. Are there any error values in the Unit Assumptions tab, the Detailed P&L tab, the Expense Assumptions tab, the Revenue Assumptions tab, the Revenue Detail tab, and the Revenue Build tab (#REF!, #DIV/0!, #VALUE!, #NAME?, #N/A, #NUM!)? [-5] 6.2. Is any data or label text truncated due to insufficient column widths or row heights in the Unit Assumptions tab, the Detailed P&L tab, the Expense Assumptions tab, the Revenue Assumptions tab, the Revenue Detail tab, and the Revenue Build tab? [-3] | K15: FALSE | N15: ="https://admin.tsip.ai/tasks/"&A15 -> https://admin.tsip.ai/tasks/4cd85cb8-ca9a-42b6-a531-2a9066090578 | O15: FALSE | P15: REF errors in N; skip for now
A16: c27d425f-d821-4e33-aa94-c3578e6381b1 | B16: 0cddf145-b561-4b9e-81fd-d4dfa1dd1eae | C16: Jalaj G | D16: =concat("https://www.tsip.ai/force/",A16) -> https://www.tsip.ai/force/c27d425f-d821-4e33-aa94-c3578e6381b1 | E16: FALSE | F16: FALSE | I16: =iferror(VLOOKUP(A16,'Decomp Rubrics'!A:B,2,false),"generating") -> Section 1: Formula Correctness 1.1. Is each department subtotal on the Detailed P&L calculated as the sum of its Non-Labor sub-row and its Labor sub-row for all periods? [+2] 1.2. Is Total Operating Expenses on the Detailed P&L calculated as the sum of all ten department subtotals (Admin through Atlas Platform)? [+2] 1.3. Is Capitalized Software Development on the Detailed P&L for projected years computed as a negative value based on Software Development expense times the Capitalization Rate, rounded to the nearest hundred? [+2] 1.4. Is Net Operating Expenses on the Detailed P&L calculated as Total Operating Expenses plus Capitalized Software Development (where Capitalized Software Development is negative)? [+1] 1.5. Is EBITDA on the Detailed P&L calculated as Gross Profit minus Net Operating Expenses? [+2] 1.6. Is EBITDA Margin on the Detailed P&L calculated as EBITDA divided by Total Net Revenue? [+1] 1.7. Is Amortization on the Detailed P&L for projected years computed as a negative value, starting at negative $2,500,000 in 2025P and growing at 1.3 times the prior year's value? [+2] 1.8. Is Tax Expense on the Detailed P&L for projected years calculated as negative 3% of EBITDA, rounded to the nearest hundred? [+2] 1.9. Is Total Other Income / (Expenses) on the Detailed P&L computed as the sum of Interest Income, Depreciation, Amortization, Interest, Tax Expense, and Other (net)? [+2] 1.10. Is Net Income on the Detailed P&L calculated as EBITDA plus Total Other Income / (Expenses)? [+1] 1.11. Is Gross Profit on the Summary P&L calculated as Total Net Revenue minus Total Cost of Goods Sold? [+1] 1.12. Is Other Expenses on the Summary P&L for projected years calculated as the negative of the sum of Depreciation, Amortization, Interest, and Tax Expense from the Detailed P&L? [+2] 1.13. Is Total Other Income / (Expenses) on the Summary P&L calculated as Other Income minus Other Expenses? [+1] 1.14. Does the blended core business net margin on the Summary P&L equal one minus the sum of Profile COGS and Data COGS divided by the sum of Profile Net Revenue and Data Net Revenue? [+2] 1.15. Do the YoY growth rates in the Growth Analysis section on the Summary P&L suppress the formula (return blank or empty) when the prior period value is zero? [+3] Section 2: Model Integration 2.1. Is the Capitalized Software Development on the Detailed P&L tab linked to the Capitalization Rate on the Expense Assumptions tab? [+5] 2.2. Is the Staffing Costs operating expense on the Summary P&L tab linked to the Staffing Costs in the non-labor expense detail on the Detailed P&L tab? [+4] 2.3. Is the Admin department margin on the Summary P&L tab linked to the Admin department subtotal on the Detailed P&L tab? [+4] 2.4. Is the operating expense growth rate on the Expense Assumptions tab linked to the operating expense line on the Summary P&L tab? [+4] 2.5. Is the period header row on the Summary P&L tab linked to the period header row on the Detailed P&L tab? [+3] 2.6. Is the Net Income check row on the Summary P&L tab linked to the Net Income on the Detailed P&L tab? [+3] 2.7. Is the COGS growth rate on the Expense Assumptions tab linked to the COGS line item on the Detailed P&L tab? [+3] Section 3: Output Validation 3.1. Is Net Income for 2029P on the Detailed P&L tab within +/- 2% of 44,584,400? [+5] 3.2. Is EBITDA for 2029P on the Detailed P&L tab within +/- 2% of 62,498,200? [+5] 3.3. Is Total Other Income / (Expenses) for 2028P on the Detailed P&L tab within +/- 2% of -13,819,100? [+5] 3.4. Is Net Income for 2029P on the Summary P&L tab within +/- 2% of 44,584,400? [+5] 3.5. Is EBITDA Margin for 2027P on the Detailed P&L tab within +/- 0.5 pp of 24.3%? [+4] 3.6. Is Amortization for 2028P on the Detailed P&L tab within +/- 2% of -5,489,400? [+4] 3.7. Is Total Operating Expenses for 2025P on the Detailed P&L tab within +/- 2% of 42,498,572? [+3] 3.8. Is EBITDA for 2024F on the Detailed P&L tab within +/- 2% of 5,175,097? [+3] 3.9. Is Net Operating Expenses for 2026P on the Summary P&L tab within +/- 2% of 42,766,900? [+5] Section 4: Perturbation 4.1. If the projected Interest Income value on the Detailed P&L tab for 2025P is changed from 300000 to 600000, does the Net Income on the Summary P&L tab for 2025P update to reflect this increase (within +/- 2% of the expected value)? [+5] 4.2. If the projected Amortization value on the Detailed P&L tab for 2025P is changed from -2500000 to -5000000, does the Net Income on the Summary P&L tab for 2029P update to reflect the compounded impact (within +/- 2% of the expected value)? [+5] 4.3. If the projected Depreciation value on the Detailed P&L tab for 2025P is changed from -200000 to -1000000, does the Other Expenses line on the Summary P&L tab for 2025P update to within +/- 2% of the expected value? [+5] 4.4. If the Capitalization Rate on the Expense Assumptions tab is changed from its current value of 0.5 to 0.25, does the EBITDA on the Summary P&L tab for 2027P update to within +/- 2% of the expected value? [+5] 4.5. If the projected Tax Expense percentage assumption on the Detailed P&L tab for 2025P is changed from -3% applied to EBITDA (resulting in the current Tax Expense value) by changing the Tax Expense hardcoded value from its current amount to double that amount, does the Net Income on the Detailed P&L tab for 2025P update to within +/- 2% of the expected value? [+5] 4.6. If the historical Other Income value on the Summary P&L tab for 2021A is changed from 47224.73 to 500000, does the Total Other Income / (Expenses) on the Summary P&L tab for 2021A update to within +/- 2% of the expected value? [+5] 4.7. If the historical Other Expenses value on the Summary P&L tab for 2022A is changed from 1219225.61 to 2400000, does the Net Income on the Summary P&L tab for 2022A update to within +/- 2% of the expected value? [+5] Section 5: Presentation 5.1. Are hardcoded values displayed in blue font, formula-driven values in black font, and cross-sheet references in green font on the Summary P&L and Detailed P&L tabs? [+2] 5.2. Are all non-empty currency values on the Summary P&L and Detailed P&L tabs formatted with thousands separators, no decimal places, and parentheses for negatives? [+2] 5.3. Are total and subtotal rows such as Gross Revenue, Net Operating Expenses, and Net Income on the Summary P&L and Detailed P&L tabs visually distinguished with bold text? [+2] Section 6: Pitfalls 6.1. Are there any error values in the Summary P&L tab, the Detailed P&L tab, and the Expense Assumptions tab (#REF!, #DIV/0!, #VALUE!, #NAME?, #N/A, #NUM!)? [-5] 6.2. Is any data or label text truncated due to insufficient column widths or row heights in the Summary P&L tab, the Detailed P&L tab, and the Expense Assumptions tab? [-3] | K16: FALSE | N16: ="https://admin.tsip.ai/tasks/"&A16 -> https://admin.tsip.ai/tasks/c27d425f-d821-4e33-aa94-c3578e6381b1 | O16: FALSE | P16: REF errors in N; skip for now
A17: 9f73b336-d815-4df1-9696-cec256055a58 | B17: 0cddf145-b561-4b9e-81fd-d4dfa1dd1eae | C17: Jalaj G | D17: =concat("https://www.tsip.ai/force/",A17) -> https://www.tsip.ai/force/9f73b336-d815-4df1-9696-cec256055a58 | E17: FALSE | F17: FALSE | I17: =iferror(VLOOKUP(A17,'Decomp Rubrics'!A:B,2,false),"generating") -> Section 1: Formula Correctness 1.1. Is Gross Revenue on the Detailed P&L calculated as the sum of Profile, Data, Atlas Platform, New Markets, and Other revenue lines for each projection year? [+2] 1.2. Is Total Net Revenue on the Detailed P&L calculated as the sum of Profile Net Revenue, Data Net Revenue, Atlas Platform Net Revenue, and New Markets Net Revenue for each period? [+2] 1.3. Is Profile Net Revenue on the Detailed P&L derived as Profile gross revenue minus Profile Disputes and Profile Refunds for each projection year? [+2] 1.4. Is Atlas Platform Net Revenue on the Detailed P&L derived as Atlas Platform gross revenue minus Atlas Platform Returns and Atlas Platform Discounts for each projection year? [+2] 1.5. Is Gross Profit on the Detailed P&L calculated as Total Net Revenue minus Total COGS for each period? [+2] 1.6. Is Gross Margin on the Detailed P&L calculated as Gross Profit divided by Total Net Revenue for each period? [+1] 1.7. Is FTA Supplies in the COGS section calculated as a percentage of the FTA Fulfillment line item rather than as a percentage of Atlas Platform gross revenue? [+2] 1.8. Is each projected labor department line on the Detailed P&L computed as the beginning-of-year run rate times the fully loaded rate, plus additional new hire salary times the fully loaded rate times a partial-year factor of (12 minus average start month) divided by 12? [+3] 1.9. Are projected labor department amounts on the Detailed P&L rounded to the nearest hundred? [+1] 1.10. Is the beginning-of-year run rate for 2026P onward on the Expense Assumptions tab calculated as the prior year's run rate grown by the ongoing salary growth rate plus the annualized new hire salaries for that department and year? [+3] 1.11. Is Marketing Costs FTA on the Detailed P&L projected as a percentage of the combined Data plus Atlas Platform gross revenue using the rate from the Expense Assumptions tab, rather than using a YoY growth rate? [+2] 1.12. Is Profile Disputes in 2025P on the Detailed P&L calculated as the 2024F implied dispute rate grown by 13%, then multiplied by Profile gross revenue? [+2] 1.13. Is the Total Non-Labor Expenses line on the Detailed P&L computed as the aggregate of all non-labor category subtotals for each period? [+1] 1.14. Does the Additional Labor Expense By Department section on the Expense Assumptions tab aggregate new hire salaries by department for each projection year, with a total row summing across all departments? [+1] 1.15. Is the 2025P beginning-of-year run rate for each department on the Expense Assumptions tab calculated as the 2024F ending run rate multiplied by one plus the first plan year salary growth rate? [+2] Section 2: Model Integration 2.1. Is the Disputes deduction on the Detailed P&L tab linked to the Disputes rate on the Expense Assumptions tab? [+5] 2.2. Is the Profile gross revenue on the Detailed P&L tab linked to the Profile revenue on the Revenue Detail tab? [+4] 2.3. Is the Disputes rate on the Expense Assumptions tab linked to the Disputes amount on the Detailed P&L tab? [+4] Section 3: Output Validation 3.1. Is Total Net Revenue for 2029P on the Detailed P&L tab within +/- 2% of 80,076,830? [+5] 3.2. Is Total COGS for 2029P on the Detailed P&L tab within +/- 2% of 21,539,519? [+5] 3.3. Is Total Non-Labor Expenses for 2029P on the Detailed P&L tab within +/- 2% of 20,785,476? [+5] 3.4. Is Total Labor Expenses for 2029P on the Detailed P&L tab within +/- 2% of 22,003,200? [+5] 3.5. Is EBITDA for 2029P on the Detailed P&L tab within +/- 2% of 15,748,635? [+5] 3.6. Is Gross Margin for 2027P on the Detailed P&L tab within +/- 0.5 pp of 72.6%? [+4] 3.7. Is Gross Profit for 2025P on the Detailed P&L tab within +/- 2% of 36,813,024? [+4] 3.8. Is Total Net Revenue for 2025P on the Detailed P&L tab within +/- 2% of 50,717,498? [+3] 3.9. Is the Total Labor Run Rate for 2027P on the Expense Assumptions tab within +/- 2% of 13,785,416? [+4] 3.10. Is Total Labor Expenses for 2025P on the Detailed P&L tab within +/- 2% of 12,096,100? [+5] Section 4: Perturbation 4.1. If the Atlas Platform gross revenue for 2025P on the Revenue Detail tab is changed from 1,600,000 to 3,200,000, does Total Net Revenue on the Detailed P&L tab for 2025P update to within +/- 2% of the expected value (reflecting doubled Atlas revenue less 70% discounts and other deductions)? [+5] 4.2. If the Fully Loaded Rate on the Expense Assumptions tab is changed from 1.15 to 1.50, does Total Labor Expenses on the Detailed P&L tab for 2025P update to within +/- 2% of the expected value (reflecting a 30% increase in all labor cost calculations)? [+5] 4.3. If the Average Start Month for new hires on the Expense Assumptions tab is changed from 3 to 9, does Total Labor Expenses on the Detailed P&L tab for 2029P update to within +/- 2% of the expected value (reflecting a reduced partial-year factor of 0.25 instead of 0.75 for new hire costs)? [+5] 4.4. If the Atlas Platform gross revenue for 2027P on the Revenue Detail tab is changed from 3,200,000 to 6,400,000, does the Atlas Platform COGS subtotal on the Detailed P&L tab for 2027P update to within +/- 2% of the expected value (reflecting doubled fulfillment, texting, merchant fees, and supplies driven by Atlas revenue)? [+5] 4.5. If the Atlas Platform gross revenue for 2029P on the Revenue Detail tab is changed from 4,800,000 to 2,400,000, does Gross Profit on the Detailed P&L tab for 2029P update to within +/- 2% of the expected value (reflecting halved Atlas revenue flowing through net revenue deductions and COGS)? [+5] 4.6. If the Atlas Platform gross revenue for 2026P on the Revenue Detail tab is changed from 2,400,000 to 4,800,000, does Gross Margin percentage on the Detailed P&L tab for 2026P update to within +/- 0.5 percentage points of the expected value (reflecting doubled Atlas revenue impacting both gross profit and net revenue)? [+5] Section 5: Presentation 5.1. Are hardcoded assumption values displayed in blue font, formula-driven values in black font, and cross-sheet references in green font on both the Detailed P&L and Expense Assumptions tabs? [+2] 5.2. Are all currency values on the Detailed P&L formatted with thousands separators and no decimal places conventions? [+2] 5.3. Are total and subtotal rows on the Detailed P&L (e.g., Gross Revenue, Total Net Revenue, Total COGS, Gross Profit, Total Non-Labor Expenses, Total Labor Expenses) visually distinguished with bold text? [+2] Section 6: Pitfalls 6.1. Are there any error values in the Detailed P&L tab and the Expense Assumptions tab (#REF!, #DIV/0!, #VALUE!, #NAME?, #N/A, #NUM!)? [-5] 6.2. Is any data or label text truncated due to insufficient column widths or row heights in the Detailed P&L tab and the Expense Assumptions tab? [-3] | K17: FALSE | N17: ="https://admin.tsip.ai/tasks/"&A17 -> https://admin.tsip.ai/tasks/9f73b336-d815-4df1-9696-cec256055a58 | O17: FALSE | P17: REF errors in N; skip for now
A18: 9e4e5488-5a4a-4061-879d-466ca0755ccf | B18: 99d2a8db-318f-4435-b03f-a5a8f78c091b | C18: Jared M | D18: =concat("https://www.tsip.ai/force/",A18) -> https://www.tsip.ai/force/9e4e5488-5a4a-4061-879d-466ca0755ccf | E18: TRUE | F18: FALSE | G18: 46162 | H18: 5 | I18: =iferror(VLOOKUP(A18,'Decomp Rubrics'!A:B,2,false),"generating") -> Section 1: Formula Correctness 1.1. Do the new monthly forecast cells on the Summary Budget (June 2024 onward) for flow-item rows such as revenue use a SUMIFS lookup against the relocated Monthly Calcs date header to return values? [+2] 1.2. Are quarterly columns for flow items (e.g., Total Revenue, Total OpEx, Net Income) on the Summary Budget computed as the sum of the three corresponding monthly cells in that quarter? [+2] 1.3. Are quarterly columns for stock/balance items such as Ending Cash Balance and Total Employees on the Summary Budget set equal to the last month of that quarter rather than summing the three months? [+2] 1.4. Are annual columns for flow items on the Summary Budget computed as the sum of the 12 monthly cells for that year rather than referencing a single month or quarterly subtotals? [+2] 1.5. Is the Ending Cash Balance on the Summary Budget for quarterly and annual columns derived as the point-in-time value from the last month of the period, not as a sum of monthly balances? [+2] 1.6. Is the Ending Cash Balance reconciliation on the Summary Budget correctly computed as Beginning Cash plus Total Cash Change for each monthly period? [+2] 1.7. Is Beginning Cash for each monthly column on the Summary Budget equal to the prior month's Ending Cash Balance, maintaining a continuous rollforward? [+2] 1.8. Is Total Cash Change on the Summary Budget computed as the sum of Net Income, cash flow adjustment items (depreciation add-back, capex, debt service, equity financing), not as a difference of ending and beginning cash? [+2] 1.9. Is Gross Margin percentage on the Summary Budget for quarterly and annual columns derived as that period's Gross Profit divided by that period's Total Revenue, not carried from a monthly SUMIFS? [+2] 1.10. Is Total ARR on the Summary Budget for quarterly and annual columns derived as the point-in-time end-of-period balance (referencing the last month), not as a sum of monthly ARR values? [+2] 1.11. Is Consolidated Total ARR on the Summary Budget computed as the sum of the Industrial ARR subtotal and the Automotive ARR subtotal for each period? [+1] 1.12. Are the existing 2023 and Jan-May 2024 SUMIFS formulas on the Summary Budget updated so their lookup range spans the new Monthly Calcs column location rather than the old location? [+2] 1.13. Is the annual column date header for each year on the Summary Budget derived as the YEAR of that year's December date, not hardcoded? [+1] 1.14. Does each new monthly date header on the Summary Budget chain continuously via EOMONTH from the prior month's date, starting from May 2024 through December 2029? [+1] 1.15. Is the Headcount row for each department on the Summary Budget treated as a stock item in quarterly columns, referencing the last month of the quarter instead of summing the three months? [+1] Section 2: Model Integration 2.1. Is the Total Revenue in the Monthly Calcs section on the Summary Budget tab linked to the Total Revenue on the Consolidation Sheet tab? [+5] 2.2. Is the Total Revenue in the Monthly Calcs section on the Summary Budget tab linked to the Total Revenue on the Report Data - P&L tab? [+5] 2.3. Is the Monthly Calcs anchor date on the Summary Budget tab linked to the forecast start date on the Assumptions tab? [+4] 2.4. Is the headcount data on the Summary Budget tab linked to the headcount assumptions on the Assumptions tab? [+4] 2.5. Is the Depreciation and Amortization on the Summary Budget tab linked to the Depreciation and Amortization on the Cash Flow Budget tab? [+4] 2.6. Is the Ending Cash Balance on the Summary Budget tab linked to the Cash and Cash Equivalents on the BS Budget tab? [+4] 2.7. Is the Operating Expenses on the P&L Budget tab linked to the Operating Expenses on the Summary Budget tab? [+4] 2.8. Is the Capital Expenditures on the Summary Budget tab linked to the Capital Expenditures on the Report Data - CFS tab? [+3] 2.9. Is the Other Expenses on the Summary Budget tab linked to the Other Expenses on the 5. Other tab? [+3] 2.10. Is the Total Employees on the Report Data - P&L tab linked to the Total Employees on the Summary Budget tab? [+3] Section 3: Output Validation 3.1. Is the 2029 annual Total Revenue on the Summary Budget tab within +/- 2% of 91,725,001? [+5] 3.2. Is the 2029 annual Ending Cash Balance on the Summary Budget tab within +/- 2% of 53,155,784? [+5] 3.3. Is the 2029 annual Net Income on the Summary Budget tab within +/- 2% of 14,893,590? [+5] 3.4. Is the 2028 annual Ending Cash Balance on the Summary Budget tab within +/- 2% of 38,549,494? [+5] 3.5. Is the 2024 annual Total Revenue on the Summary Budget tab within +/- 2% of 31,149,738? [+3] 3.6. Is the 2025 annual Gross Profit on the Summary Budget tab within +/- 2% of 24,143,838? [+4] 3.7. Is the 2027 annual Gross Margin percentage on the Summary Budget tab within +/- 0.5 pp of 67.5%? [+4] 3.8. Is the 2026 annual Total Operating Expenses on the Summary Budget tab within +/- 2% of 18,821,159? [+3] 3.9. Is the 2029 annual Total Employees (headcount) on the Summary Budget tab within +/- 2% of 148? [+5] 3.10. Is the 2028 annual Total Employees (headcount) on the Summary Budget tab within +/- 2% of 124? [+4] Section 4: Perturbation 4.1. If the Consolidation Sheet forecast value for the Network Infrastructure revenue line in the first month showing 250,000 (corresponds to approximately October 2024) is changed from 250,000 to 500,000, does the corresponding monthly revenue value on the Summary Budget tab for that forecast month update to reflect the doubled input, within +/- 2% of the expected value? [+5] 4.2. If the Consolidation Sheet forecast value for the Industrial segment revenue line showing 400,000 (corresponding to approximately August 2024) is changed from 400,000 to 800,000, does the Total Revenue on the Summary Budget tab for the 2024 annual column update to within +/- 2% of the expected value reflecting this doubling? [+5] 4.3. If the Consolidation Sheet forecast value for the Industrial segment revenue line showing 1,636,000 (corresponding to approximately January 2025) is changed from 1,636,000 to 3,272,000, does the first monthly revenue cell in the 2025 section on the Summary Budget tab update to within +/- 2% of the expected doubled value? [+5] 4.4. If the Consolidation Sheet forecast value for the segment cost line showing 545,333 (corresponding to approximately February 2025) is changed from 545,333 to 1,090,667, does the corresponding monthly value on the Summary Budget tab for February 2025 update to within +/- 2% of the expected doubled value? [+5] 4.5. If the Consolidation Sheet forecast value for the Network Infrastructure line showing 465,000 (corresponding to approximately January 2025) is changed from 465,000 to 930,000, does the Q1 2025 quarterly total revenue on the Summary Budget tab update to within +/- 2% of the expected value reflecting this increase? [+5] 4.6. If the Consolidation Sheet forecast value for the segment revenue line showing 600,000 (corresponding to approximately November 2024) is changed from 600,000 to 1,200,000, does the Net Cash Change on the Cash Flow Budget tab for the corresponding month update to within +/- 2% of the expected value reflecting this revenue doubling? [+5] 4.7. If the Consolidation Sheet forecast value for the Network Infrastructure line showing 333,333 (corresponding to approximately December 2024) is changed from 333,333 to 666,667, does the 2024 annual total revenue on the Summary Budget tab update to within +/- 2% of the expected value reflecting this increase? [+5] Section 5: Presentation 5.1. Are all non-empty numeric values in the newly extended columns of the Summary Budget formatted with comma separators and no decimal places, consistent with the existing 2023 and early-2024 sections? [+2] 5.2. Are total and subtotal rows in the newly extended Summary Budget columns visually distinguished with bold text and light blue fill color of the existing year sections? [+2] 5.3. Are percentage rows such as Gross Margin and revenue mix in the newly extended Summary Budget columns formatted as percentages with zero decimal places, consistent with the existing sections? [+2] Section 6: Pitfalls 6.1. Are there any error values in the P&L Budget tab, the Summary Budget tab, the BS Budget tab, the Cash Flow Budget tab, the 2. Mobile tab, the 3. Logistics & Mapping tab, the 4. Robotics & Automation tab, the 5. Other tab, and the Report Data - P&L tab (#REF!, #DIV/0!, #VALUE!, #NAME?, #N/A, #NUM!)? [-5] 6.2. Is any data or label text truncated due to insufficient column widths or row heights in the P&L Budget tab, the Summary Budget tab, the BS Budget tab, the Cash Flow Budget tab, the 2. Mobile tab, the 3. Logistics & Mapping tab, the 4. Robotics & Automation tab, the 5. Other tab, and the Report Data - P&L tab? [-3] | K18: FALSE | N18: ="https://admin.tsip.ai/tasks/"&A18 -> https://admin.tsip.ai/tasks/9e4e5488-5a4a-4061-879d-466ca0755ccf | O18: FALSE
A19: 7bdb5914-3b20-4748-9e7a-314750f41e79 | B19: 99d2a8db-318f-4435-b03f-a5a8f78c091b | C19: Jared M | D19: =concat("https://www.tsip.ai/force/",A19) -> https://www.tsip.ai/force/7bdb5914-3b20-4748-9e7a-314750f41e79 | E19: TRUE | F19: FALSE | G19: 46162 | H19: 5 | I19: =iferror(VLOOKUP(A19,'Decomp Rubrics'!A:B,2,false),"generating") -> Section 1: Formula Correctness 1.1. Is Total Bookings on the P&L Budget Forecast section calculated as the sum of its three component Bookings line items (Industrial, Automotive, Other) within each column? [+2] 1.2. Is Total Billings on the P&L Budget Forecast section calculated as the sum of its component Billings line items within each column? [+2] 1.3. Is Total Revenue on the P&L Budget Forecast section derived as the sum of its component Revenue line items within each column? [+1] 1.4. Is Gross Margin on the P&L Budget Forecast section derived as Total Revenue minus the sum of COGS items within the same column? [+2] 1.5. Is Gross Margin Percent on the P&L Budget Forecast section calculated by dividing Gross Margin by Total Revenue for the same column? [+1] 1.6. Is EBITDA on the P&L Budget Forecast section derived as Gross Margin minus Total Operating Expenses plus Other Income/Expense within each column? [+2] 1.7. Are quarterly roll-up columns for flow items like Revenue and Bookings on the P&L Budget computed as the sum of the three constituent monthly columns? [+2] 1.8. Are quarterly roll-up columns for Total Backlog on the P&L Budget computed by referencing only the last monthly column of that quarter, not summing all three months? [+2] 1.9. Are quarterly roll-up columns for Average FTE on the P&L Budget computed as the average of the three constituent monthly values, not a sum? [+2] 1.10. Are annual roll-up columns for flow items on the P&L Budget computed as the sum of the four quarterly roll-up columns for that year? [+2] 1.11. Is the annual Opex Per Average FTE on the P&L Budget computed as annual Total Operating Expenses divided by the average of twelve monthly Average FTE values? [+3] 1.12. Is the quarterly Opex Per Average FTE for 2024 and 2025 on the P&L Budget computed as quarterly operating expenses multiplied by 4 then divided by quarterly Average FTE? [+3] 1.13. Is Total Operating Expenses by Department on the P&L Budget Forecast section calculated as the sum of its six departmental operating expense line items? [+1] 1.14. Are annual roll-up columns for Average FTE on the P&L Budget computed as the average of all twelve monthly Average FTE values for that year? [+2] Section 2: Model Integration 2.1. Is the Industrial Billings on the BS Budget tab linked to the Industrial Billings in the Monthly Calcs section on the P&L Budget tab? [+5] 2.2. Is the Industrial Revenue in the Monthly Calcs section on the P&L Budget tab linked to the Industrial Revenue on the Summary Budget tab? [+4] 2.3. Is the Industrial Backlog in the Monthly Calcs section on the P&L Budget tab linked to the Industrial Backlog on the Report Data - P&L tab? [+4] 2.4. Is the Industrial Billings in the Monthly Calcs section on the P&L Budget tab linked to the Accounts Receivable on the BS Budget tab? [+4] 2.5. Is the Industrial Backlog in the Monthly Calcs section on the P&L Budget tab linked to the Total Backlog on the Consolidation Sheet tab? [+4] 2.6. Is the Product Cost in the Monthly Calcs section on the P&L Budget tab linked to the Product Cost on the Summary Budget tab? [+4] 2.7. Is the Sales and Marketing expense in the Monthly Calcs section on the P&L Budget tab linked to the Sales and Marketing components on the Summary Budget tab? [+4] 2.8. Is the Eliminations Bookings in the Monthly Calcs section on the P&L Budget tab linked to the Eliminations on the Consolidation Sheet tab? [+3] 2.9. Is the Other Bookings in the Monthly Calcs section on the P&L Budget tab linked to the Bookings on the 5. Other tab? [+3] 2.10. Is the Monthly Calcs start date on the P&L Budget tab linked to the start date on the Assumptions tab? [+3] Section 3: Output Validation 3.1. Is the Total Revenue for the 2029 annual column on the P&L Budget tab within +/- 2% of 96,891,498? [+5] 3.2. Is the EBITDA for the 2029 annual column on the P&L Budget tab within +/- 2% of 18,820,281? [+5] 3.3. Is the Net Income for the 2028 annual column on the P&L Budget tab within +/- 2% of 14,959,363? [+5] 3.4. Is the Ending Cash Balance for the 2029 annual column on the P&L Budget tab within +/- 2% of 5,736,802? [+5] 3.5. Is the Total Revenue for the 2025 annual column on the P&L Budget tab within +/- 2% of 55,338,474? [+3] 3.6. Is the Gross Margin Percent for the 2024 annual column on the P&L Budget tab within +/- 0.5 pp of 56.5%? [+4] 3.7. Is the Total Operating Expenses for the 2028 annual column on the P&L Budget tab within +/- 2% of 35,728,765? [+4] 3.8. Is the Gross Margin for the 2026 annual column on the P&L Budget tab within +/- 2% of 39,694,920? [+4] 3.9. Is the Average FTE for the 2027 annual column on the P&L Budget tab within +/- 2% of 157.25? [+3] 3.10. Is the Total Bookings for the 2029 annual column on the P&L Budget tab within +/- 2% of 102,012,600? [+5] Section 4: Perturbation 4.1. If the Bookings value for the Network Infrastructure segment on the Consolidation Sheet (row 46, corresponding to the month feeding into October 2024 forecasts) is changed from 250000 to 625000, does the Total Bookings line on the P&L Budget tab for the 2024 Annual roll-up column update to within +/- 2% of the correctly recomputed value? [+5] 4.2. If the Billings value on the Consolidation Sheet for the month corresponding to March 2024 in row 60 is changed from 1636000 to 3272000, does the Industrial Billings line on the BS Budget tab for that same period update to within +/- 2% of the correctly recomputed value? [+5] 4.3. If the Bookings value on the Consolidation Sheet for the month feeding September 2024 in the Network Infrastructure segment (row 46) is changed from 333333.3333333333 to 666666.6666666666, does the Total Bookings line on the P&L Budget for the 2025 Annual roll-up update to within +/- 2% of the correctly recomputed value? [+5] 4.4. If the Billings value on the Consolidation Sheet for the Industrial segment in the month corresponding to November 2023 (row 60, feeding into BS Budget billings) is changed from 400000 to 800000, does the Industrial Billings value on the BS Budget tab for the corresponding November 2023 period update to within +/- 2% of 800000? [+5] 4.5. If the Bookings value on the Consolidation Sheet for the Network Infrastructure segment in the month feeding January 2025 (row 46) is changed from 465000 to 930000, does the Total Bookings line on the P&L Budget for the Q1 2025 quarterly roll-up update to within +/- 2% of the correctly recomputed value? [+5] 4.6. If the Bookings value on the Consolidation Sheet for the Industrial segment in the month feeding June 2024 (row 60) is changed from 600000 to 1200000, does the Total Billings line on the P&L Budget for the 2024 Annual roll-up column update to within +/- 2% of the correctly recomputed value? [+5] 4.7. If the added constant for COGS-related data on the P&L Budget (cell GI75, a Monthly Calcs value) is changed from 201932.91 to 403865.82, does the Gross Margin line on the P&L Budget for the 2029 Annual roll-up update to within +/- 2% of the correctly recomputed value reflecting the doubled cost? [+5] Section 5: Presentation 5.1. Are all non-empty currency values in the new Forecast section of the P&L Budget formatted with dollar sign prefix, thousands separators, and no decimal places, consistent with the Actuals columns? [+2] 5.2. Are hardcoded values in the P&L Budget Forecast section displayed in blue font while formula-driven values use green or black font, following the model's color-coding convention? [+2] 5.3. Are total and subtotal rows in the P&L Budget Forecast section visually distinguished with bold text and a light blue fill color, matching the styling of the Actuals section? [+2] Section 6: Pitfalls 6.1. Are there any error values in the P&L Budget tab, the BS Budget tab, the 2. Mobile tab, the 3. Logistics & Mapping tab, the 4. Robotics & Automation tab, and the 5. Other tab (#REF!, #DIV/0!, #VALUE!, #NAME?, #N/A, #NUM!)? [-5] 6.2. Is any data or label text truncated due to insufficient column widths or row heights in the P&L Budget tab, the BS Budget tab, the 2. Mobile tab, the 3. Logistics & Mapping tab, the 4. Robotics & Automation tab, and the 5. Other tab? [-3] | K19: FALSE | N19: ="https://admin.tsip.ai/tasks/"&A19 -> https://admin.tsip.ai/tasks/7bdb5914-3b20-4748-9e7a-314750f41e79 | O19: FALSE
A20: 320b10a2-7b9c-443d-bc9f-47dd6469ccc2 | B20: 99d2a8db-318f-4435-b03f-a5a8f78c091b | C20: Ava Z | D20: =concat("https://www.tsip.ai/force/",A20) -> https://www.tsip.ai/force/320b10a2-7b9c-443d-bc9f-47dd6469ccc2 | E20: TRUE | F20: FALSE | G20: 46162 | H20: 30 | I20: Section 1: Formula Correctness 1.1. Is Depreciation in the staging area of the Cash Flow Budget tab sign-flipped (negated) relative to the Summary Budget depreciation line so it appears as a positive cash add-back? [+2] 1.2. Is the Total Changes in Assets and Liabilities row on the Cash Flow Budget tab computed as the sum of its constituent working capital line items within each monthly column? [+2] 1.3. Is Net Cash Provided by Operating Activities on the Cash Flow Budget tab calculated as the sum of Net Income, Depreciation, and Total Changes in Assets and Liabilities? [+2] 1.4. Is Net Cash Used in Investing Activities on the Cash Flow Budget tab calculated as the sum of its investing component line items within each column? [+1] 1.5. Is Net Cash from Financing Activities on the Cash Flow Budget tab calculated as the sum of its financing component line items within each column? [+1] 1.6. Is the Net Change in Cash on the Cash Flow Budget tab derived as the sum of operating, investing, and financing subtotals? [+2] 1.7. Is Ending Cash on the Cash Flow Budget tab computed as Beginning Cash plus Net Change in Cash plus any other cash adjustments in the same column? [+2] 1.8. Are quarterly summary columns on the Cash Flow Budget tab computed as the direct sum of their three constituent monthly columns for every line item? [+2] 1.9. Are annual total columns on the Cash Flow Budget tab computed as the direct sum of their four constituent quarterly columns for every line item? [+2] 1.10. Do working capital line items in the staging area compute each month's change as the prior month-end balance minus the current month-end balance from the BS Budget for asset items? [+2] 1.11. Do liability working capital line items in the staging area compute each month's change as the current month-end balance minus the prior month-end balance from the BS Budget? [+2] 1.12. Do forecast monthly columns in the main presentation area of the Cash Flow Budget pull each line item via a conditional sum matching the column date against the staging area date row? [+1] 1.13. Does the staging area check row verify that the computed ending cash equals the corresponding month's cash balance from the BS Budget? [+1] 1.14. Is the annual header for each year group on the Cash Flow Budget tab derived from the date of the last month in that year rather than being hardcoded? [+1] Section 2: Model Integration 2.1. Is the Accounts Receivable on the Cash Flow Budget tab linked to the Cash and Cash Equivalents on the BS Budget tab? [+5] 2.2. Is the Net Income on the Cash Flow Budget tab linked to the Net Income on the Summary Budget tab? [+4] 2.3. Is the Depreciation and Amortization on the Cash Flow Budget tab linked to the Depreciation and Amortization on the Summary Budget tab? [+4] 2.4. Is the Beginning Cash Balance on the Cash Flow Budget tab linked to the Cash and Cash Equivalents on the BS Budget tab? [+4] 2.5. Is the Accounts Receivable on the Summary Budget tab linked to the Accounts Receivable on the Cash Flow Budget tab? [+4] 2.6. Is the Actual or Forecast label on the Cash Flow Budget tab linked to the Forecast Start on the Assumptions tab? [+3] 2.7. Is the Check to CFS on the Summary Budget tab linked to the Net Cash from Operating Activities on the Cash Flow Budget tab? [+3] Section 3: Output Validation 3.1. Is the Ending Cash for the 2024 annual total on the Cash Flow Budget tab within +/- 2% of 13382548.82? [+5] 3.2. Is the Ending Cash for the 2029 annual total on the Cash Flow Budget tab within +/- 2% of 63convey let me re-read precisely.? [+5] 3.3. Is the Ending Cash for the 2029 annual total on the Cash Flow Budget tab within +/- 2% of 63038498.16? [+5] 3.5. Is the Net Cash from Operating Activities for the 2027 annual total on the Cash Flow Budget tab within +/- 2% of 12498498.60? [+5] 3.6. Is the Net Change in Cash for the 2029 annual total on the Cash Flow Budget tab within +/- 2% of 12219498.60? [+5] 3.7. Is the Net Cash from Operating Activities for Q3 2024 on the Cash Flow Budget tab within +/- 2% of 2216624.71? [+4] 3.8. Is the Total Changes in Assets and Liabilities for the 2026 annual total on the Cash Flow Budget tab within +/- 2% of -1555950.00? [+4] 3.9. Is the Net Cash from Operating Activities for the 2025 annual total on the Cash Flow Budget tab within +/- 2% of 8802498.60? [+3] 3.10. Is the Beginning Cash for the 2028 annual total on the Cash Flow Budget tab within +/- 2% of 38599500.96? [+5] 3.11. Is the Ending Cash for the 2026 annual total on the Cash Flow Budget tab within +/- 2% of 26380002.36? [+5] Section 4: Perturbation 4.1. If the Cash & Cash Equivalents value on the BS Budget tab for the end of December 2022 (the beginning balance reference point) is changed from 18455246.45 to 27682870, does the Beginning Cash balance on the Cash Flow Budget tab for the 2023 annual total update to reflect this change, showing a value within +/- 2% of 27682870? [+5] 4.2. If the Accounts Receivable balance on the BS Budget tab for the end of January 2023 is changed from 763062.72 to 1526125.44, does the 2023 annual total for Changes in Accounts Receivable on the Cash Flow Budget tab update to within +/- 2% of the correctly recomputed value (approximately 1136121.10 minus change propagation through AR differences)? [+5] 4.3. If the Inventory balance on the BS Budget tab for the end of January 2023 is changed from 2607621.11 to 1303810.56, does the 2023 annual total for Changes in Inventory on the Cash Flow Budget tab update to within +/- 2% of the recomputed value (approximately reflecting the larger Jan 2023 inventory decrease)? [+5] 4.4. If the Prepaids & Other Current Assets balance on the BS Budget tab for end of January 2023 is changed from 580837.94 to 1161675.88, does the 2023 annual total for Changes in Prepaids on the Cash Flow Budget tab update to within +/- 2% of the recomputed value (approximately reflecting the larger Jan 2023 prepaids increase)? [+5] 4.5. If the Cash & Cash Equivalents balance on the BS Budget tab for the end of October 2023 is changed from 850203.28 to 425101.64, does the Ending Cash on the Cash Flow Budget tab for the Q4 2023 quarterly summary update to within +/- 2% of the recomputed value (reflecting the changed beginning cash for November 2023)? [+5] 4.6. If the Accounts Receivable balance on the BS Budget tab for the end of September 2023 is changed from 4760852.36 to 2380426.18, does the 2023 annual total for Total Changes in Assets and Liabilities on the Cash Flow Budget tab update to within +/- 2% of the recomputed value reflecting the large AR swing? [+5] 4.7. If the Inventory balance on the BS Budget tab for the end of December 2022 is changed from 2628920.60 to 5257841.20, does the January 2023 monthly column on the Cash Flow Budget tab for Changes in Inventory update to within +/- 2% of the recomputed value (approximately reflecting the doubled starting inventory creating a larger decrease)? [+5] Section 5: Presentation 5.1. Are all numeric values on the new Cash Flow Budget columns formatted with comma separators, no decimal places, and parentheses for negatives, consistent with the existing prior-year columns? [+2] 5.2. Are subtotal and total rows on the Cash Flow Budget tab (operating, investing, financing, and net change) styled with bold font and green fill to match the existing year columns? [+2] 5.3. Do formula-driven cells in the new Cash Flow Budget columns use green font observed across the existing model tabs? [+2] Section 6: Pitfalls 6.1. Are there any error values in the Summary Budget tab, the Cash Flow Budget tab, the 2. Mobile tab, the 3. Logistics & Mapping tab, the 4. Robotics & Automation tab, and the 5. Other tab (#REF!, #DIV/0!, #VALUE!, #NAME?, #N/A, #NUM!)? [-5] 6.2. Is any data or label text truncated due to insufficient column widths or row heights in the Summary Budget tab, the Cash Flow Budget tab, the 2. Mobile tab, the 3. Logistics & Mapping tab, the 4. Robotics & Automation tab, and the 5. Other tab? [-3] | K20: FALSE | N20: ="https://admin.tsip.ai/tasks/"&A20 -> https://admin.tsip.ai/tasks/320b10a2-7b9c-443d-bc9f-47dd6469ccc2 | O20: FALSE
A21: 3ee14907-f96b-4884-9150-b5e6a8366bdc | B21: 99d2a8db-318f-4435-b03f-a5a8f78c091b | C21: Jared M | D21: =concat("https://www.tsip.ai/force/",A21) -> https://www.tsip.ai/force/3ee14907-f96b-4884-9150-b5e6a8366bdc | E21: TRUE | F21: TRUE | G21: 46162 | H21: 5 | I21: =iferror(VLOOKUP(A21,'Decomp Rubrics'!A:B,2,false),"generating") -> Section 1: Formula Correctness 1.1. Is the first period start date in the annual header row on the Consolidation Sheet hardcoded as January 1, 2023? [+1] 1.2. Are subsequent period start dates in the annual header derived incrementally by adding one year to the previous start date, producing January 1 for 2024 through 2029? [+2] 1.3. Is the first period end date in the annual header on the Consolidation Sheet hardcoded as December 31, 2023? [+1] 1.4. Are subsequent period end dates in the annual header derived incrementally by adding one year to the previous end date, producing December 31 for 2024 through 2029? [+2] 1.5. Is the year integer row on the Consolidation Sheet derived by extracting the year from the corresponding period end date in the header? [+1] 1.6. Does the aggregation formula for Sum-type rows on the Consolidation Sheet sum monthly values where the monthly date falls between the period start and end dates inclusively? [+3] 1.7. Does the aggregation formula for Average-type rows on the Consolidation Sheet average monthly values within the date range while excluding zero values from the average? [+3] 1.8. Does the aggregation formula for EOP-type rows on the Consolidation Sheet return the monthly value whose date exactly matches the period end date only? [+3] 1.9. Is the aggregation type for Bookings section rows on the Consolidation Sheet set to Sum? [+1] 1.10. Is the aggregation type for Backlog section rows on the Consolidation Sheet set to EOP? [+2] 1.11. Is the aggregation type for Subscribers section rows on the Consolidation Sheet set to Average? [+2] 1.12. Is the aggregation type for all Revenue subsection rows (Aurora, Comet, Hardware, Services, and All) on the Consolidation Sheet set to Sum? [+1] 1.13. Do all annual aggregation formulas on the Consolidation Sheet return zero when an error occurs, via error-wrapping logic? [+1] 1.14. Do subsequent rows within each metric section on the Consolidation Sheet inherit their aggregation type by referencing the first row of that section rather than hardcoding the type? [+2] Section 3: Output Validation 3.1. Is the Total Cedarbrook Bookings (Sum) for FY 2029 on the Consolidation Sheet within +/- 2% of 1316924? [+5] 3.2. Is the Total Cedarbrook Backlog (EOP) for FY 2029 on the Consolidation Sheet within +/- 2% of 1893498? [+5] 3.3. Is the Total Cedarbrook Revenue All (Sum) for FY 2027 on the Consolidation Sheet within +/- 2% of 694498? [+5] 3.4. Is the Total Cedarbrook Revenue All (Sum) for FY 2029 on the Consolidation Sheet within +/- 2% of 1148498? [+5] 3.5. Is the Total Cedarbrook Billings (Sum) for FY 2026 on the Consolidation Sheet within +/- 2% of 480866? [+5] 3.6. Is the Total Cedarbrook Product COGS (Sum) for FY 2028 on the Consolidation Sheet within +/- 2% of 339683? [+5] 3.7. Is the Total Cedarbrook Subscribers (Average) for FY 2025 on the Consolidation Sheet within +/- 2% of 1096? [+4] 3.8. Is the Total Cedarbrook Bookings (Sum) for FY 2023 on the Consolidation Sheet within +/- 2% of 128133? [+3] 3.9. Is the Industrial subtotal Revenue All (Sum) for FY 2026 on the Consolidation Sheet within +/- 2% of 286614? [+4] Section 4: Perturbation 4.1. If the period start date on the Consolidation Sheet (first year start date in the annual aggregation header, row 7) is changed from January 1, 2023 to January 1, 2024, does the Total Cedarbrook Product COGS annual Sum for 2023 on the Consolidation Sheet update to zero or near-zero (since no monthly data would fall within a range starting 2024 and ending 2023)? [+5] Section 5: Presentation 5.1. Are all annual numeric values on the Consolidation Sheet formatted with thousands separators and no decimal places, consistent with the existing monthly source data area? [+2] 5.2. Are subtotal and total rows in the annual columns on the Consolidation Sheet visually distinguished with bold font and light gray fill? [+2] Section 6: Pitfalls 6.1. Are there any error values in the Consolidation Sheet tab, the 2. Mobile tab, the 3. Logistics & Mapping tab, the 4. Robotics & Automation tab, and the 5. Other tab (#REF!, #DIV/0!, #VALUE!, #NAME?, #N/A, #NUM!)? [-5] 6.2. Is any data or label text truncated due to insufficient column widths or row heights in the Consolidation Sheet tab, the 2. Mobile tab, the 3. Logistics & Mapping tab, the 4. Robotics & Automation tab, and the 5. Other tab? [-3] | K21: TRUE | L21: 46162 | M21: 15 | N21: ="https://admin.tsip.ai/tasks/"&A21 -> https://admin.tsip.ai/tasks/3ee14907-f96b-4884-9150-b5e6a8366bdc | O21: FALSE
A22: d4097001-c960-449f-883c-5ae8ef80cc38 | B22: 99d2a8db-318f-4435-b03f-a5a8f78c091b | C22: Jared M | D22: =concat("https://www.tsip.ai/force/",A22) -> https://www.tsip.ai/force/d4097001-c960-449f-883c-5ae8ef80cc38 | E22: TRUE | F22: TRUE | G22: 46162 | H22: 5 | I22: =iferror(VLOOKUP(A22,'Decomp Rubrics'!A:B,2,false),"generating") -> Section 1: Formula Correctness 1.1. Is the annual value formula on the Mobile tab for rows marked 'Sum' computed as the sum of monthly values whose dates fall within that column's January 1 to December 31 window? [+2] 1.2. Is the annual value formula on the Mobile tab for rows marked 'Average' computed as the average of non-zero monthly values whose dates fall within that column's January 1 to December 31 window? [+3] 1.3. Is the annual value formula on the Mobile tab for rows marked 'EOP' computed as the value from the single month matching exactly the December 31 date for that year? [+2] 1.4. Does every annual value formula on the Mobile tab wrap the entire conditional logic in an error-trapping function that returns zero on error? [+1] 1.5. Is the aggregation type indicator for Bookings rows on the Mobile tab set to 'Sum' for both the summary section and the Aurora DGNSS detail section? [+1] 1.6. Is the aggregation type indicator for Revenue rows on the Mobile tab set to 'Sum' for both the summary section and all detail sections? [+1] 1.7. Is the aggregation type indicator for Backlog rows in the Aurora DGNSS detail section on the Mobile tab set to 'EOP' rather than 'Sum'? [+2] 1.8. Is the aggregation type indicator for Aurora DGNSS Units rows on the Mobile tab set to 'Average' in both the summary section and the deal-cohort detail section? [+2] 1.9. Is the aggregation type indicator for ASP rows on the Mobile tab set to 'Average' in both the summary and detail sections? [+2] 1.10. Is the aggregation type indicator for Non-Aurora Units rows (Comet, Services, Ranger) on the Mobile tab set to 'Sum' rather than 'Average'? [+2] 1.11. Are the second-label-row dates in the annual header on the Mobile tab correctly set to December 31 of each year from 2023 through 2029, each derived by stepping one year forward? [+1] 1.12. Are the first-label-row dates in the annual header on the Mobile tab correctly set to January 1 of each year from 2023 through 2029, each derived by stepping one year forward? [+1] 1.13. Is the year-number row on the Mobile tab derived from the December 31 date in each annual column, yielding years 2023 through 2029? [+1] 1.14. Do subsequent rows within each metric group on the Mobile tab reference the aggregation type from the first row of that group rather than hardcoding the type string? [+1] Section 3: Output Validation 3.1. Is the annual Bookings All total for 2029 on the 2. Mobile tab within +/- 2% of 8622720? [+5] 3.2. Is the annual Revenue All total for 2027 on the 2. Mobile tab within +/- 2% of 10174605? [+5] 3.3. Is the annual Backlog All value for 2028 on the 2. Mobile tab within +/- 2% of 10768530? [+5] 3.4. Is the annual Gross Margin All total for 2029 on the 2. Mobile tab within +/- 2% of 6487897.5? [+5] 3.5. Is the annual Billings All total for 2025 on the 2. Mobile tab within +/- 2% of 5945070? [+4] 3.6. Is the annual No. of Deals summary value for 2024 on the 2. Mobile tab within +/- 2% of 6? [+3] 3.7. Is the Aurora DGNSS detail Units average for 2026 on the 2. Mobile tab within +/- 2% of 3325? [+4] 3.8. Is the Non-Aurora Comet Units annual sum for 2025 on the 2. Mobile tab within +/- 2% of 78? [+4] Section 4: Perturbation 4.1. If the monthly Bookings value for January 2025 on the 2. Mobile tab (the first monthly data column for that row in the summary Bookings section, row 13) is changed from its current value to 5000000, does the annual Bookings figure for 2025 in the summary section on the 2. Mobile tab update accordingly to reflect the new sum, within +/- 2% of the expected value? [+5] 4.2. If the monthly Revenue value for January 2026 on the 2. Mobile tab (summary Revenue section, row 31) is changed from its current value to 3000000, does the annual Revenue figure for 2026 in the summary section on the 2. Mobile tab update to reflect the modified sum, within +/- 2% of the expected value? [+5] 4.3. If a monthly ASP value in the Aurora DGNSS summary Average row (row 58) for March 2025 on the 2. Mobile tab is changed from 0 to 25000, does the annual ASP Average figure for 2025 on the 2. Mobile tab update to reflect the new average including non-zero values, within +/- 2% of the expected value? [+5] 4.4. If the monthly Backlog EOP value for December 2027 in the Aurora DGNSS detail section (row 333) on the 2. Mobile tab is changed from 0 to 8000000, does the annual EOP Backlog figure for 2027 on the 2. Mobile tab update to match the December end-of-period value, within +/- 2% of 8000000? [+5] 4.5. If the monthly Units value for the Aurora DGNSS detail Average row (row 165) for June 2026 on the 2. Mobile tab is changed from 0 to 500, does the annual Units Average figure for 2026 on the 2. Mobile tab update to reflect the new non-zero average, within +/- 2% of the expected value? [+5] 4.6. If the monthly Billings value for February 2028 in the Non-Aurora detail section (row 397) on the 2. Mobile tab is changed from 0 to 2000000, does the annual Billings Sum figure for 2028 on the 2. Mobile tab update to reflect the increased total, within +/- 2% of the expected value? [+5] 4.7. If the monthly No. of Deals value for April 2024 in the summary section (row 49) on the 2. Mobile tab is changed from 0 to 100, does the annual No. of Deals Sum figure for 2024 on the 2. Mobile tab update to include the new value, within +/- 2% of the expected value? [+5] Section 5: Presentation 5.1. Are the annual data cells in the new section on the Mobile tab formatted with comma separators and parentheses for negatives tab? [+2] 5.2. Are total and subtotal rows in the new annual section on the Mobile tab visually distinguished with bold font and light gray fill color tab? [+2] 5.3. Do formula-driven annual values on the Mobile tab use green font while the hardcoded aggregation-type indicator labels use blue font tab? [+2] Section 6: Pitfalls 6.1. Are there any error values in the 2. Mobile tab, the 3. Logistics & Mapping tab, the 4. Robotics & Automation tab, and the 5. Other tab (#REF!, #DIV/0!, #VALUE!, #NAME?, #N/A, #NUM!)? [-5] 6.2. Is any data or label text truncated due to insufficient column widths or row heights in the 2. Mobile tab, the 3. Logistics & Mapping tab, the 4. Robotics & Automation tab, and the 5. Other tab? [-3] | K22: TRUE | L22: 46162 | M22: 15 | N22: ="https://admin.tsip.ai/tasks/"&A22 -> https://admin.tsip.ai/tasks/d4097001-c960-449f-883c-5ae8ef80cc38 | O22: FALSE
A23: 9f0c3d4c-7729-40f4-a945-12de83eb9c7d | B23: 99d2a8db-318f-4435-b03f-a5a8f78c091b | C23: Jared M | D23: =concat("https://www.tsip.ai/force/",A23) -> https://www.tsip.ai/force/9f0c3d4c-7729-40f4-a945-12de83eb9c7d | E23: TRUE | F23: TRUE | G23: 46162 | H23: 5 | I23: =iferror(VLOOKUP(A23,'Decomp Rubrics'!A:B,2,false),"generating") -> Section 1: Formula Correctness 1.1. Is the annual aggregation formula on the Logistics & Mapping tab for Sum-type rows computed as the sum of monthly values falling between the year start date and year end date inclusive? [+2] 1.2. Is the annual aggregation formula on the Logistics & Mapping tab for Average-type rows computed as the average of monthly values within the year's date range, excluding zeros from the average? [+3] 1.3. Is the annual aggregation formula on the Logistics & Mapping tab for EOP-type rows computed as the sum of monthly values where the date exactly equals the year end date? [+2] 1.4. Does the triple-nested IF in the annual aggregation formula on the Logistics & Mapping tab return the text 'error - no logic' when the row's type label matches none of Average, Sum, or EOP? [+1] 1.5. Is the annual aggregation formula on the Logistics & Mapping tab wrapped in an IFERROR that returns zero if the inner formula errors? [+1] 1.6. Are the start-of-year dates on the Logistics & Mapping tab for 2024 through 2029 derived by adding one year to the prior column's start date rather than being hardcoded? [+2] 1.7. Are the end-of-year dates on the Logistics & Mapping tab for 2024 through 2029 derived by adding one year to the prior column's end date rather than being hardcoded? [+2] 1.8. Is the first annual column's start date on the Logistics & Mapping tab hardcoded as January 1, 2023, and its end date hardcoded as December 31, 2023? [+1] 1.9. Is the year label row on the Logistics & Mapping tab for each annual column derived from the year of the end-of-year date in that column? [+1] 1.10. Is the Backlog metric in the product-level cohort waterfall sections on the Logistics & Mapping tab assigned the EOP aggregation type? [+2] 1.11. Is the ASP metric on the Logistics & Mapping tab assigned the Average aggregation type so its annual values are computed as averages rather than sums? [+1] 1.12. Are non-anchor rows within each metric block on the Logistics & Mapping tab inheriting their aggregation type by referencing the anchor row's type cell rather than being independently hardcoded? [+2] 1.13. Is the Backlog metric in the top summary section on the Logistics & Mapping tab assigned the Sum aggregation type, distinct from the EOP type used in the cohort waterfall? [+2] 1.14. Does the annual aggregation formula on the Logistics & Mapping tab use absolute row references for the date header row and type label rows so they remain fixed as the formula is copied across metric rows? [+2] Section 3: Output Validation 3.1. Is the No. of Deals annual total for 2029 (column X) on the '3. Logistics & Mapping' tab within +/- 2% of 30? [+5] 3.2. Is the Units annual sum for 2023 on the '3. Logistics & Mapping' tab summary section within +/- 2% of 5700? [+3] 3.3. Is the Bookings annual sum for 2029 on the '3. Logistics & Mapping' tab summary section within +/- 2% of 1130400? [+5] 3.4. Is the Revenue annual sum for 2023 on the '3. Logistics & Mapping' tab summary section within +/- 2% of 59800? [+3] 3.5. Is the Gross Margin annual sum for 2029 on the '3. Logistics & Mapping' tab summary section within +/- 2% of 734760? [+5] 3.6. Is the ASP annual average for 2023 on the '3. Logistics & Mapping' tab summary section within +/- 2% of 14.04? [+4] 3.7. Is the Units annual sum for 2029 on the '3. Logistics & Mapping' tab summary section within +/- 2% of 141000? [+5] 3.8. Is the Billings annual sum for 2029 on the '3. Logistics & Mapping' tab summary section within +/- 2% of 1130400? [+5] 3.9. Is the Bookings annual sum for 2023 on the '3. Logistics & Mapping' tab summary section within +/- 2% of 79900? [+4] Section 4: Perturbation 4.1. If the start-of-year date for 2023 on the 3. Logistics & Mapping tab (row 3, first annual column) is changed from January 1, 2023 to July 1, 2023, does the 2023 annual No. of Deals (Sum) row in the top summary section on the 3. Logistics & Mapping tab update to reflect only the second half of 2023 data, within +/- 2% of the expected value? [+5] 4.3. If the aggregation type label in the type-label column on the 3. Logistics & Mapping tab for the Bookings summary row is changed from Sum to Average, does the 2025 annual Bookings value on the 3. Logistics & Mapping tab update to an averaged value (rather than summed) that is within +/- 2% of the expected value? [+5] 4.4. If the aggregation type label for the ASP metric anchor row on the 3. Logistics & Mapping tab is changed from Average to Sum, does the 2025 annual ASP value on the 3. Logistics & Mapping tab switch from an average calculation to a sum calculation, updating to within +/- 2% of the expected value? [+5] 4.5. If the aggregation type label for the Backlog product-level row on the 3. Logistics & Mapping tab is changed from EOP to Sum, does the 2025 annual Backlog value on the 3. Logistics & Mapping tab switch from an end-of-period lookup to a full-year sum, updating to within +/- 2% of the expected value? [+5] 4.6. If the Average type-label reference text in the type-label row on the 3. Logistics & Mapping tab (used as the lookup key for AVERAGEIFS logic) is changed from Average to XYZZY, does the 2025 annual Units per Deal value on the 3. Logistics & Mapping tab for the Aurora section return 0 (since no type matches), within +/- 2% of 0? [+5] Section 5: Presentation 5.1. Are the annual aggregation columns on the Logistics & Mapping tab formatted with comma separators and two decimal places for numeric values tab? [+2] 5.2. Are total and subtotal rows in the annual columns on the Logistics & Mapping tab visually distinguished with bold font and light gray fill color on sibling segment tabs? [+2] 5.3. Do formula-driven cells in the new annual aggregation block on the Logistics & Mapping tab use green font on the Robotics & Automation and Other tabs? [+2] Section 6: Pitfalls 6.1. Are there any error values in the 2. Mobile tab, the 3. Logistics & Mapping tab, the 4. Robotics & Automation tab, and the 5. Other tab (#REF!, #DIV/0!, #VALUE!, #NAME?, #N/A, #NUM!)? [-5] 6.2. Is any data or label text truncated due to insufficient column widths or row heights in the 2. Mobile tab, the 3. Logistics & Mapping tab, the 4. Robotics & Automation tab, and the 5. Other tab? [-3] | K23: TRUE | L23: 46162 | M23: 10 | N23: ="https://admin.tsip.ai/tasks/"&A23 -> https://admin.tsip.ai/tasks/9f0c3d4c-7729-40f4-a945-12de83eb9c7d | O23: FALSE
A24: 9451a181-4b36-4410-92ad-7ae329eb3099 | B24: 99d2a8db-318f-4435-b03f-a5a8f78c091b | C24: Jared M | D24: =concat("https://www.tsip.ai/force/",A24) -> https://www.tsip.ai/force/9451a181-4b36-4410-92ad-7ae329eb3099 | E24: TRUE | F24: TRUE | G24: 46162 | H24: 15 | I24: =iferror(VLOOKUP(A24,'Decomp Rubrics'!A:B,2,false),"generating") -> Section 1: Formula Correctness 1.1. Is the three-way conditional aggregation formula on the Robotics & Automation tab correctly branching to compute an average (excluding zeros) when the row's aggregation type is Average? [+3] 1.2. Is the three-way conditional aggregation formula on the Robotics & Automation tab correctly branching to compute a sum of monthly values within the year range when the row's aggregation type is Sum? [+3] 1.3. Is the EOP branch of the conditional aggregation formula on the Robotics & Automation tab correctly selecting only the single month matching the year-end date rather than summing the full year? [+3] 1.4. Does the aggregation formula on the Robotics & Automation tab return zero instead of an error when no monthly data matches the date criteria, using an error-trapping wrapper? [+2] 1.5. Is the Bookings metric in the Robotics & Automation summary section assigned the Sum aggregation type so that annual columns sum monthly bookings values? [+1] 1.6. Is the Revenue metric in the Robotics & Automation summary section assigned the Sum aggregation type so that annual columns sum monthly revenue values? [+1] 1.7. Is the Units metric for the Aurora RTK product row in the Robotics & Automation summary section assigned the Average aggregation type, distinct from other product rows which use Sum? [+2] 1.8. Do subsequent product rows and the All subtotal row within each metric group on the Robotics & Automation tab inherit the aggregation type from the first product row in that group via a reference formula? [+2] 1.9. Is the Average header row on the Robotics & Automation tab correctly populated with start-of-year dates beginning at 2023-01-01 and stepping forward by exactly one year per column through 2029? [+1] 1.10. Is the Sum header row on the Robotics & Automation tab correctly populated with end-of-year dates beginning at 2023-12-31 and stepping forward by exactly one year per column through 2029? [+1] 1.11. Is the year display row on the Robotics & Automation tab derived from the Sum header row dates by extracting the four-digit year, not hardcoded? [+1] 1.12. Are the ASP waterfall deal entry rows in the Aurora RTK detail section on the Robotics & Automation tab assigned the Average aggregation type so annual values represent averages excluding zeros? [+2] 1.13. Is the entire annual aggregate section on the Logistics and Mapping tab cleared of all aggregation type labels, date headers, year display values, and annual period formulas? [+2] 1.14. Does the boundary marker row at the bottom of the Robotics & Automation summary section contain the placeholder value x in the aggregation type and each annual period column? [+1] Section 3: Output Validation 3.1. Is the Bookings All row for 2029 on the 4. Robotics & Automation tab within +/- 2% of 17640000? [+5] 3.2. Is the Revenue Aurora RTK row for 2027 on the 4. Robotics & Automation tab within +/- 2% of 10290000? [+5] 3.3. Is the Backlog All row for 2028 on the 4. Robotics & Automation tab within +/- 2% of 4410000? [+5] 3.4. Is the Units Aurora RTK summary row for 2026 on the 4. Robotics & Automation tab within +/- 2% of 1225? [+4] 3.5. Is the Revenue All row for 2025 on the 4. Robotics & Automation tab within +/- 2% of 4116000? [+4] 3.6. Are all annual aggregate columns (2023 through 2029) in the Bookings Aurora RTK summary row on the 3. Logistics & Mapping tab cleared to empty or zero? [+5] 3.7. Is the year display row on the 3. Logistics & Mapping tab cleared such that the 2023 through 2029 year labels in columns R through X are removed? [+3] 3.8. Is the Billings All row for 2029 on the 4. Robotics & Automation tab within +/- 2% of 17640000? [+5] 3.9. Is the No. of Deals Aurora RTK summary row for 2025 on the 4. Robotics & Automation tab within +/- 2% of 4? [+3] 3.10. Is the ASP waterfall rollup row for 2028 on the 4. Robotics & Automation tab within +/- 2% of 1400? [+5] Section 4: Perturbation 4.1. If the hardcoded end-of-year date anchor (2023-12-31) on the 4. Robotics & Automation tab in the Sum header row for the first annual period is changed from 2023-12-31 to 2024-12-31, does the Year display row value for the first annual period on the 4. Robotics & Automation tab update to within +/- 2% of 2024 (within +/- 0.5)? [+5] 4.2. If the hardcoded start-of-year date anchor (2023-01-01) on the 4. Robotics & Automation tab in the Average header row for the first annual period is changed from 2023-01-01 to 2024-01-01, does the second annual period start date on the 4. Robotics & Automation tab in the Average header row update to within +/- 2% of 2025-01-01 (represented as the serial date value within +/- 2%)? [+5] 4.3. If the hardcoded end-of-year date anchor (2023-12-31) on the 4. Robotics & Automation tab in the Sum header row for the first annual period is changed from 2023-12-31 to 2024-12-31, does the Year display row value for the last annual period (7th period) on the 4. Robotics & Automation tab update to within +/- 2% of 2030 (within +/- 0.5)? [+5] 4.4. If the hardcoded end-of-year date anchor (2023-12-31) on the 4. Robotics & Automation tab in the Sum header row for the first annual period is changed from 2023-12-31 to 2024-12-31, does the Bookings summary Aurora RTK row annual value for the first period on the 4. Robotics & Automation tab update correctly to reflect only months in the shifted 2024-01-01 to 2024-12-31 window (expected value within +/- 2% of the recalculated sum)? [+5] 4.5. If the hardcoded start-of-year date anchor (2023-01-01) on the 4. Robotics & Automation tab in the Average header row for the first annual period is changed from 2023-01-01 to 2025-01-01, does the third annual period start date on the 4. Robotics & Automation tab in the Average header row update to within +/- 2% of 2027-01-01 (represented as the serial date value within +/- 2%)? [+5] 4.6. If the hardcoded end-of-year date anchor (2023-12-31) on the 4. Robotics & Automation tab in the Sum header row for the first annual period is changed from 2023-12-31 to 2025-12-31, does the second annual period end-of-year date on the 4. Robotics & Automation tab in the Sum header row update to within +/- 2% of 2026-12-31 (represented as the serial date value within +/- 2%)? [+5] 4.7. If the hardcoded Bookings aggregation type label on the 4. Robotics & Automation tab (currently set to Sum for the first Bookings product row) is changed from Sum to Average, does the Bookings Aurora RTK annual value for 2026 on the 4. Robotics & Automation tab update to reflect an AVERAGEIFS calculation instead of SUMIFS (expected to be significantly lower than the sum, within +/- 2% of the monthly average for that year)? [+5] Section 5: Presentation 5.1. Are formula-driven values in the annual aggregate section of the Robotics and Automation tab displayed in green font used across the other segment tabs? [+2] 5.2. Are subtotal and rollup rows in the Robotics and Automation tab's annual aggregate section styled with bold font and light gray fill? [+2] 5.3. Do all numeric cells in the annual aggregate columns on the Robotics and Automation tab use comma-separated number formats with two decimal places, consistent with the monthly detail columns? [+2] Section 6: Pitfalls 6.1. Are there any error values in the 2. Mobile tab, the 3. Logistics & Mapping tab, the 4. Robotics & Automation tab, and the 5. Other tab (#REF!, #DIV/0!, #VALUE!, #NAME?, #N/A, #NUM!)? [-5] 6.2. Is any data or label text truncated due to insufficient column widths or row heights in the 2. Mobile tab, the 3. Logistics & Mapping tab, the 4. Robotics & Automation tab, and the 5. Other tab? [-3] | K24: TRUE | L24: 46162 | M24: 30 | N24: ="https://admin.tsip.ai/tasks/"&A24 -> https://admin.tsip.ai/tasks/9451a181-4b36-4410-92ad-7ae329eb3099 | O24: FALSE
A25: d3c49dda-ea40-44f5-aac4-7e128754a6dd | B25: 13a79273-28e7-4a18-a4e0-3bc96b121206 | C25: Jared M | D25: =concat("https://www.tsip.ai/force/",A25) -> https://www.tsip.ai/force/d3c49dda-ea40-44f5-aac4-7e128754a6dd | E25: TRUE | F25: TRUE | G25: 46162 | H25: 15 | I25: =iferror(VLOOKUP(A25,'Decomp Rubrics'!A:B,2,false),"generating") -> Section 1: Formula Correctness 1.1. Is the Auto OEM 001 Totals Ending Backlog row on the Exist Auto Program Detail sheet computed as the sum of Ending Backlog from all four sub-programs period by period? [+2] 1.2. Is the Auto OEM 001 Totals Ending ARR row on the Exist Auto Program Detail sheet computed as the sum of Ending ARR from all four sub-programs period by period? [+2] 1.3. Is the Auto OEM 001 Totals Bookings row on the Exist Auto Program Detail sheet computed as the sum of all individual booking lines including renewal bookings across all four sub-programs? [+2] 1.4. Is the Auto OEM 001 Totals Revenue row on the Exist Auto Program Detail sheet computed as the sum of all revenue lines across all four sub-programs? [+1] 1.5. Is the Auto OEM 002 Totals Ending Backlog row on the Exist Auto Program Detail sheet computed as the sum of Ending Backlog from the Initial and Expansion sub-programs? [+1] 1.6. Is the Auto OEM 004 Totals Bookings row on the Exist Auto Program Detail sheet computed as the sum of all booking lines across the three VW sub-programs? [+2] 1.7. Is the Auto OEM 004 Totals Cash row on the Exist Auto Program Detail sheet computed as the sum of the Cash lines from the three VW sub-programs? [+2] 1.8. Is the Auto OEM 003 Totals Ending Backlog row on the Exist Auto Program Detail sheet computed as the sum of Ending Backlog from the Initial Program, Expansion Program, and Atlas Product 004 sub-programs? [+2] 1.9. Is the Total Pipeline row on the 2024-2028 Revenue Pipeline summary computed as the sum of Auto Pipeline Revenue and Total Industrial Pipeline Revenue for each year? [+2] 1.10. Is the Robotics and Automation row on the 2024-2028 Revenue Pipeline summary computed as the sum of all six robotics subsegment totals rows? [+2] 1.11. Is the Total Logistics and Mapping row on the 2024-2025 Qtrly Indus Pipeline sheet computed as the sum of Total Fleet Management, Total Surveying And Mapping, and Total Asset Tracking? [+2] 1.12. Is the Total Robotics and Automation row on the 2024-2025 Qtrly Indus Pipeline sheet computed as the sum of the six robotics sub-totals? [+2] 1.13. Is the FY 2024 annual total column on the 2024-2025 Qtrly Indus Pipeline sheet computed as the sum of Q1 through Q4 2024 for each detail and totals row? [+2] 1.14. Is the Pipeline Segment Summary grand total row on the 2024-2025 Qtrly Indus Pipeline sheet computed as the sum of the Mobile, Logistics and Mapping, Robotics and Automation, and Other vertical rows? [+2] 1.15. Is the grand total row at the bottom of the Revenue Forecast section on the 2024-2025 Qtrly Indus Pipeline sheet computed as the sum of Mobile, Logistics and Mapping, Robotics and Automation, and Other forecast rows? [+1] Section 3: Output Validation 3.1. Is the Auto OEM 001 Totals Revenue row for 2031-2040 on the Exist Auto Program Detail sheet within +/- 2% of 432000000? [+5] 3.2. Is the Auto OEM 004 Totals Ending Backlog for 2026 on the Exist Auto Program Detail sheet within +/- 2% of 193200000? [+5] 3.3. Is the Auto OEM 003 Totals Bookings for 2025 on the Exist Auto Program Detail sheet within +/- 2% of 4200000? [+4] 3.4. Is the Auto OEM 002 (Tier1 A) Totals Ending ARR for 2028 on the Exist Auto Program Detail sheet within +/- 2% of 19200000? [+5] 3.5. Is the Total Pipeline Revenue for 2028 (Total column V) on the 2024-2028 Revenue Pipeline sheet within +/- 2% of 28565000? [+5] 3.6. Is the Total Industrial Pipeline Revenue for 2026 on the 2024-2028 Revenue Pipeline sheet within +/- 2% of 7498000? [+5] 3.7. Is the Robotics and Automation summary row for 2025 on the 2024-2028 Revenue Pipeline sheet within +/- 2% of 1498000? [+4] 3.8. Is the grand total Revenue Forecast row for FY 2024 on the 2024-2025 Qtrly Indus Pipeline sheet within +/- 2% of 3498000? [+5] 3.9. Is the Total Robotics and Automation pipeline row for Q4 2024 on the 2024-2025 Qtrly Indus Pipeline sheet within +/- 2% of 247000? [+4] 3.10. Is the Auto OEM 004 Totals Cash row for 2027 on the Exist Auto Program Detail sheet within +/- 2% of 28800000? [+3] Section 4: Perturbation 4.1. If the Auto OEM 001 Atlas Product 001 vehicle production value for 2024 on the Exist Auto Program Detail tab is changed from 4,200,000 to 8,400,000, does the Auto OEM 001 Totals Ending ARR for 2024 update to within +/- 2% of the correctly recomputed value? [+5] 4.2. If the Auto OEM 001 Region vehicle production value for 2024 on the Exist Auto Program Detail tab is changed from 3,500,000 to 7,000,000, does the Auto OEM 001 Totals Revenue for 2024 update to within +/- 2% of the correctly recomputed value? [+5] 4.3. If the Auto OEM 004 1.1/1.2 Architecture ending backlog value for the Total column on the Exist Auto Program Detail tab is changed from 28,172,000 to 56,344,000, does the Auto OEM 004 Totals Ending Backlog Total column update to within +/- 2% of the correctly recomputed value? [+5] 4.4. If the Mobile subsegment Trimble Marine revenue value for Q3 2024 on the 2024-2025 Qtrly Indus Pipeline tab is changed from its current value to double that amount, does the Pipeline Segment Summary grand total row for FY 2024 update to within +/- 2% of the correctly recomputed value? [+5] 4.5. If the Auto OEM 003 Initial Program ending ARR value for 2025 on the Exist Auto Program Detail tab is changed from 300,000 to 900,000, does the Auto OEM 003 Totals Ending ARR for 2025 update to within +/- 2% of the correctly recomputed value? [+5] 4.6. If the Auto OEM 002 Expansion Program vehicle production value for 2027 on the Exist Auto Program Detail tab is changed from 40,000 to 120,000, does the Auto OEM 002 (Tier1 A) Totals Ending ARR for 2027 update to within +/- 2% of the correctly recomputed value? [+5] 4.7. If the Robotics and Automation subsegment Commercial RLM account revenue for Q3 2024 on the 2024-2025 Qtrly Indus Pipeline tab is changed from its current value to triple that amount, does the Total Robotics and Automation row for FY 2024 update to within +/- 2% of the correctly recomputed value? [+5] Section 5: Presentation 5.1. Are hardcoded values displayed in blue font and formula-driven values in black font across all new totals blocks on the Exist Auto Program Detail, 2024-2028 Revenue Pipeline, and 2024-2025 Qtrly Indus Pipeline sheets? [+2] 5.2. Are the new OEM totals blocks on the Exist Auto Program Detail sheet formatted with yellow fill and bold text, matching the existing Auto OEM 006 Totals block pattern? [+2] 5.3. Are all currency values in the newly added rows formatted with a dollar sign prefix, comma separators, and no decimal places? [+2] Section 6: Pitfalls 6.1. Are there any error values in the Exist Auto Program Detail tab, the 2024-2028 Revenue Pipeline tab, and the 2024-2025 Qtrly Indus Pipeline tab (#REF!, #DIV/0!, #VALUE!, #NAME?, #N/A, #NUM!)? [-5] 6.2. Is any data or label text truncated due to insufficient column widths or row heights in the Exist Auto Program Detail tab, the 2024-2028 Revenue Pipeline tab, and the 2024-2025 Qtrly Indus Pipeline tab? [-3] | K25: TRUE | L25: 46162 | M25: 45 | N25: ="https://admin.tsip.ai/tasks/"&A25 -> https://admin.tsip.ai/tasks/d3c49dda-ea40-44f5-aac4-7e128754a6dd | O25: FALSE
A26: 00c07d57-1124-49c2-b354-6df05adc7a7f | B26: 0294871c-c0a6-404e-ac74-d957f673aa5b | C26: Jared M | D26: =concat("https://www.tsip.ai/force/",A26) -> https://www.tsip.ai/force/00c07d57-1124-49c2-b354-6df05adc7a7f | E26: TRUE | F26: FALSE | G26: 46162 | H26: 50 | I26: =iferror(VLOOKUP(A26,'Decomp Rubrics'!A:B,2,false),"generating") -> Section 1: Formula Correctness 1.1. Is Total Attributed CAC on the Unit Economics tab expressed as a negative value (hardcoded amounts divided by FX_ with a negative sign) for all projected quarters? [+2] 1.2. Is Global ARR on the Unit Economics tab computed as the sum of all MRR from the MRR calculation tab, multiplied by 12, divided by 1,000,000, and divided by FX_? [+2] 1.3. Is Regional ARR on the Unit Economics tab computed using a conditional sum on the region column of the MRR calculation tab, multiplied by 12, divided by 1,000,000, and divided by FX_? [+2] 1.4. Is the FY column for Absolute ARR Growth on the Unit Economics tab calculated as the sum of the four quarterly values within that year? [+1] 1.5. Is NDR-driven ARR growth on the Unit Economics tab derived as total absolute ARR growth minus new business ARR growth? [+2] 1.6. Is Organic NDR on the Unit Economics tab computed as NDR-driven ARR growth minus account expansion for each quarter? [+1] 1.7. Is Net New ARR from Regular Operations on the Unit Economics tab calculated as total new business ARR minus enterprise deal ARR? [+1] 1.8. Is Total Sales Result on the Unit Economics tab computed as the sum of new business bookings, enterprise MRR bookings, and AM net growth bookings, with FY columns summing the four quarters? [+2] 1.9. Is CAC Payback on the Unit Economics tab calculated as the absolute value of CAC divided by the product of total sales result and gross margin percentage? [+2] 1.10. Is Absolute Cash Burn on the Unit Economics tab derived as monthly average cash burn multiplied by three and divided by one million? [+1] 1.11. Is the Quarterly Burn Multiple on the Unit Economics tab computed as negative monthly burn times three divided by the quantity of current ARR minus 14.48/FX_ times one million? [+2] 1.12. Is Runway on the Unit Economics tab calculated as bank balance in millions divided by the absolute value of monthly burn in millions, showing a dash text when monthly burn is positive? [+3] 1.13. Is Rule of 40 on the Unit Economics tab calculated as the YoY ARR growth rate plus the gross margin percentage from the P&L tab for each projected quarter? [+1] 1.14. Is ARR per FTE on the Unit Economics tab derived as global ARR divided by FTE count, scaled back up by multiplying by one million? [+1] 1.15. Is NNARR per S&M FTE on the Unit Economics tab computed as the sum of NDR-driven and new business ARR growth times one million divided by the sum of the two S&M headcount rows? [+2] Section 2: Model Integration 2.1. Is the EMEA ARR on the I. Unit Economics tab linked to the MRR by region on the 5. MRR calculation tab? [+5] 2.2. Is the Additional financing on the III. Cash tab linked to the Additional financing on the I. Unit Economics tab? [+5] 2.3. Is the NDR rate on the I. Unit Economics tab linked to the NDR rate on the 3.2. NDR 26-28 tab? [+4] 2.4. Is the Enterprise deal ARR on the I. Unit Economics tab linked to the Enterprise MRR bookings on the 4. Enterprise motion tab? [+4] 2.5. Is the Rule of 40 on the I. Unit Economics tab linked to the Gross margin percentage on the II. P&L tab? [+4] 2.6. Is the New business bookings MRR on the I. Unit Economics tab linked to the New Business bookings on the 2. New Business tab? [+4] 2.7. Is the period code on the I. Unit Economics tab linked to the quarter-to-code mapping on the mappings tab? [+3] 2.8. Is the SQL generation on the I. Unit Economics tab linked to the SQL generation on the 1. Pipeline generation tab? [+3] 2.9. Is the number of Customers on the I. Unit Economics tab linked to the Total number of customers on the 6. Other Sales functions tab? [+3] 2.10. Is the FTE count on the I. Unit Economics tab linked to the Total FTEs on the 8. R&D and G&A Overheads tab? [+3] Section 3: Output Validation 3.1. Is the Global ARR on the 'I. Unit Economics' tab for 2028 Q4 within +/- 2% of 109.62? [+5] 3.2. Is the Global ARR on the 'I. Unit Economics' tab for 2025 Q2 within +/- 2% of 36.72? [+4] 3.3. Is the FY Absolute ARR Growth on the 'I. Unit Economics' tab for 2023 FY within +/- 2% of 5.76? [+3] 3.4. Is the FY Absolute ARR Growth on the 'I. Unit Economics' tab for 2026 FY within +/- 2% of 17.49? [+4] 3.5. Is the Total Attributed CAC on the 'I. Unit Economics' tab for 2024 Q3 within +/- 2% of -2.85? [+4] 3.6. Is the NDR Rate on the 'I. Unit Economics' tab for 2025 Q1 within +/- 0.5 pp of 102.9%? [+3] 3.7. Is the Rule of 40 on the 'I. Unit Economics' tab for 2028 FY within +/- 0.5 pp of 123.0%? [+5] 3.8. Is the FY Absolute ARR Growth on the 'I. Unit Economics' tab for 2028 FY within +/- 2% of 25.51? [+5] 3.9. Does the 'III. Cash' tab row 27 for 2027 Q1 contain a formula linking to the 'I. Unit Economics' additional financing row, resulting in a value of 0? [+5] Section 4: Perturbation 4.1. If the SQL generation count on the Pipeline generation tab for 2024 Q1 is changed from 213 to 426, does the SQL generation metric on the Unit Economics tab for 2024 Q1 update to within +/- 2% of 426 (within +/- 2%)? [+5] 4.2. If the SQL generation count on the Pipeline generation tab for 2025 Q1 is changed from approximately 290 to 580, does the SQL generation metric on the Unit Economics tab for 2025 Q1 update to within +/- 2% of 580 (within +/- 2%)? [+5] 4.3. If the SQL generation count on the Pipeline generation tab for 2026 Q1 is changed from approximately 377.85 to 755.70, does the SQL generation metric on the Unit Economics tab for 2026 Q1 update to within +/- 2% of 755.70 (within +/- 2%)? [+5] 4.4. If the SQL generation count on the Pipeline generation tab for 2024 Q2 is changed from 182 to 364, does the SQL generation metric on the Unit Economics tab for 2024 Q2 update to within +/- 2% of 364 (within +/- 2%)? [+5] 4.5. If the SQL generation count on the Pipeline generation tab for 2024 Q3 is changed from 258 to 516, does the SQL generation metric on the Unit Economics tab for 2024 Q3 update to within +/- 2% of 516 (within +/- 2%)? [+5] 4.6. If the SQL generation count on the Pipeline generation tab for 2026 Q2 is changed from approximately 383.35 to 766.70, does the SQL generation metric on the Unit Economics tab for 2026 Q2 update to within +/- 2% of 766.70 (within +/- 2%)? [+5] Section 5: Presentation 5.1. Are all percentage values on the I. Unit Economics tab (YoY growth, QoQ growth, NDR, regional splits, Rule of 40) formatted as percentages with zero decimal places? [+2] 5.2. Are all non-empty numeric values in the ARR and growth sections of the I. Unit Economics tab formatted with comma thousands separators and one decimal place conventions? [+2] 5.3. Are summary and total rows on the I. Unit Economics tab (e.g., Global ARR, total new business, total sales result) visually distinguished with bold font's existing styling? [+2] Section 6: Pitfalls 6.1. Are there any error values in the I. Unit Economics tab and the III. Cash tab (#REF!, #DIV/0!, #VALUE!, #NAME?, #N/A, #NUM!)? [-5] 6.2. Is any data or label text truncated due to insufficient column widths or row heights in the I. Unit Economics tab and the III. Cash tab? [-3] | K26: FALSE | N26: ="https://admin.tsip.ai/tasks/"&A26 -> https://admin.tsip.ai/tasks/00c07d57-1124-49c2-b354-6df05adc7a7f | O26: FALSE | P26: 5/17 Claim Sheet Rollover
A27: 3a1f76de-2e68-4036-aa3d-d325bb2ea100 | B27: 0294871c-c0a6-404e-ac74-d957f673aa5b | C27: Jared M | D27: =concat("https://www.tsip.ai/force/",A27) -> https://www.tsip.ai/force/3a1f76de-2e68-4036-aa3d-d325bb2ea100 | E27: TRUE | F27: TRUE | G27: 46160 | H27: 45 | I27: =iferror(VLOOKUP(A27,'Decomp Rubrics'!A:B,2,false),"generating") -> generating | K27: TRUE | L27: 46163 | M27: 20 | N27: ="https://admin.tsip.ai/tasks/"&A27 -> https://admin.tsip.ai/tasks/3a1f76de-2e68-4036-aa3d-d325bb2ea100 | O27: FALSE | P27: needs rubric regen 5/17 Claim Sheet Rollover
A28: 76dfed95-97aa-4610-be20-44beb1d5ab35 | B28: 0294871c-c0a6-404e-ac74-d957f673aa5b | C28: Jalaj G | D28: =concat("https://www.tsip.ai/force/",A28) -> https://www.tsip.ai/force/76dfed95-97aa-4610-be20-44beb1d5ab35 | E28: FALSE | F28: FALSE | G28: 46159 | H28: 55 | I28: =iferror(VLOOKUP(A28,'Decomp Rubrics'!A:B,2,false),"generating") -> Section 1: Formula Correctness 1.1. Is the high value customer ending stock on the Other Sales Functions sheet computed as prior period stock minus the product of prior year same-quarter stock and annual churn rate, plus new high value customers? [+3] 1.2. Is the medium value customer ending stock computed as prior period stock minus churn on prior year same-quarter stock, plus total new customers minus new high value customers for that period? [+3] 1.3. Is the low value customer ending stock computed as the prior year same-quarter stock multiplied by one minus the annual churn rate, with no new customer additions in the projected period? [+2] 1.4. Is the CS Success FTE needed per region computed as the maximum of high value customers divided by 15 and medium value customers divided by 60, each rounded up to zero decimals? [+3] 1.5. Is the AVG TOTAL BDR to AE ratio on the Other Sales Functions sheet computed as the simple average of the four regional BDR to AE ratio rows for each quarterly column? [+1] 1.6. Is the per-region productive BDR FTE computed as the region's fully ramped AE headcount divided by that region's BDR to AE ratio, rounded to zero decimals? [+1] 1.7. Is BDR FTEs needed per region on the Sales Overhead sheet computed as the region's productive BDR FTE plus the non-quota carriers total multiplied by that region's share of total productive BDR FTE? [+2] 1.8. Is BDR payroll cost per region computed as headcount on payroll times monthly base OTE times three times the cumulative salary inflation factor, times one plus the payroll tax rate, plus three times the monthly benefit amount? [+2] 1.9. Is BDR management headcount per region computed as headcount on payroll divided by the management ratio, rounded to zero decimals, defaulting to zero when the ratio produces an error? [+2] 1.10. Is total BDR payroll cost per region on the Sales Overhead sheet computed as the sum of direct BDR payroll cost and BDR management payroll cost? [+1] 1.11. Are the EMEA AEs on payroll correctly split between Budapest and London using the hardcoded BUD percentage share and one minus that share for London, respectively? [+2] 1.12. Is the APAC GM cost on the Sales Overhead sheet computed as 300,000 divided by 4 per quarter, scaled by the cumulative salary inflation factor for the corresponding year? [+1] 1.13. Is the OPEX cost per role on the Sales Overhead sheet computed as headcount on payroll multiplied by the per-FTE quarterly OPEX rate looked up from the OPEX assumptions table? [+1] 1.14. Is total cost per region and function on the Sales Overhead sheet computed as the sum of payroll cost and OPEX cost for that region and function? [+1] 1.15. Does the customer segment ratio check row on the Other Sales Functions sheet confirm that the high value, medium value, and low value ratios sum to exactly one for each column? [+1] Section 2: Model Integration 2.1. Is the productive BDR FTE on the 6. Other Sales functions tab linked to the fully ramped AE headcount on the 2. New Business tab? [+5] 2.2. Is the AM FTEs needed on the 7. Sales Overhead calculation tab linked to the AM FTE needed on the 3.2. NDR 26-28 tab? [+4] 2.3. Is the AE FTEs needed on the 7. Sales Overhead calculation tab linked to the fully ramped AE headcount on the 2. New Business tab? [+4] 2.4. Is the CS FTEs needed on the 7. Sales Overhead calculation tab linked to the CS Success FTE headcount needed on the 6. Other Sales functions tab? [+3] 2.5. Is the Enterprise AE payroll cost on the 7. Sales Overhead calculation tab linked to the Enterprise AE headcount on the 4. Enterprise motion tab? [+3] 2.6. Is the AE payroll cost on the 7. Sales Overhead calculation tab linked to the cumulative salary inflation factor on the 2. New Business tab? [+3] 2.7. Is the SE FTEs needed on the 7. Sales Overhead calculation tab linked to the productive SE FTE on the 6. Other Sales functions tab? [+3] 2.8. Is the AM payroll cost on the 7. Sales Overhead calculation tab linked to the AM OTE on the 3.2. NDR 26-28 tab? [+3] 2.9. Is the Enterprise AE FTEs needed on the 7. Sales Overhead calculation tab linked to the Enterprise AE headcount on the 4. Enterprise motion tab? [+3] Section 3: Output Validation 3.1. Is the TOTAL productive BDR FTE on the '6. Other Sales functions' sheet for Q4 2028 within +/- 2% of 10? [+3] 3.2. Is the TOTAL customers row on the '6. Other Sales functions' sheet for Q4 2026 within +/- 2% of 709? [+4] 3.3. Is the TOTAL productive SE FTE on the '6. Other Sales functions' sheet for Q4 2028 within +/- 2% of 7? [+3] 3.4. Is the TOTAL CS Success FTE headcount needed on the '6. Other Sales functions' sheet for Q4 2027 within +/- 2% of 38? [+4] 3.5. Is the high value customer segment ratio check row on the '6. Other Sales functions' sheet equal to 1 (within +/- 0.5 pp) for Q4 2028? [+3] 3.6. Is the total BDR payroll cost (all regions combined) on the '7. Sales Overhead calculation' sheet for FY 2027 within +/- 2% of 838,929? [+5] 3.7. Is the total AE payroll cost (all regions combined) on the '7. Sales Overhead calculation' sheet for FY 2028 within +/- 2% of 2,789,484? [+5] 3.8. Is the total headcount on payroll (all roles, all regions) on the '7. Sales Overhead calculation' sheet for Q4 2028 within +/- 2% of 95? [+5] 3.9. Is the total cost (payroll plus OPEX, all regions and functions) on the '7. Sales Overhead calculation' sheet for FY 2026 within +/- 2% of 5,769,498? [+5] 3.10. Is the total OPEX cost (all roles combined) on the '7. Sales Overhead calculation' sheet for FY 2028 within +/- 2% of 1,232,200? [+5] Section 4: Perturbation 4.1. If the EMEA BDR to AE ratio on the Other Sales functions tab is changed from 2 to 4 for all projected quarters, does the TOTAL productive BDR FTE on the Other Sales functions tab for 2028 Q4 update to within +/- 2% of the expected reduced value? (Testing with the 2028 Q4 quarterly column.)? [+5] 4.2. If the EMEA SE to AE ratio on the Other Sales functions tab is changed from 3 to 6 for 2028 Q4, does the TOTAL productive SE FTE on the Other Sales functions tab for 2028 Q4 update to within +/- 2% of the expected reduced value reflecting halved EMEA SE headcount? [+5] 4.3. If the high value customer annual churn rate on the Other Sales functions tab is changed from 10% to 50%, does the TOTAL high value customers ending stock on the Other Sales functions tab for 2028 Q4 update to within +/- 2% of the expected significantly reduced value? [+5] 4.4. If the high value customers per CS Success FTE capacity ratio on the Other Sales functions tab is changed from 15 to 5, does the TOTAL CS Success FTE headcount needed on the Other Sales functions tab for 2028 Q4 update to within +/- 2% of the expected tripled value? [+5] 4.5. If the APAC GM annual cost on the Sales Overhead calculation tab is changed from 300000 to 600000, does the TOTAL management and central functions cost on the Sales Overhead calculation tab for 2028 Q4 update to within +/- 2% of the expected value reflecting the doubled APAC GM cost? [+5] 4.6. If the BDR quarterly OPEX per FTE on the Sales Overhead calculation tab is changed from 4250 to 8500, does the TOTAL OPEX cost for BDRs on the Sales Overhead calculation tab for FY 2028 update to within +/- 2% of the expected doubled BDR OPEX value? [+5] 4.7. If the medium value customer annual churn rate on the Other Sales functions tab is changed from 15% to 50%, does the TOTAL medium value customers ending stock on the Other Sales functions tab for 2028 Q4 update to within +/- 2% of the expected significantly reduced value? [+5] Section 5: Presentation 5.1. Are all numeric values on the Other Sales functions and Sales Overhead calculation sheets formatted with comma thousands separators and zero decimal places? [+2] 5.2. Are all non-empty percentage values on the Other Sales functions sheet (customer segment ratios, churn rates) formatted as percentages with zero decimal places? [+2] 5.3. Are total and subtotal rows on both changed sheets visually distinguished with bold font and light gray fill color used across other model tabs? [+2] Section 6: Pitfalls 6.1. Are there any error values in the 6. Other Sales functions tab and the 7. Sales Overhead calculation tab (#REF!, #DIV/0!, #VALUE!, #NAME?, #N/A, #NUM!)? [-5] 6.2. Is any data or label text truncated due to insufficient column widths or row heights in the 6. Other Sales functions tab and the 7. Sales Overhead calculation tab? [-3] | K28: FALSE | N28: ="https://admin.tsip.ai/tasks/"&A28 -> https://admin.tsip.ai/tasks/76dfed95-97aa-4610-be20-44beb1d5ab35 | O28: FALSE | P28: needs rubric regen 5/17 Claim Sheet Rollover
